Workbook

Sheet JOIN
A1: サブシス | B1: テーブル論理名 | C1: 決裁番号 | D1: オーダ番号 | E1: エントリ番号 | F1: 統一企業コード | G1: summit統一企業番号 | H1: s# | I1: サービスID(S#) | J1: サービスID | K1: b# | L1: 請求グループID(B#) | M1: 請求グループID | N1: c# | O1: 契約者ID(C#) | P1: 契約者ID | Q1: トランザクション番号
A2: BFSエントリ | B2: モバイル_サービスサマリ_付属品 | C2: =IFERROR(VLOOKUP(C$1, '(BFSエントリ)モバイル_サービスサマリ_付属品'!$C$9:$C$30, 1, FALSE), "") | D2: =IFERROR(VLOOKUP(D$1, '(BFSエントリ)モバイル_サービスサマリ_付属品'!$C$9:$C$30, 1, FALSE), "") | E2: =IFERROR(VLOOKUP(E$1, '(BFSエントリ)モバイル_サービスサマリ_付属品'!$C$9:$C$30, 1, FALSE), "") -> エントリ番号 | F2: =IFERROR(VLOOKUP(F$1, '(BFSエントリ)モバイル_サービスサマリ_付属品'!$C$9:$C$30, 1, FALSE), "") | G2: =IFERROR(VLOOKUP(G$1, '(BFSエントリ)モバイル_サービスサマリ_付属品'!$C$9:$C$30, 1, FALSE), "") | H2: =IFERROR(VLOOKUP(H$1, '(BFSエントリ)モバイル_サービスサマリ_付属品'!$C$9:$C$30, 1, FALSE), "") | I2: =IFERROR(VLOOKUP(I$1, '(BFSエントリ)モバイル_サービスサマリ_付属品'!$C$9:$C$30, 1, FALSE), "") | J2: =IFERROR(VLOOKUP(J$1, '(BFSエントリ)モバイル_サービスサマリ_付属品'!$C$9:$C$30, 1, FALSE), "") | ... Q2: =IFERROR(VLOOKUP(Q$1, '(BFSエントリ)モバイル_サービスサマリ_付属品'!$C$9:$C$30, 1, FALSE), "")
A3: BFSエントリ | B3: モバイル_サービスサマリ_端末 | C3: =IFERROR(VLOOKUP(C$1, '(BFSエントリ)モバイル_サービスサマリ_端末'!$C$9:$C$504, 1, FALSE),"") | D3: =IFERROR(VLOOKUP(D$1, '(BFSエントリ)モバイル_サービスサマリ_端末'!$C$9:$C$504, 1, FALSE),"") | E3: =IFERROR(VLOOKUP(E$1, '(BFSエントリ)モバイル_サービスサマリ_端末'!$C$9:$C$504, 1, FALSE),"") | F3: =IFERROR(VLOOKUP(F$1, '(BFSエントリ)モバイル_サービスサマリ_端末'!$C$9:$C$504, 1, FALSE),"") | G3: =IFERROR(VLOOKUP(G$1, '(BFSエントリ)モバイル_サービスサマリ_端末'!$C$9:$C$504, 1, FALSE),"") | H3: =IFERROR(VLOOKUP(H$1, '(BFSエントリ)モバイル_サービスサマリ_端末'!$C$9:$C$504, 1, FALSE),"") | I3: =IFERROR(VLOOKUP(I$1, '(BFSエントリ)モバイル_サービスサマリ_端末'!$C$9:$C$504, 1, FALSE),"") | J3: =IFERROR(VLOOKUP(J$1, '(BFSエントリ)モバイル_サービスサマリ_端末'!$C$9:$C$504, 1, FALSE),"") | ... Q3: =IFERROR(VLOOKUP(Q$1, '(BFSエントリ)モバイル_サービスサマリ_端末'!$C$9:$C$504, 1, FALSE),"")
A4: BFSエントリ | B4: モバイル_エントリ情報 | C4: =IFERROR(VLOOKUP(C$1, '(BFSエントリ)モバイル_エントリ情報'!$C$9:$C$224, 1, FALSE), "") | D4: =IFERROR(VLOOKUP(D$1, '(BFSエントリ)モバイル_エントリ情報'!$C$9:$C$224, 1, FALSE), "") | E4: =IFERROR(VLOOKUP(E$1, '(BFSエントリ)モバイル_エントリ情報'!$C$9:$C$224, 1, FALSE), "") -> エントリ番号 | F4: =IFERROR(VLOOKUP(F$1, '(BFSエントリ)モバイル_エントリ情報'!$C$9:$C$224, 1, FALSE), "") -> 統一企業コード | G4: =IFERROR(VLOOKUP(G$1, '(BFSエントリ)モバイル_エントリ情報'!$C$9:$C$224, 1, FALSE), "") | H4: =IFERROR(VLOOKUP(H$1, '(BFSエントリ)モバイル_エントリ情報'!$C$9:$C$224, 1, FALSE), "") | I4: =IFERROR(VLOOKUP(I$1, '(BFSエントリ)モバイル_エントリ情報'!$C$9:$C$224, 1, FALSE), "") | J4: =IFERROR(VLOOKUP(J$1, '(BFSエントリ)モバイル_エントリ情報'!$C$9:$C$224, 1, FALSE), "") | ... Q4: =IFERROR(VLOOKUP(Q$1, '(BFSエントリ)モバイル_エントリ情報'!$C$9:$C$224, 1, FALSE), "")
A5: RMS | B5: 契約基本情報 | C5: =IFERROR(VLOOKUP(C$1, '(RMS)契約基本情報'!$C$9:$C$999, 1, FALSE), "") | D5: =IFERROR(VLOOKUP(D$1, '(RMS)契約基本情報'!$C$9:$C$999, 1, FALSE), "") -> オーダ番号 | E5: =IFERROR(VLOOKUP(E$1, '(RMS)契約基本情報'!$C$9:$C$999, 1, FALSE), "") | F5: =IFERROR(VLOOKUP(F$1, '(RMS)契約基本情報'!$C$9:$C$999, 1, FALSE), "") | G5: =IFERROR(VLOOKUP(G$1, '(RMS)契約基本情報'!$C$9:$C$999, 1, FALSE), "") -> summit統一企業番号 | H5: =IFERROR(VLOOKUP(H$1, '(RMS)契約基本情報'!$C$9:$C$999, 1, FALSE), "") -> s# | I5: =IFERROR(VLOOKUP(I$1, '(RMS)契約基本情報'!$C$9:$C$999, 1, FALSE), "") | J5: =IFERROR(VLOOKUP(J$1, '(RMS)契約基本情報'!$C$9:$C$999, 1, FALSE), "") | ... Q5: =IFERROR(VLOOKUP(Q$1, '(RMS)契約基本情報'!$C$9:$C$999, 1, FALSE), "")
A6: RMS | B6: 契約料金情報 | C6: =IFERROR(VLOOKUP(C$1, '(RMS)契約料金情報'!$C$9:$C$999, 1, FALSE), "") -> 決裁番号 | D6: =IFERROR(VLOOKUP(D$1, '(RMS)契約料金情報'!$C$9:$C$999, 1, FALSE), "") -> オーダ番号 | E6: =IFERROR(VLOOKUP(E$1, '(RMS)契約料金情報'!$C$9:$C$999, 1, FALSE), "") | F6: =IFERROR(VLOOKUP(F$1, '(RMS)契約料金情報'!$C$9:$C$999, 1, FALSE), "") | G6: =IFERROR(VLOOKUP(G$1, '(RMS)契約料金情報'!$C$9:$C$999, 1, FALSE), "") | H6: =IFERROR(VLOOKUP(H$1, '(RMS)契約料金情報'!$C$9:$C$999, 1, FALSE), "") | I6: =IFERROR(VLOOKUP(I$1, '(RMS)契約料金情報'!$C$9:$C$999, 1, FALSE), "") | J6: =IFERROR(VLOOKUP(J$1, '(RMS)契約料金情報'!$C$9:$C$999, 1, FALSE), "") | ... Q6: =IFERROR(VLOOKUP(Q$1, '(RMS)契約料金情報'!$C$9:$C$999, 1, FALSE), "")
A7: COP | B7: 支払情報 | C7: =IFERROR(VLOOKUP(C$1, '(COP)支払情報'!$C$9:$C$999, 1, FALSE), "") | D7: =IFERROR(VLOOKUP(D$1, '(COP)支払情報'!$C$9:$C$999, 1, FALSE), "") | E7: =IFERROR(VLOOKUP(E$1, '(COP)支払情報'!$C$9:$C$999, 1, FALSE), "") | F7: =IFERROR(VLOOKUP(F$1, '(COP)支払情報'!$C$9:$C$999, 1, FALSE), "") | G7: =IFERROR(VLOOKUP(G$1, '(COP)支払情報'!$C$9:$C$999, 1, FALSE), "") | H7: =IFERROR(VLOOKUP(H$1, '(COP)支払情報'!$C$9:$C$999, 1, FALSE), "") | I7: =IFERROR(VLOOKUP(I$1, '(COP)支払情報'!$C$9:$C$999, 1, FALSE), "") | J7: =IFERROR(VLOOKUP(J$1, '(COP)支払情報'!$C$9:$C$999, 1, FALSE), "") | ... Q7: =IFERROR(VLOOKUP(Q$1, '(COP)支払情報'!$C$9:$C$999, 1, FALSE), "")
A8: COP | B8: 契約者リンク履歴 | C8: =IFERROR(VLOOKUP(C$1, '(COP)契約者リンク履歴'!$H$9:$H$999, 1, FALSE), "") | D8: =IFERROR(VLOOKUP(D$1, '(COP)契約者リンク履歴'!$H$9:$H$999, 1, FALSE), "") | E8: =IFERROR(VLOOKUP(E$1, '(COP)契約者リンク履歴'!$H$9:$H$999, 1, FALSE), "") | F8: =IFERROR(VLOOKUP(F$1, '(COP)契約者リンク履歴'!$H$9:$H$999, 1, FALSE), "") | G8: =IFERROR(VLOOKUP(G$1, '(COP)契約者リンク履歴'!$H$9:$H$999, 1, FALSE), "") | H8: =IFERROR(VLOOKUP(H$1, '(COP)契約者リンク履歴'!$H$9:$H$999, 1, FALSE), "") | I8: =IFERROR(VLOOKUP(I$1, '(COP)契約者リンク履歴'!$H$9:$H$999, 1, FALSE), "") -> サービスID(S#) | J8: =IFERROR(VLOOKUP(J$1, '(COP)契約者リンク履歴'!$H$9:$H$999, 1, FALSE), "") | ... Q8: =IFERROR(VLOOKUP(Q$1, '(COP)契約者リンク履歴'!$H$9:$H$999, 1, FALSE), "")
A9: COP | B9: svcリンク履歴 | C9: =IFERROR(VLOOKUP(C$1, '(COP)svcリンク履歴'!$H$9:$H$999, 1, FALSE), "") | D9: =IFERROR(VLOOKUP(D$1, '(COP)svcリンク履歴'!$H$9:$H$999, 1, FALSE), "") | E9: =IFERROR(VLOOKUP(E$1, '(COP)svcリンク履歴'!$H$9:$H$999, 1, FALSE), "") | F9: =IFERROR(VLOOKUP(F$1, '(COP)svcリンク履歴'!$H$9:$H$999, 1, FALSE), "") | G9: =IFERROR(VLOOKUP(G$1, '(COP)svcリンク履歴'!$H$9:$H$999, 1, FALSE), "") | H9: =IFERROR(VLOOKUP(H$1, '(COP)svcリンク履歴'!$H$9:$H$999, 1, FALSE), "") | I9: =IFERROR(VLOOKUP(I$1, '(COP)svcリンク履歴'!$H$9:$H$999, 1, FALSE), "") -> サービスID(S#) | J9: =IFERROR(VLOOKUP(J$1, '(COP)svcリンク履歴'!$H$9:$H$999, 1, FALSE), "") | ... Q9: =IFERROR(VLOOKUP(Q$1, '(COP)svcリンク履歴'!$H$9:$H$999, 1, FALSE), "") -> トランザクション番号
A10: COP | B10: 販売履歴 | C10: =IFERROR(VLOOKUP(C$1, '(COP)販売履歴'!$H$9:$H$999, 1, FALSE), "") | D10: =IFERROR(VLOOKUP(D$1, '(COP)販売履歴'!$H$9:$H$999, 1, FALSE), "") | E10: =IFERROR(VLOOKUP(E$1, '(COP)販売履歴'!$H$9:$H$999, 1, FALSE), "") | F10: =IFERROR(VLOOKUP(F$1, '(COP)販売履歴'!$H$9:$H$999, 1, FALSE), "") | G10: =IFERROR(VLOOKUP(G$1, '(COP)販売履歴'!$H$9:$H$999, 1, FALSE), "") | H10: =IFERROR(VLOOKUP(H$1, '(COP)販売履歴'!$H$9:$H$999, 1, FALSE), "") | I10: =IFERROR(VLOOKUP(I$1, '(COP)販売履歴'!$H$9:$H$999, 1, FALSE), "") -> サービスID(S#) | J10: =IFERROR(VLOOKUP(J$1, '(COP)販売履歴'!$H$9:$H$999, 1, FALSE), "") | ... Q10: =IFERROR(VLOOKUP(Q$1, '(COP)販売履歴'!$H$9:$H$999, 1, FALSE), "")
A11: COP | B11: 機器割当 | C11: =IFERROR(VLOOKUP(C$1, '(COP)機器割当'!$H$9:$H$999, 1, FALSE), "") | D11: =IFERROR(VLOOKUP(D$1, '(COP)機器割当'!$H$9:$H$999, 1, FALSE), "") | E11: =IFERROR(VLOOKUP(E$1, '(COP)機器割当'!$H$9:$H$999, 1, FALSE), "") | F11: =IFERROR(VLOOKUP(F$1, '(COP)機器割当'!$H$9:$H$999, 1, FALSE), "") | G11: =IFERROR(VLOOKUP(G$1, '(COP)機器割当'!$H$9:$H$999, 1, FALSE), "") | H11: =IFERROR(VLOOKUP(H$1, '(COP)機器割当'!$H$9:$H$999, 1, FALSE), "") | I11: =IFERROR(VLOOKUP(I$1, '(COP)機器割当'!$H$9:$H$999, 1, FALSE), "") -> サービスID(S#) | J11: =IFERROR(VLOOKUP(J$1, '(COP)機器割当'!$H$9:$H$999, 1, FALSE), "") | ... Q11: =IFERROR(VLOOKUP(Q$1, '(COP)機器割当'!$H$9:$H$999, 1, FALSE), "") -> トランザクション番号
A12: COP | B12: プロダクト | C12: =IFERROR(VLOOKUP(C$1, '(COP)プロダクト'!$H$9:$H$999, 1, FALSE), "") | D12: =IFERROR(VLOOKUP(D$1, '(COP)プロダクト'!$H$9:$H$999, 1, FALSE), "") | E12: =IFERROR(VLOOKUP(E$1, '(COP)プロダクト'!$H$9:$H$999, 1, FALSE), "") | F12: =IFERROR(VLOOKUP(F$1, '(COP)プロダクト'!$H$9:$H$999, 1, FALSE), "") | G12: =IFERROR(VLOOKUP(G$1, '(COP)プロダクト'!$H$9:$H$999, 1, FALSE), "") | H12: =IFERROR(VLOOKUP(H$1, '(COP)プロダクト'!$H$9:$H$999, 1, FALSE), "") | I12: =IFERROR(VLOOKUP(I$1, '(COP)プロダクト'!$H$9:$H$999, 1, FALSE), "") | J12: =IFERROR(VLOOKUP(J$1, '(COP)プロダクト'!$H$9:$H$999, 1, FALSE), "") | ... Q12: =IFERROR(VLOOKUP(Q$1, '(COP)プロダクト'!$H$9:$H$999, 1, FALSE), "") -> トランザクション番号
A13: Mars | B13: 取次店 | C13: =IFERROR(VLOOKUP(C$1, '(Mars)取次店'!$C$9:$C$999, 1, FALSE), "") | D13: =IFERROR(VLOOKUP(D$1, '(Mars)取次店'!$C$9:$C$999, 1, FALSE), "") | E13: =IFERROR(VLOOKUP(E$1, '(Mars)取次店'!$C$9:$C$999, 1, FALSE), "") | F13: =IFERROR(VLOOKUP(F$1, '(Mars)取次店'!$C$9:$C$999, 1, FALSE), "") | G13: =IFERROR(VLOOKUP(G$1, '(Mars)取次店'!$C$9:$C$999, 1, FALSE), "") | H13: =IFERROR(VLOOKUP(H$1, '(Mars)取次店'!$C$9:$C$999, 1, FALSE), "") | I13: =IFERROR(VLOOKUP(I$1, '(Mars)取次店'!$C$9:$C$999, 1, FALSE), "") | J13: =IFERROR(VLOOKUP(J$1, '(Mars)取次店'!$C$9:$C$999, 1, FALSE), "") | ... Q13: =IFERROR(VLOOKUP(Q$1, '(Mars)取次店'!$C$9:$C$999, 1, FALSE), "")
A14: Mars | B14: キャンペーン | C14: =IFERROR(VLOOKUP(C$1, '(Mars)キャンペーン'!$C$9:$C$999, 1, FALSE), "") | D14: =IFERROR(VLOOKUP(D$1, '(Mars)キャンペーン'!$C$9:$C$999, 1, FALSE), "") | E14: =IFERROR(VLOOKUP(E$1, '(Mars)キャンペーン'!$C$9:$C$999, 1, FALSE), "") | F14: =IFERROR(VLOOKUP(F$1, '(Mars)キャンペーン'!$C$9:$C$999, 1, FALSE), "") | G14: =IFERROR(VLOOKUP(G$1, '(Mars)キャンペーン'!$C$9:$C$999, 1, FALSE), "") | H14: =IFERROR(VLOOKUP(H$1, '(Mars)キャンペーン'!$C$9:$C$999, 1, FALSE), "") | I14: =IFERROR(VLOOKUP(I$1, '(Mars)キャンペーン'!$C$9:$C$999, 1, FALSE), "") | J14: =IFERROR(VLOOKUP(J$1, '(Mars)キャンペーン'!$C$9:$C$999, 1, FALSE), "") | ... Q14: =IFERROR(VLOOKUP(Q$1, '(Mars)キャンペーン'!$C$9:$C$999, 1, FALSE), "")
A15: Mars | B15: 商品 | C15: =IFERROR(VLOOKUP(C$1, '(Mars)商品'!$C$9:$C$999, 1, FALSE), "") | D15: =IFERROR(VLOOKUP(D$1, '(Mars)商品'!$C$9:$C$999, 1, FALSE), "") | E15: =IFERROR(VLOOKUP(E$1, '(Mars)商品'!$C$9:$C$999, 1, FALSE), "") | F15: =IFERROR(VLOOKUP(F$1, '(Mars)商品'!$C$9:$C$999, 1, FALSE), "") | G15: =IFERROR(VLOOKUP(G$1, '(Mars)商品'!$C$9:$C$999, 1, FALSE), "") | H15: =IFERROR(VLOOKUP(H$1, '(Mars)商品'!$C$9:$C$999, 1, FALSE), "") | I15: =IFERROR(VLOOKUP(I$1, '(Mars)商品'!$C$9:$C$999, 1, FALSE), "") | J15: =IFERROR(VLOOKUP(J$1, '(Mars)商品'!$C$9:$C$999, 1, FALSE), "") | ... Q15: =IFERROR(VLOOKUP(Q$1, '(Mars)商品'!$C$9:$C$999, 1, FALSE), "")
A16: SUMMIT | B16: 決裁_料金決裁 | C16: =IFERROR(VLOOKUP(C$1, '(SUMMIT)決裁_料金決裁'!$C$9:$C$999, 1, FALSE), "") -> 決裁番号 | D16: =IFERROR(VLOOKUP(D$1, '(SUMMIT)決裁_料金決裁'!$C$9:$C$999, 1, FALSE), "") | E16: =IFERROR(VLOOKUP(E$1, '(SUMMIT)決裁_料金決裁'!$C$9:$C$999, 1, FALSE), "") | F16: =IFERROR(VLOOKUP(F$1, '(SUMMIT)決裁_料金決裁'!$C$9:$C$999, 1, FALSE), "") | G16: =IFERROR(VLOOKUP(G$1, '(SUMMIT)決裁_料金決裁'!$C$9:$C$999, 1, FALSE), "") | H16: =IFERROR(VLOOKUP(H$1, '(SUMMIT)決裁_料金決裁'!$C$9:$C$999, 1, FALSE), "") | I16: =IFERROR(VLOOKUP(I$1, '(SUMMIT)決裁_料金決裁'!$C$9:$C$999, 1, FALSE), "") | J16: =IFERROR(VLOOKUP(J$1, '(SUMMIT)決裁_料金決裁'!$C$9:$C$999, 1, FALSE), "") | ... Q16: =IFERROR(VLOOKUP(Q$1, '(SUMMIT)決裁_料金決裁'!$C$9:$C$999, 1, FALSE), "")
A17: SUMMIT | B17: 決裁_提案モバイル | C17: =IFERROR(VLOOKUP(C$1, '(SUMMIT)決裁_提案モバイル'!$C$9:$C$999, 1, FALSE), "") -> 決裁番号 | D17: =IFERROR(VLOOKUP(D$1, '(SUMMIT)決裁_提案モバイル'!$C$9:$C$999, 1, FALSE), "") | E17: =IFERROR(VLOOKUP(E$1, '(SUMMIT)決裁_提案モバイル'!$C$9:$C$999, 1, FALSE), "") | F17: =IFERROR(VLOOKUP(F$1, '(SUMMIT)決裁_提案モバイル'!$C$9:$C$999, 1, FALSE), "") | G17: =IFERROR(VLOOKUP(G$1, '(SUMMIT)決裁_提案モバイル'!$C$9:$C$999, 1, FALSE), "") | H17: =IFERROR(VLOOKUP(H$1, '(SUMMIT)決裁_提案モバイル'!$C$9:$C$999, 1, FALSE), "") | I17: =IFERROR(VLOOKUP(I$1, '(SUMMIT)決裁_提案モバイル'!$C$9:$C$999, 1, FALSE), "") | J17: =IFERROR(VLOOKUP(J$1, '(SUMMIT)決裁_提案モバイル'!$C$9:$C$999, 1, FALSE), "") | ... M17: =IFERROR(VLOOKUP(M$1, '(SUMMIT)決裁_提案モバイル'!$C$9:$C$999, 1, FALSE), "") | Q17: =IFERROR(VLOOKUP(Q$1, '(SUMMIT)決裁_提案モバイル'!$C$9:$C$999, 1, FALSE), "")
A18: SUMMIT | B18: 決裁_共通決裁 | C18: =IFERROR(VLOOKUP(C$1, '(SUMMIT)決裁_共通決裁'!$C$9:$C$999, 1, FALSE), "") -> 決裁番号 | D18: =IFERROR(VLOOKUP(D$1, '(SUMMIT)決裁_共通決裁'!$C$9:$C$999, 1, FALSE), "") | E18: =IFERROR(VLOOKUP(E$1, '(SUMMIT)決裁_共通決裁'!$C$9:$C$999, 1, FALSE), "") | F18: =IFERROR(VLOOKUP(F$1, '(SUMMIT)決裁_共通決裁'!$C$9:$C$999, 1, FALSE), "") | G18: =IFERROR(VLOOKUP(G$1, '(SUMMIT)決裁_共通決裁'!$C$9:$C$999, 1, FALSE), "") | H18: =IFERROR(VLOOKUP(H$1, '(SUMMIT)決裁_共通決裁'!$C$9:$C$999, 1, FALSE), "") | I18: =IFERROR(VLOOKUP(I$1, '(SUMMIT)決裁_共通決裁'!$C$9:$C$999, 1, FALSE), "") | J18: =IFERROR(VLOOKUP(J$1, '(SUMMIT)決裁_共通決裁'!$C$9:$C$999, 1, FALSE), "") | ... Q18: =IFERROR(VLOOKUP(Q$1, '(SUMMIT)決裁_共通決裁'!$C$9:$C$999, 1, FALSE), "")
A19: SUMMIT | B19: 決裁_基本_補足 | C19: =IFERROR(VLOOKUP(C$1, '(SUMMIT)決裁_基本_補足'!$C$9:$C$999, 1, FALSE), "") -> 決裁番号 | D19: =IFERROR(VLOOKUP(D$1, '(SUMMIT)決裁_基本_補足'!$C$9:$C$999, 1, FALSE), "") | E19: =IFERROR(VLOOKUP(E$1, '(SUMMIT)決裁_基本_補足'!$C$9:$C$999, 1, FALSE), "") | F19: =IFERROR(VLOOKUP(F$1, '(SUMMIT)決裁_基本_補足'!$C$9:$C$999, 1, FALSE), "") -> 統一企業コード | G19: =IFERROR(VLOOKUP(G$1, '(SUMMIT)決裁_基本_補足'!$C$9:$C$999, 1, FALSE), "") | H19: =IFERROR(VLOOKUP(H$1, '(SUMMIT)決裁_基本_補足'!$C$9:$C$999, 1, FALSE), "") | I19: =IFERROR(VLOOKUP(I$1, '(SUMMIT)決裁_基本_補足'!$C$9:$C$999, 1, FALSE), "") | J19: =IFERROR(VLOOKUP(J$1, '(SUMMIT)決裁_基本_補足'!$C$9:$C$999, 1, FALSE), "") | ... Q19: =IFERROR(VLOOKUP(Q$1, '(SUMMIT)決裁_基本_補足'!$C$9:$C$999, 1, FALSE), "")
A20: SUMMIT | B20: 決裁_関連申請書 | C20: =IFERROR(VLOOKUP(C$1, '(SUMMIT)決裁_関連申請書'!$C$9:$C$999, 1, FALSE), "") | D20: =IFERROR(VLOOKUP(D$1, '(SUMMIT)決裁_関連申請書'!$C$9:$C$999, 1, FALSE), "") | E20: =IFERROR(VLOOKUP(E$1, '(SUMMIT)決裁_関連申請書'!$C$9:$C$999, 1, FALSE), "") | F20: =IFERROR(VLOOKUP(F$1, '(SUMMIT)決裁_関連申請書'!$C$9:$C$999, 1, FALSE), "") | G20: =IFERROR(VLOOKUP(G$1, '(SUMMIT)決裁_関連申請書'!$C$9:$C$999, 1, FALSE), "") | H20: =IFERROR(VLOOKUP(H$1, '(SUMMIT)決裁_関連申請書'!$C$9:$C$999, 1, FALSE), "") | I20: =IFERROR(VLOOKUP(I$1, '(SUMMIT)決裁_関連申請書'!$C$9:$C$999, 1, FALSE), "") | J20: =IFERROR(VLOOKUP(J$1, '(SUMMIT)決裁_関連申請書'!$C$9:$C$999, 1, FALSE), "") | ... Q20: =IFERROR(VLOOKUP(Q$1, '(SUMMIT)決裁_関連申請書'!$C$9:$C$999, 1, FALSE), "")

Sheet メモ

Sheet (BFSエントリ)モバイル_サービスサマリ_付属品
G2: 種別 | H2: DWH公開名 | I2: 旧DWH公開名 | J2: 統合テーブルID | K2: スキーマ
G3: ビュー | H3: b_hjn_bfs_モバイル_サービスサマリ_付属品 | J3: V004659 | K3: user_l2_prvl | L3: bfs_service_summary_accessories
G4: データ概要：
G5: 0
K6: ="DROP TABLE IF EXISTS "&L3&" CASCADE;" -> DROP TABLE IF EXISTS bfs_service_summary_accessories CASCADE; | R6: DROP TABLE IF EXISTS bfs_service_summary_accessories CASCADE;
K7: ="CREATE TABLE IF NOT EXISTS "&L3&" (" -> CREATE TABLE IF NOT EXISTS bfs_service_summary_accessories ( | N7: ="COMMENT ON TABLE "&L3&" IS '"&H3&"';" -> COMMENT ON TABLE bfs_service_summary_accessories IS 'b_hjn_bfs_モバイル_サービスサマリ_付属品'; | R7: CREATE TABLE IF NOT EXISTS bfs_service_summary_accessories (
A8: pk | B8: SEQ | C8: 項目名 | D8: TYPE | E8: 桁 | F8: 仮名化 | G8: 項目説明およびリスト値 | H8: コードリファレンスリンク | I8: 備考 | J8: 更新日 | K8: id BIGINT GENERATED BY DEFAULT AS IDENTITY, | N8: ="COMMENT ON COLUMN "&$L$3&".id IS '"&C8&"';" -> COMMENT ON COLUMN bfs_service_summary_accessories.id IS '項目名'; | R8: id BIGINT GENERATED BY DEFAULT AS IDENTITY,
B9: 1 | C9: エントリ番号 | D9: VARCHAR | E9: 54 | F9: － | K9: entry_number | L9: =D9&"("&E9&")," -> VARCHAR(54), | N9: ="COMMENT ON COLUMN "&$L$3&"."&K9&" IS '"&C9&"';" -> COMMENT ON COLUMN bfs_service_summary_accessories.entry_number IS 'エントリ番号'; | R9: entry_number VARCHAR(54),
B10: 2 | C10: サマリ番号 | D10: VARCHAR | E10: 36 | F10: － | K10: summary_number | L10: =D10&"("&E10&")," -> VARCHAR(36), | N10: ="COMMENT ON COLUMN "&$L$3&"."&K10&" IS '"&C10&"';" -> COMMENT ON COLUMN bfs_service_summary_accessories.summary_number IS 'サマリ番号'; | R10: summary_number VARCHAR(36),
B11: 3 | C11: シリアル付付属品 | D11: VARCHAR | E11: 2295 | F11: － | K11: serial_number_accessories | L11: =D11&"("&E11&")," -> VARCHAR(2295), | N11: ="COMMENT ON COLUMN "&$L$3&"."&K11&" IS '"&C11&"';" -> COMMENT ON COLUMN bfs_service_summary_accessories.serial_number_accessories IS 'シリアル付付属品'; | R11: serial_number_accessories VARCHAR(2295),
B12: 4 | C12: 商品コード | D12: VARCHAR | E12: 45 | F12: － | K12: product_code | L12: =D12&"("&E12&")," -> VARCHAR(45), | N12: ="COMMENT ON COLUMN "&$L$3&"."&K12&" IS '"&C12&"';" -> COMMENT ON COLUMN bfs_service_summary_accessories.product_code IS '商品コード'; | R12: product_code VARCHAR(45),
B13: 5 | C13: メーカ | D13: VARCHAR | E13: 1800 | F13: － | K13: manufacturer | L13: =D13&"("&E13&")," -> VARCHAR(1800), | N13: ="COMMENT ON COLUMN "&$L$3&"."&K13&" IS '"&C13&"';" -> COMMENT ON COLUMN bfs_service_summary_accessories.manufacturer IS 'メーカ'; | R13: manufacturer VARCHAR(1800),
B14: 6 | C14: 商品名 | D14: VARCHAR | E14: 900 | F14: － | K14: product_name | L14: =D14&"("&E14&")," -> VARCHAR(900), | N14: ="COMMENT ON COLUMN "&$L$3&"."&K14&" IS '"&C14&"';" -> COMMENT ON COLUMN bfs_service_summary_accessories.product_name IS '商品名'; | R14: product_name VARCHAR(900),
B15: 7 | C15: カラー1 | D15: VARCHAR | E15: 900 | F15: － | K15: color_1 | L15: =D15&"("&E15&")," -> VARCHAR(900), | N15: ="COMMENT ON COLUMN "&$L$3&"."&K15&" IS '"&C15&"';" -> COMMENT ON COLUMN bfs_service_summary_accessories.color_1 IS 'カラー1'; | R15: color_1 VARCHAR(900),
B16: 8 | C16: 台数1 | D16: DECIMAL | E16: 6 | F16: － | K16: quantity_1 | L16: =D16&"("&E16&")," -> DECIMAL(6), | N16: ="COMMENT ON COLUMN "&$L$3&"."&K16&" IS '"&C16&"';" -> COMMENT ON COLUMN bfs_service_summary_accessories.quantity_1 IS '台数1'; | R16: quantity_1 DECIMAL(6),
B17: 9 | C17: カラー2 | D17: VARCHAR | E17: 900 | F17: － | K17: color_2 | L17: =D17&"("&E17&")," -> VARCHAR(900), | N17: ="COMMENT ON COLUMN "&$L$3&"."&K17&" IS '"&C17&"';" -> COMMENT ON COLUMN bfs_service_summary_accessories.color_2 IS 'カラー2'; | R17: color_2 VARCHAR(900),
B18: 10 | C18: 台数2 | D18: DECIMAL | E18: 6 | F18: － | K18: quantity_2 | L18: =D18&"("&E18&")," -> DECIMAL(6), | N18: ="COMMENT ON COLUMN "&$L$3&"."&K18&" IS '"&C18&"';" -> COMMENT ON COLUMN bfs_service_summary_accessories.quantity_2 IS '台数2'; | R18: quantity_2 DECIMAL(6),
B19: 11 | C19: カラー3 | D19: VARCHAR | E19: 900 | F19: － | K19: color_3 | L19: =D19&"("&E19&")," -> VARCHAR(900), | N19: ="COMMENT ON COLUMN "&$L$3&"."&K19&" IS '"&C19&"';" -> COMMENT ON COLUMN bfs_service_summary_accessories.color_3 IS 'カラー3'; | R19: color_3 VARCHAR(900),
B20: 12 | C20: 台数3 | D20: DECIMAL | E20: 6 | F20: － | K20: quantity_3 | L20: =D20&"("&E20&")," -> DECIMAL(6), | N20: ="COMMENT ON COLUMN "&$L$3&"."&K20&" IS '"&C20&"';" -> COMMENT ON COLUMN bfs_service_summary_accessories.quantity_3 IS '台数3'; | R20: quantity_3 DECIMAL(6),
... B29: 21 | C29: 紐付けサマリ番号 | D29: VARCHAR | E29: 90 | F29: － | K29: linked_summary_number | L29: =D29&"("&E29&")," -> VARCHAR(90), | N29: ="COMMENT ON COLUMN "&$L$3&"."&K29&" IS '"&C29&"';" -> COMMENT ON COLUMN bfs_service_summary_accessories.linked_summary_number IS '紐付けサマリ番号'; | R29: linked_summary_number VARCHAR(90),
B30: 22 | C30: 原価予備費 | D30: DECIMAL | E30: 8,0 | F30: － | K30: cost_contingency | L30: =D30&"("&E30&")," -> DECIMAL(8,0), | N30: ="COMMENT ON COLUMN "&$L$3&"."&K30&" IS '"&C30&"';" -> COMMENT ON COLUMN bfs_service_summary_accessories.cost_contingency IS '原価予備費'; | R30: cost_contingency DECIMAL(8,0),
K31: ="CONSTRAINT pk_"&L3&" PRIMARY KEY (id));" -> CONSTRAINT pk_bfs_service_summary_accessories PRIMARY KEY (id)); | R31: CONSTRAINT pk_bfs_service_summary_accessories PRIMARY KEY (id));
R32: COMMENT ON TABLE bfs_service_summary_accessories IS 'b_hjn_bfs_モバイル_サービスサマリ_付属品';
R33: COMMENT ON COLUMN bfs_service_summary_accessories.id IS '項目名';
R34: COMMENT ON COLUMN bfs_service_summary_accessories.entry_number IS 'エントリ番号';
R35: COMMENT ON COLUMN bfs_service_summary_accessories.summary_number IS 'サマリ番号';
R36: COMMENT ON COLUMN bfs_service_summary_accessories.serial_number_accessories IS 'シリアル付付属品';
R37: COMMENT ON COLUMN bfs_service_summary_accessories.product_code IS '商品コード';
R38: COMMENT ON COLUMN bfs_service_summary_accessories.manufacturer IS 'メーカ';
R39: COMMENT ON COLUMN bfs_service_summary_accessories.product_name IS '商品名';
R40: COMMENT ON COLUMN bfs_service_summary_accessories.color_1 IS 'カラー1';
R41: COMMENT ON COLUMN bfs_service_summary_accessories.quantity_1 IS '台数1';
R42: COMMENT ON COLUMN bfs_service_summary_accessories.color_2 IS 'カラー2';
R43: COMMENT ON COLUMN bfs_service_summary_accessories.quantity_2 IS '台数2';
... R55: COMMENT ON COLUMN bfs_service_summary_accessories.cost_contingency IS '原価予備費';

Sheet (BFSエントリ)モバイル_サービスサマリ_端末
C2: 種別 | D2: DWH公開名 | E2: 旧DWH公開名 | F2: 統合テーブルID | G2: スキーマ
C3: ビュー | D3: b_hjn_bfs_モバイル_サービスサマリ_端末 | F3: V004515 | G3: user_l2_prvl | H3: bfs_service_summary_device
K4: ="DROP TABLE IF EXISTS "&H3&" CASCADE;" -> DROP TABLE IF EXISTS bfs_service_summary_device CASCADE; | R4: DROP TABLE IF EXISTS bfs_service_summary_device CASCADE;
K5: ="CREATE TABLE IF NOT EXISTS "&H3&" (" -> CREATE TABLE IF NOT EXISTS bfs_service_summary_device ( | N5: ="COMMENT ON TABLE "&H3&" IS '"&D3&"';" -> COMMENT ON TABLE bfs_service_summary_device IS 'b_hjn_bfs_モバイル_サービスサマリ_端末'; | R5: CREATE TABLE IF NOT EXISTS bfs_service_summary_device (
A6: pk | B6: SEQ | C6: 項目名 | D6: TYPE | E6: 桁 | F6: 仮名化 | G6: 項目説明およびリスト値 | H6: コードリファレンスリンク | I6: 備考 | J6: 更新日 | K6: id BIGINT GENERATED BY DEFAULT AS IDENTITY, | N6: ="COMMENT ON COLUMN "&$H$3&".id IS 'id';" -> COMMENT ON COLUMN bfs_service_summary_device.id IS 'id'; | R6: id BIGINT GENERATED BY DEFAULT AS IDENTITY,
B7: 1 | C7: エントリ番号 | D7: VARCHAR | E7: 54 | F7: － | K7: entry_number | L7: =D7&"("&E7&")," -> VARCHAR(54), | N7: ="COMMENT ON COLUMN "&$H$3&"."&$K7&" IS '"&C7&"';" -> COMMENT ON COLUMN bfs_service_summary_device.entry_number IS 'エントリ番号'; | R7: entry_number VARCHAR(54),
B8: 2 | C8: サマリ番号 | D8: VARCHAR | E8: 36 | F8: － | K8: summary_number | L8: =D8&"("&E8&")," -> VARCHAR(36), | N8: ="COMMENT ON COLUMN "&$H$3&"."&$K8&" IS '"&C8&"';" -> COMMENT ON COLUMN bfs_service_summary_device.summary_number IS 'サマリ番号'; | R8: summary_number VARCHAR(36),
B9: 3 | C9: 回線数 | D9: DECIMAL | E9: 10 | F9: － | K9: number_of_lines | L9: =D9&"("&E9&")," -> DECIMAL(10), | N9: ="COMMENT ON COLUMN "&$H$3&"."&$K9&" IS '"&C9&"';" -> COMMENT ON COLUMN bfs_service_summary_device.number_of_lines IS '回線数'; | R9: number_of_lines DECIMAL(10),
B10: 4 | C10: レンタルセット端末 | D10: VARCHAR | E10: 2295 | F10: － | K10: rental_set_device | L10: =D10&"("&E10&")," -> VARCHAR(2295), | N10: ="COMMENT ON COLUMN "&$H$3&"."&$K10&" IS '"&C10&"';" -> COMMENT ON COLUMN bfs_service_summary_device.rental_set_device IS 'レンタルセット端末'; | R10: rental_set_device VARCHAR(2295),
B11: 5 | C11: mnp | D11: VARCHAR | E11: 2295 | F11: － | K11: mnp | L11: =D11&"("&E11&")," -> VARCHAR(2295), | N11: ="COMMENT ON COLUMN "&$H$3&"."&$K11&" IS '"&C11&"';" -> COMMENT ON COLUMN bfs_service_summary_device.mnp IS 'mnp'; | R11: mnp VARCHAR(2295),
B12: 6 | C12: 商品コード | D12: VARCHAR | E12: 45 | F12: － | K12: product_code | L12: =D12&"("&E12&")," -> VARCHAR(45), | N12: ="COMMENT ON COLUMN "&$H$3&"."&$K12&" IS '"&C12&"';" -> COMMENT ON COLUMN bfs_service_summary_device.product_code IS '商品コード'; | R12: product_code VARCHAR(45),
B13: 7 | C13: メーカ | D13: VARCHAR | E13: 1800 | F13: － | K13: manufacturer | L13: =D13&"("&E13&")," -> VARCHAR(1800), | N13: ="COMMENT ON COLUMN "&$H$3&"."&$K13&" IS '"&C13&"';" -> COMMENT ON COLUMN bfs_service_summary_device.manufacturer IS 'メーカ'; | R13: manufacturer VARCHAR(1800),
B14: 8 | C14: 移動機分類 | D14: VARCHAR | E14: 900 | F14: － | K14: mobile_device_classification | L14: =D14&"("&E14&")," -> VARCHAR(900), | N14: ="COMMENT ON COLUMN "&$H$3&"."&$K14&" IS '"&C14&"';" -> COMMENT ON COLUMN bfs_service_summary_device.mobile_device_classification IS '移動機分類'; | R14: mobile_device_classification VARCHAR(900),
B15: 9 | C15: 機種名 | D15: VARCHAR | E15: 900 | F15: － | K15: model_name | L15: =D15&"("&E15&")," -> VARCHAR(900), | N15: ="COMMENT ON COLUMN "&$H$3&"."&$K15&" IS '"&C15&"';" -> COMMENT ON COLUMN bfs_service_summary_device.model_name IS '機種名'; | R15: model_name VARCHAR(900),
B16: 10 | C16: カラー1 | D16: VARCHAR | E16: 900 | F16: － | K16: color_1 | L16: =D16&"("&E16&")," -> VARCHAR(900), | N16: ="COMMENT ON COLUMN "&$H$3&"."&$K16&" IS '"&C16&"';" -> COMMENT ON COLUMN bfs_service_summary_device.color_1 IS 'カラー1'; | R16: color_1 VARCHAR(900),
B17: 11 | C17: 台数1 | D17: DECIMAL | E17: 10 | F17: － | K17: quantity_1 | L17: =D17&"("&E17&")," -> DECIMAL(10), | N17: ="COMMENT ON COLUMN "&$H$3&"."&$K17&" IS '"&C17&"';" -> COMMENT ON COLUMN bfs_service_summary_device.quantity_1 IS '台数1'; | R17: quantity_1 DECIMAL(10),
B18: 12 | C18: カラー2 | D18: VARCHAR | E18: 900 | F18: － | K18: color_2 | L18: =D18&"("&E18&")," -> VARCHAR(900), | N18: ="COMMENT ON COLUMN "&$H$3&"."&$K18&" IS '"&C18&"';" -> COMMENT ON COLUMN bfs_service_summary_device.color_2 IS 'カラー2'; | R18: color_2 VARCHAR(900),
... B508: 502 | C508: esim登録 | D508: VARCHAR | E508: 2295 | F508: － | K508: esim_registration | L508: =D508&"("&E508&")," -> VARCHAR(2295), | N508: ="COMMENT ON COLUMN "&$H$3&"."&$K508&" IS '"&C508&"';" -> COMMENT ON COLUMN bfs_service_summary_device.esim_registration IS 'esim登録'; | R508: esim_registration VARCHAR(2295),
B509: 503 | C509: 現端末契約期間 | D509: DECIMAL | E509: 2,0 | F509: － | K509: current_device_contract_period | L509: =D509&"("&E509&")," -> DECIMAL(2,0), | N509: ="COMMENT ON COLUMN "&$H$3&"."&$K509&" IS '"&C509&"';" -> COMMENT ON COLUMN bfs_service_summary_device.current_device_contract_period IS '現端末契約期間'; | R509: current_device_contract_period DECIMAL(2,0),
B510: 504 | C510: サマリ単位反映 | D510: VARCHAR | E510: 90 | F510: － | K510: reflected_in_summary_unit | L510: =D510&"("&E510&")," -> VARCHAR(90), | N510: ="COMMENT ON COLUMN "&$H$3&"."&$K510&" IS '"&C510&"';" -> COMMENT ON COLUMN bfs_service_summary_device.reflected_in_summary_unit IS 'サマリ単位反映'; | R510: reflected_in_summary_unit VARCHAR(90),
K511: ="CONSTRAINT pk_"&H3&" PRIMARY KEY (id));" -> CONSTRAINT pk_bfs_service_summary_device PRIMARY KEY (id)); | R511: CONSTRAINT pk_bfs_service_summary_device PRIMARY KEY (id));
R512: COMMENT ON TABLE bfs_service_summary_device IS 'b_hjn_bfs_モバイル_サービスサマリ_端末';
R513: COMMENT ON COLUMN bfs_service_summary_device.id IS 'id';
R514: COMMENT ON COLUMN bfs_service_summary_device.entry_number IS 'エントリ番号';
R515: COMMENT ON COLUMN bfs_service_summary_device.summary_number IS 'サマリ番号';
R516: COMMENT ON COLUMN bfs_service_summary_device.number_of_lines IS '回線数';
R517: COMMENT ON COLUMN bfs_service_summary_device.rental_set_device IS 'レンタルセット端末';
R518: COMMENT ON COLUMN bfs_service_summary_device.mnp IS 'mnp';
R519: COMMENT ON COLUMN bfs_service_summary_device.product_code IS '商品コード';
R520: COMMENT ON COLUMN bfs_service_summary_device.manufacturer IS 'メーカ';
R521: COMMENT ON COLUMN bfs_service_summary_device.mobile_device_classification IS '移動機分類';
R522: COMMENT ON COLUMN bfs_service_summary_device.model_name IS '機種名';
R523: COMMENT ON COLUMN bfs_service_summary_device.color_1 IS 'カラー1';
... R1017: COMMENT ON COLUMN bfs_service_summary_device.reflected_in_summary_unit IS 'サマリ単位反映';

Sheet (BFSエントリ)モバイル_エントリ情報
C2: 種別 | D2: DWH公開名 | E2: 旧DWH公開名 | F2: 統合テーブルID | G2: スキーマ
C3: ビュー | D3: b_hjn_bfs_モバイル_エントリ情報 | F3: V004409 | G3: user_l2_prvl | H3: user_l2_prvl | K3: bfs_entry_information
C4: データ概要：
C5: （BFS）モバイル_エントリ情報
K6: ="DROP TABLE IF EXISTS "&K3&" CASCADE;" -> DROP TABLE IF EXISTS bfs_entry_information CASCADE; | R6: DROP TABLE IF EXISTS bfs_entry_information CASCADE;
K7: ="CREATE TABLE IF NOT EXISTS "&K3&" (" -> CREATE TABLE IF NOT EXISTS bfs_entry_information ( | N7: ="COMMENT ON TABLE "&K3&" IS '"&D3&"';" -> COMMENT ON TABLE bfs_entry_information IS 'b_hjn_bfs_モバイル_エントリ情報'; | R7: CREATE TABLE IF NOT EXISTS bfs_entry_information (
A8: pk | B8: SEQ | C8: 項目名 | D8: TYPE | E8: 桁 | F8: 仮名化 | G8: 項目説明およびリスト値 | H8: コードリファレンスリンク | I8: 備考 | J8: 更新日 | K8: id BIGINT GENERATED BY DEFAULT AS IDENTITY, | N8: ="COMMENT ON COLUMN "&$K$3&".id IS 'id';" -> COMMENT ON COLUMN bfs_entry_information.id IS 'id'; | R8: id BIGINT GENERATED BY DEFAULT AS IDENTITY,
B9: 1 | C9: エントリ番号 | D9: VARCHAR | E9: 54 | F9: － | K9: entry_number | L9: =D9&"("&E9&")," -> VARCHAR(54), | N9: ="COMMENT ON COLUMN "&$K$3&"."&$K9&" IS '"&C9&"';" -> COMMENT ON COLUMN bfs_entry_information.entry_number IS 'エントリ番号'; | R9: entry_number VARCHAR(54),
B10: 2 | C10: 件名 | D10: VARCHAR | E10: 2304 | F10: － | K10: subject | L10: =D10&"("&E10&")," -> VARCHAR(2304), | N10: ="COMMENT ON COLUMN "&$K$3&"."&$K10&" IS '"&C10&"';" -> COMMENT ON COLUMN bfs_entry_information.subject IS '件名'; | R10: subject VARCHAR(2304),
B11: 3 | C11: 作成区分 | D11: VARCHAR | E11: 900 | F11: － | K11: creation_category | L11: =D11&"("&E11&")," -> VARCHAR(900), | N11: ="COMMENT ON COLUMN "&$K$3&"."&$K11&" IS '"&C11&"';" -> COMMENT ON COLUMN bfs_entry_information.creation_category IS '作成区分'; | R11: creation_category VARCHAR(900),
B12: 4 | C12: オーダ種別 | D12: VARCHAR | E12: 900 | F12: － | K12: order_type | L12: =D12&"("&E12&")," -> VARCHAR(900), | N12: ="COMMENT ON COLUMN "&$K$3&"."&$K12&" IS '"&C12&"';" -> COMMENT ON COLUMN bfs_entry_information.order_type IS 'オーダ種別'; | R12: order_type VARCHAR(900),
B13: 5 | C13: 申込書連携 | D13: VARCHAR | E13: 900 | F13: － | K13: application_form_linkage | L13: =D13&"("&E13&")," -> VARCHAR(900), | N13: ="COMMENT ON COLUMN "&$K$3&"."&$K13&" IS '"&C13&"';" -> COMMENT ON COLUMN bfs_entry_information.application_form_linkage IS '申込書連携'; | R13: application_form_linkage VARCHAR(900),
B14: 6 | C14: 特約分離出力有無 | D14: VARCHAR | E14: 900 | F14: － | K14: special_contract_separate_output | L14: =D14&"("&E14&")," -> VARCHAR(900), | N14: ="COMMENT ON COLUMN "&$K$3&"."&$K14&" IS '"&C14&"';" -> COMMENT ON COLUMN bfs_entry_information.special_contract_separate_output IS '特約分離出力有無'; | R14: special_contract_separate_output VARCHAR(900),
B15: 7 | C15: 通知書対象 | D15: VARCHAR | E15: 900 | F15: － | K15: notification_target | L15: =D15&"("&E15&")," -> VARCHAR(900), | N15: ="COMMENT ON COLUMN "&$K$3&"."&$K15&" IS '"&C15&"';" -> COMMENT ON COLUMN bfs_entry_information.notification_target IS '通知書対象'; | R15: notification_target VARCHAR(900),
B16: 8 | C16: 開通済有無 | D16: VARCHAR | E16: 900 | F16: － | K16: activation_status | L16: =D16&"("&E16&")," -> VARCHAR(900), | N16: ="COMMENT ON COLUMN "&$K$3&"."&$K16&" IS '"&C16&"';" -> COMMENT ON COLUMN bfs_entry_information.activation_status IS '開通済有無'; | R16: activation_status VARCHAR(900),
B17: 9 | C17: 開通日 | D17: VARCHAR | E17: 60 | F17: － | K17: activation_date | L17: =D17&"("&E17&")," -> VARCHAR(60), | N17: ="COMMENT ON COLUMN "&$K$3&"."&$K17&" IS '"&C17&"';" -> COMMENT ON COLUMN bfs_entry_information.activation_date IS '開通日'; | R17: activation_date VARCHAR(60),
B18: 10 | C18: 非完結依頼種別 | D18: VARCHAR | E18: 900 | F18: － | K18: incomplete_request_type | L18: =D18&"("&E18&")," -> VARCHAR(900), | N18: ="COMMENT ON COLUMN "&$K$3&"."&$K18&" IS '"&C18&"';" -> COMMENT ON COLUMN bfs_entry_information.incomplete_request_type IS '非完結依頼種別'; | R18: incomplete_request_type VARCHAR(900),
B19: 11 | C19: コピー元エントリ種別 | D19: VARCHAR | E19: 900 | F19: － | K19: source_entry_type | L19: =D19&"("&E19&")," -> VARCHAR(900), | N19: ="COMMENT ON COLUMN "&$K$3&"."&$K19&" IS '"&C19&"';" -> COMMENT ON COLUMN bfs_entry_information.source_entry_type IS 'コピー元エントリ種別'; | R19: source_entry_type VARCHAR(900),
B20: 12 | C20: 営業担当者コード | D20: VARCHAR | E20: 21 | F20: － | K20: salesperson_code | L20: =D20&"("&E20&")," -> VARCHAR(21), | N20: ="COMMENT ON COLUMN "&$K$3&"."&$K20&" IS '"&C20&"';" -> COMMENT ON COLUMN bfs_entry_information.salesperson_code IS '営業担当者コード'; | R20: salesperson_code VARCHAR(21),
... B224: 216 | C224: rental_中古_期間_ヶ月 | D224: VARCHAR | E224: 6 | F224: － | K224: rental_used_period_months | L224: =D224&"("&E224&")," -> VARCHAR(6), | N224: ="COMMENT ON COLUMN "&$K$3&"."&$K224&" IS '"&C224&"';" -> COMMENT ON COLUMN bfs_entry_information.rental_used_period_months IS 'rental_中古_期間_ヶ月'; | R224: rental_used_period_months VARCHAR(6),
K225: ="CONSTRAINT pk_"&K3&" PRIMARY KEY (id));" -> CONSTRAINT pk_bfs_entry_information PRIMARY KEY (id)); | R225: CONSTRAINT pk_bfs_entry_information PRIMARY KEY (id));
R226: COMMENT ON TABLE bfs_entry_information IS 'b_hjn_bfs_モバイル_エントリ情報';
R227: COMMENT ON COLUMN bfs_entry_information.id IS 'id';
R228: COMMENT ON COLUMN bfs_entry_information.entry_number IS 'エントリ番号';
R229: COMMENT ON COLUMN bfs_entry_information.subject IS '件名';
R230: COMMENT ON COLUMN bfs_entry_information.creation_category IS '作成区分';
R231: COMMENT ON COLUMN bfs_entry_information.order_type IS 'オーダ種別';
R232: COMMENT ON COLUMN bfs_entry_information.application_form_linkage IS '申込書連携';
R233: COMMENT ON COLUMN bfs_entry_information.special_contract_separate_output IS '特約分離出力有無';
R234: COMMENT ON COLUMN bfs_entry_information.notification_target IS '通知書対象';
R235: COMMENT ON COLUMN bfs_entry_information.activation_status IS '開通済有無';
R236: COMMENT ON COLUMN bfs_entry_information.activation_date IS '開通日';
R237: COMMENT ON COLUMN bfs_entry_information.incomplete_request_type IS '非完結依頼種別';
... R443: COMMENT ON COLUMN bfs_entry_information.rental_used_period_months IS 'rental_中古_期間_ヶ月';

Sheet (RMS)契約基本情報
F2: 種別 | G2: DWH公開名 | H2: 旧DWH公開名 | I2: 統合テーブルID | J2: スキーマ
F3: ビュー | G3: b_hjn_rms_契約基本情報 | I3: V004566 | J3: user_l2_prvl | K3: rms_contract_basic_information
F4: データ概要：
F5: オーダー番号毎に、納品先、契約内容、支払い方法等の情報を持つ
K6: ="DROP TABLE IF EXISTS "&K3&" CASCADE;" -> DROP TABLE IF EXISTS rms_contract_basic_information CASCADE; | R6: DROP TABLE IF EXISTS rms_contract_basic_information CASCADE;
K7: ="CREATE TABLE IF NOT EXISTS "&K3&" (" -> CREATE TABLE IF NOT EXISTS rms_contract_basic_information ( | N7: ="COMMENT ON TABLE "&K3&" IS '"&G3&"';" -> COMMENT ON TABLE rms_contract_basic_information IS 'b_hjn_rms_契約基本情報'; | R7: CREATE TABLE IF NOT EXISTS rms_contract_basic_information (
A8: pk | B8: SEQ | C8: 項目名 | D8: TYPE | E8: 桁 | F8: 仮名化 | G8: 項目説明およびリスト値 | H8: コードリファレンスリンク | I8: 備考 | J8: 更新日 | K8: id BIGINT GENERATED BY DEFAULT AS IDENTITY, | N8: ="COMMENT ON COLUMN "&$K$3&".id IS 'id';" -> COMMENT ON COLUMN rms_contract_basic_information.id IS 'id'; | R8: id BIGINT GENERATED BY DEFAULT AS IDENTITY,
B9: 1 | C9: オーダ番号 | D9: VARCHAR | E9: 48 | F9: － | K9: order_number | L9: =D9&"("&E9&")," -> VARCHAR(48), | N9: ="COMMENT ON COLUMN "&$K$3&"."&$K9&" IS '"&C9&"';" -> COMMENT ON COLUMN rms_contract_basic_information.order_number IS 'オーダ番号'; | R9: order_number VARCHAR(48),
B10: 2 | C10: オーダ明細行番号 | D10: VARCHAR | E10: 9 | F10: － | G10: 1～999で指定可能 | K10: order_detail_line_number | L10: =D10&"("&E10&")," -> VARCHAR(9), | N10: ="COMMENT ON COLUMN "&$K$3&"."&$K10&" IS '"&C10&"';" -> COMMENT ON COLUMN rms_contract_basic_information.order_detail_line_number IS 'オーダ明細行番号'; | R10: order_detail_line_number VARCHAR(9),
B11: 3 | C11: g3オーダ番号 | D11: VARCHAR | E11: 48 | F11: － | G11: UK | K11: g3_order_number | L11: =D11&"("&E11&")," -> VARCHAR(48), | N11: ="COMMENT ON COLUMN "&$K$3&"."&$K11&" IS '"&C11&"';" -> COMMENT ON COLUMN rms_contract_basic_information.g3_order_number IS 'g3オーダ番号'; | R11: g3_order_number VARCHAR(48),
B12: 4 | C12: g3オーダ回線コード | D12: VARCHAR | E12: 48 | F12: － | G12: UK。 G3のグリッド画面の行番号に相当 | K12: g3_order_line_code | L12: =D12&"("&E12&")," -> VARCHAR(48), | N12: ="COMMENT ON COLUMN "&$K$3&"."&$K12&" IS '"&C12&"';" -> COMMENT ON COLUMN rms_contract_basic_information.g3_order_line_code IS 'g3オーダ回線コード'; | R12: g3_order_line_code VARCHAR(48),
B13: 5 | C13: s# | D13: VARCHAR | E13: 30 | F13: － | K13: ssharp | L13: =D13&"("&E13&")," -> VARCHAR(30), | N13: ="COMMENT ON COLUMN "&$K$3&"."&$K13&" IS '"&C13&"';" -> COMMENT ON COLUMN rms_contract_basic_information.ssharp IS 's#'; | R13: ssharp VARCHAR(30),
B14: 6 | C14: b# | D14: VARCHAR | E14: 30 | F14: － | G14: 洗替処理にてB#を更新 | K14: bsharp | L14: =D14&"("&E14&")," -> VARCHAR(30), | N14: ="COMMENT ON COLUMN "&$K$3&"."&$K14&" IS '"&C14&"';" -> COMMENT ON COLUMN rms_contract_basic_information.bsharp IS 'b#'; | R14: bsharp VARCHAR(30),
B15: 7 | C15: 機種契約s# | D15: VARCHAR | E15: 30 | F15: － | G15: ハイフンの場合 回線契約のみ nullの場合 新規、MNP等、開通前(COPから機種情報が払い出される前) | K15: model_contract_ssharp | L15: =D15&"("&E15&")," -> VARCHAR(30), | N15: ="COMMENT ON COLUMN "&$K$3&"."&$K15&" IS '"&C15&"';" -> COMMENT ON COLUMN rms_contract_basic_information.model_contract_ssharp IS '機種契約s#'; | R15: model_contract_ssharp VARCHAR(30),
B16: 8 | C16: 機種契約b# | D16: VARCHAR | E16: 30 | F16: － | G16: ハイフンの場合 回線契約のみ nullの場合 新規、MNP等、開通前(COPから機種情報が払い出される前) | K16: model_contract_bsharp | L16: =D16&"("&E16&")," -> VARCHAR(30), | N16: ="COMMENT ON COLUMN "&$K$3&"."&$K16&" IS '"&C16&"';" -> COMMENT ON COLUMN rms_contract_basic_information.model_contract_bsharp IS '機種契約b#'; | R16: model_contract_bsharp VARCHAR(30),
B17: 9 | C17: 群番号 | D17: VARCHAR | E17: 6 | F17: － | G17: 毎回、BC洗替によりセット。 10：10群 20：20群 30：30群 70：70群 80：業務用 90：VPNグループ用 | K17: group_number | L17: =D17&"("&E17&")," -> VARCHAR(6), | N17: ="COMMENT ON COLUMN "&$K$3&"."&$K17&" IS '"&C17&"';" -> COMMENT ON COLUMN rms_contract_basic_information.group_number IS '群番号'; | R17: group_number VARCHAR(6),
B18: 10 | C18: カタログ品目コード | D18: VARCHAR | E18: 45 | F18: － | G18: コード変換はカタログ品目マスタ参照 | K18: catalog_item_code | L18: =D18&"("&E18&")," -> VARCHAR(45), | N18: ="COMMENT ON COLUMN "&$K$3&"."&$K18&" IS '"&C18&"';" -> COMMENT ON COLUMN rms_contract_basic_information.catalog_item_code IS 'カタログ品目コード'; | R18: catalog_item_code VARCHAR(45),
B19: 11 | C19: カタログ品目コード名 | D19: VARCHAR | E19: 450 | F19: － | G19: カタログ品目マスタ[品目略称] | K19: catalog_item_code_name | L19: =D19&"("&E19&")," -> VARCHAR(450), | N19: ="COMMENT ON COLUMN "&$K$3&"."&$K19&" IS '"&C19&"';" -> COMMENT ON COLUMN rms_contract_basic_information.catalog_item_code_name IS 'カタログ品目コード名'; | R19: catalog_item_code_name VARCHAR(450),
B20: 12 | C20: 変換後カタログ品目cd | D20: VARCHAR | E20: 45 | F20: － | G20: コード変換はカタログ品目マスタ参照 | K20: converted_catalog_item_cd | L20: =D20&"("&E20&")," -> VARCHAR(45), | N20: ="COMMENT ON COLUMN "&$K$3&"."&$K20&" IS '"&C20&"';" -> COMMENT ON COLUMN rms_contract_basic_information.converted_catalog_item_cd IS '変換後カタログ品目cd'; | R20: converted_catalog_item_cd VARCHAR(45),
B21: 13 | C21: 変換後catalogs品目cd名 | D21: VARCHAR | E21: 450 | F21: － | G21: カタログ品目マスタ[品目略称] | K21: converted_catalog_item_cd_name | L21: =D21&"("&E21&")," -> VARCHAR(450), | N21: ="COMMENT ON COLUMN "&$K$3&"."&$K21&" IS '"&C21&"';" -> COMMENT ON COLUMN rms_contract_basic_information.converted_catalog_item_cd_name IS '変換後catalogs品目cd名'; | R21: converted_catalog_item_cd_name VARCHAR(450),
B22: 14 | C22: 色 | D22: VARCHAR | E22: 1800 | F22: － | G22: UTF全角。 画面では利用しない。 | K22: color | L22: =D22&"("&E22&")," -> VARCHAR(1800), | N22: ="COMMENT ON COLUMN "&$K$3&"."&$K22&" IS '"&C22&"';" -> COMMENT ON COLUMN rms_contract_basic_information.color IS '色'; | R22: color VARCHAR(1800),
B23: 15 | C23: 旧移動機販売方法 | D23: VARCHAR | E23: 6 | F23: － | G23: 0：請求書支払い 1：通話料同時請求 2：無償 3：割賦 4：通常 5：代引き 6：レンタル | K23: old_mobile_device_sales_method | L23: =D23&"("&E23&")," -> VARCHAR(6), | N23: ="COMMENT ON COLUMN "&$K$3&"."&$K23&" IS '"&C23&"';" -> COMMENT ON COLUMN rms_contract_basic_information.old_mobile_device_sales_method IS '旧移動機販売方法'; | R23: old_mobile_device_sales_method VARCHAR(6),
B24: 16 | C24: 納品先社名 | D24: VARCHAR | E24: 2295 | F24: － | G24: UTF全角 | K24: delivery_company_name | L24: =D24&"("&E24&")," -> VARCHAR(2295), | N24: ="COMMENT ON COLUMN "&$K$3&"."&$K24&" IS '"&C24&"';" -> COMMENT ON COLUMN rms_contract_basic_information.delivery_company_name IS '納品先社名'; | R24: delivery_company_name VARCHAR(2295),
B25: 17 | C25: 納品先部署名 | D25: VARCHAR | E25: 270 | F25: － | G25: UTF全角 | K25: delivery_department_name | L25: =D25&"("&E25&")," -> VARCHAR(270), | N25: ="COMMENT ON COLUMN "&$K$3&"."&$K25&" IS '"&C25&"';" -> COMMENT ON COLUMN rms_contract_basic_information.delivery_department_name IS '納品先部署名'; | R25: delivery_department_name VARCHAR(270),
... B27: 19 | C27: 納品先ご担当者名カナ | D27: VARCHAR | E27: 540 | F27: － | G27: UTF全角 | K27: delivery_contact_name_kana | L27: =D27&"("&E27&")," -> VARCHAR(540), | N27: ="COMMENT ON COLUMN "&$K$3&"."&$K27&" IS '"&C27&"';" -> COMMENT ON COLUMN rms_contract_basic_information.delivery_contact_name_kana IS '納品先ご担当者名カナ'; | R27: delivery_contact_name_kana VARCHAR(540),
B28: 20 | C28: 納品先郵便番号 | D28: VARCHAR | E28: 21 | F28: － | K28: delivery_postal_code | L28: =D28&"("&E28&")," -> VARCHAR(21), | N28: ="COMMENT ON COLUMN "&$K$3&"."&$K28&" IS '"&C28&"';" -> COMMENT ON COLUMN rms_contract_basic_information.delivery_postal_code IS '納品先郵便番号'; | R28: delivery_postal_code VARCHAR(21),
B29: 21 | C29: 納品先都道府県 | D29: VARCHAR | E29: 90 | F29: － | G29: UTF全角 | K29: delivery_prefecture | L29: =D29&"("&E29&")," -> VARCHAR(90), | N29: ="COMMENT ON COLUMN "&$K$3&"."&$K29&" IS '"&C29&"';" -> COMMENT ON COLUMN rms_contract_basic_information.delivery_prefecture IS '納品先都道府県'; | R29: delivery_prefecture VARCHAR(90),
B30: 22 | C30: 納品先市区郡町村 | D30: VARCHAR | E30: 720 | F30: － | G30: UTF全角 | K30: delivery_address_city | L30: =D30&"("&E30&")," -> VARCHAR(720), | N30: ="COMMENT ON COLUMN "&$K$3&"."&$K30&" IS '"&C30&"';" -> COMMENT ON COLUMN rms_contract_basic_information.delivery_address_city IS '納品先市区郡町村'; | R30: delivery_address_city VARCHAR(720),
B31: 23 | C31: 納品先通称大字 | D31: VARCHAR | E31: 720 | F31: － | G31: UTF全角 | K31: delivery_address_oaza | L31: =D31&"("&E31&")," -> VARCHAR(720), | N31: ="COMMENT ON COLUMN "&$K$3&"."&$K31&" IS '"&C31&"';" -> COMMENT ON COLUMN rms_contract_basic_information.delivery_address_oaza IS '納品先通称大字'; | R31: delivery_address_oaza VARCHAR(720),
B32: 24 | C32: 納品先丁目字等 | D32: VARCHAR | E32: 720 | F32: － | G32: UTF全角 | K32: delivery_address_block | L32: =D32&"("&E32&")," -> VARCHAR(720), | N32: ="COMMENT ON COLUMN "&$K$3&"."&$K32&" IS '"&C32&"';" -> COMMENT ON COLUMN rms_contract_basic_information.delivery_address_block IS '納品先丁目字等'; | R32: delivery_address_block VARCHAR(720),
B33: 25 | C33: 納品先番地 | D33: VARCHAR | E33: 720 | F33: － | G33: UTF全角 | K33: delivery_address_street | L33: =D33&"("&E33&")," -> VARCHAR(720), | N33: ="COMMENT ON COLUMN "&$K$3&"."&$K33&" IS '"&C33&"';" -> COMMENT ON COLUMN rms_contract_basic_information.delivery_address_street IS '納品先番地'; | R33: delivery_address_street VARCHAR(720),
B34: 26 | C34: 納品先_部屋no | D34: VARCHAR | E34: 2295 | F34: － | G34: UTF全角 | K34: delivery_room_no | L34: =D34&"("&E34&")," -> VARCHAR(2295), | N34: ="COMMENT ON COLUMN "&$K$3&"."&$K34&" IS '"&C34&"';" -> COMMENT ON COLUMN rms_contract_basic_information.delivery_room_no IS '納品先_部屋no'; | R34: delivery_room_no VARCHAR(2295),
B35: 27 | C35: 納品先電話番号 | D35: VARCHAR | E35: 117 | F35: － | G35: UTF全角 | K35: delivery_phone_number | L35: =D35&"("&E35&")," -> VARCHAR(117), | N35: ="COMMENT ON COLUMN "&$K$3&"."&$K35&" IS '"&C35&"';" -> COMMENT ON COLUMN rms_contract_basic_information.delivery_phone_number IS '納品先電話番号'; | R35: delivery_phone_number VARCHAR(117),
B36: 28 | C36: 回線契約ステータス | D36: VARCHAR | E36: 6 | F36: － | G36: コード変換はコードマスタ「大区分コード：106」参照 | K36: line_contract_status | L36: =D36&"("&E36&")," -> VARCHAR(6), | N36: ="COMMENT ON COLUMN "&$K$3&"."&$K36&" IS '"&C36&"';" -> COMMENT ON COLUMN rms_contract_basic_information.line_contract_status IS '回線契約ステータス'; | R36: line_contract_status VARCHAR(6),
B37: 29 | C37: 回線契約ステータス名 | D37: VARCHAR | E37: 300 | F37: － | G37: コードマスタの[内容] 「大区分コード：106」 | K37: line_contract_status_name | L37: =D37&"("&E37&")," -> VARCHAR(300), | N37: ="COMMENT ON COLUMN "&$K$3&"."&$K37&" IS '"&C37&"';" -> COMMENT ON COLUMN rms_contract_basic_information.line_contract_status_name IS '回線契約ステータス名'; | R37: line_contract_status_name VARCHAR(300),
B38: 30 | C38: 利用期間 | D38: DECIMAL | E38: 9 | F38: － | G38: 単位：ヶ月 | K38: usage_period | L38: =D38&"("&E38&")," -> DECIMAL(9), | N38: ="COMMENT ON COLUMN "&$K$3&"."&$K38&" IS '"&C38&"';" -> COMMENT ON COLUMN rms_contract_basic_information.usage_period IS '利用期間'; | R38: usage_period DECIMAL(9),
B39: 31 | C39: 充当ポイント | D39: DECIMAL | E39: 30 | F39: － | G39: レンタル登録事務手数料に対する充当ポイント。 ※オーダ確定時の情報 | K39: allocation_points | L39: =D39&"("&E39&")," -> DECIMAL(30), | N39: ="COMMENT ON COLUMN "&$K$3&"."&$K39&" IS '"&C39&"';" -> COMMENT ON COLUMN rms_contract_basic_information.allocation_points IS '充当ポイント'; | R39: allocation_points DECIMAL(30),
B40: 32 | C40: 契約ステータス | D40: VARCHAR | E40: 6 | F40: － | G40: コード変換はコードマスタ「大区分コード：107」参照 | K40: contract_status | L40: =D40&"("&E40&")," -> VARCHAR(6), | N40: ="COMMENT ON COLUMN "&$K$3&"."&$K40&" IS '"&C40&"';" -> COMMENT ON COLUMN rms_contract_basic_information.contract_status IS '契約ステータス'; | R40: contract_status VARCHAR(6),
... B67: 59 | C67: 更新ユーザ | D67: VARCHAR | E67: 96 | F67: － | G67: 初回登録時及び更新時に担当者コード又はプログラムIDをセット。 | K67: updated_user | L67: =D67&"("&E67&")," -> VARCHAR(96), | N67: ="COMMENT ON COLUMN "&$K$3&"."&$K67&" IS '"&C67&"';" -> COMMENT ON COLUMN rms_contract_basic_information.updated_user IS '更新ユーザ'; | R67: updated_user VARCHAR(96),
B68: 60 | C68: summit統一企業番号 | D68: VARCHAR | E68: 48 | F68: － | K68: summit_unified_company_number | L68: =D68&"("&E68&")," -> VARCHAR(48), | N68: ="COMMENT ON COLUMN "&$K$3&"."&$K68&" IS '"&C68&"';" -> COMMENT ON COLUMN rms_contract_basic_information.summit_unified_company_number IS 'summit統一企業番号'; | R68: summit_unified_company_number VARCHAR(48),
B69: 61 | C69: summit統一企業名 | D69: VARCHAR | E69: 2295 | F69: － | G69: UTF全角 | K69: summit_unified_company_name | L69: =D69&"("&E69&")," -> VARCHAR(2295), | N69: ="COMMENT ON COLUMN "&$K$3&"."&$K69&" IS '"&C69&"';" -> COMMENT ON COLUMN rms_contract_basic_information.summit_unified_company_name IS 'summit統一企業名'; | R69: summit_unified_company_name VARCHAR(2295),
B70: 62 | C70: summit名義変更日 | D70: VARCHAR | E70: 24 | F70: － | G70: YYYYMMDD形式 | K70: summit_owner_change_date | L70: =D70&"("&E70&")," -> VARCHAR(24), | N70: ="COMMENT ON COLUMN "&$K$3&"."&$K70&" IS '"&C70&"';" -> COMMENT ON COLUMN rms_contract_basic_information.summit_owner_change_date IS 'summit名義変更日'; | R70: summit_owner_change_date VARCHAR(24),
B71: 63 | C71: 機種変更日 | D71: VARCHAR | E71: 24 | F71: － | G71: YYYYMMDD形式 | K71: model_change_date | L71: =D71&"("&E71&")," -> VARCHAR(24), | N71: ="COMMENT ON COLUMN "&$K$3&"."&$K71&" IS '"&C71&"';" -> COMMENT ON COLUMN rms_contract_basic_information.model_change_date IS '機種変更日'; | R71: model_change_date VARCHAR(24),
B72: 64 | C72: summit名称変更日 | D72: VARCHAR | E72: 24 | F72: － | G72: YYYYMMDD形式 | K72: summit_name_change_date | L72: =D72&"("&E72&")," -> VARCHAR(24), | N72: ="COMMENT ON COLUMN "&$K$3&"."&$K72&" IS '"&C72&"';" -> COMMENT ON COLUMN rms_contract_basic_information.summit_name_change_date IS 'summit名称変更日'; | R72: summit_name_change_date VARCHAR(24),
B73: 65 | C73: 転レンタル契約 | D73: VARCHAR | E73: 6 | F73: － | G73: コード変換はコードマスタ「大区分コード：112」参照 | K73: rental_contract_substitution | L73: =D73&"("&E73&")," -> VARCHAR(6), | N73: ="COMMENT ON COLUMN "&$K$3&"."&$K73&" IS '"&C73&"';" -> COMMENT ON COLUMN rms_contract_basic_information.rental_contract_substitution IS '転レンタル契約'; | R73: rental_contract_substitution VARCHAR(6),
B74: 66 | C74: 転レンタル契約名 | D74: VARCHAR | E74: 300 | F74: － | G74: コードマスタの[内容] 「大区分コード：112」 | K74: rental_contract_substitution_name | L74: =D74&"("&E74&")," -> VARCHAR(300), | N74: ="COMMENT ON COLUMN "&$K$3&"."&$K74&" IS '"&C74&"';" -> COMMENT ON COLUMN rms_contract_basic_information.rental_contract_substitution_name IS '転レンタル契約名'; | R74: rental_contract_substitution_name VARCHAR(300),
B75: 67 | C75: 再レンタル回数 | D75: DECIMAL | E75: 9 | F75: － | G75: 再ﾚﾝﾀﾙ契約した回数 | K75: number_of_re_rentals | L75: =D75&"("&E75&")," -> DECIMAL(9), | N75: ="COMMENT ON COLUMN "&$K$3&"."&$K75&" IS '"&C75&"';" -> COMMENT ON COLUMN rms_contract_basic_information.number_of_re_rentals IS '再レンタル回数'; | R75: number_of_re_rentals DECIMAL(9),
B76: 68 | C76: 再レンタル契約開始日 | D76: VARCHAR | E76: 24 | F76: － | G76: YYYYMMDD形式 | K76: re_rental_contract_start_date | L76: =D76&"("&E76&")," -> VARCHAR(24), | N76: ="COMMENT ON COLUMN "&$K$3&"."&$K76&" IS '"&C76&"';" -> COMMENT ON COLUMN rms_contract_basic_information.re_rental_contract_start_date IS '再レンタル契約開始日'; | R76: re_rental_contract_start_date VARCHAR(24),
B77: 69 | C77: ポイント利用可否区分 | D77: VARCHAR | E77: 3 | F77: － | G77: 0：ポイント利用不可 1：ポイント利用可 | K77: point_availability_category | L77: =D77&"("&E77&")," -> VARCHAR(3), | N77: ="COMMENT ON COLUMN "&$K$3&"."&$K77&" IS '"&C77&"';" -> COMMENT ON COLUMN rms_contract_basic_information.point_availability_category IS 'ポイント利用可否区分'; | R77: point_availability_category VARCHAR(3),
B78: 70 | C78: ポイント利用可否kbn名 | D78: VARCHAR | E78: 3 | F78: － | G78: ↑の日本語名 | K78: point_availability_kbn_name | L78: =D78&"("&E78&")," -> VARCHAR(3), | N78: ="COMMENT ON COLUMN "&$K$3&"."&$K78&" IS '"&C78&"';" -> COMMENT ON COLUMN rms_contract_basic_information.point_availability_kbn_name IS 'ポイント利用可否kbn名'; | R78: point_availability_kbn_name VARCHAR(3),
B79: 71 | C79: レンタル用途 | D79: VARCHAR | E79: 3 | F79: － | G79: コード変換はコードマスタ「大区分コード：115」参照 | K79: rental_purpose | L79: =D79&"("&E79&")," -> VARCHAR(3), | N79: ="COMMENT ON COLUMN "&$K$3&"."&$K79&" IS '"&C79&"';" -> COMMENT ON COLUMN rms_contract_basic_information.rental_purpose IS 'レンタル用途'; | R79: rental_purpose VARCHAR(3),
B80: 72 | C80: レンタル用途名 | D80: VARCHAR | E80: 300 | F80: － | G80: コードマスタの[内容] 「大区分コード：115」 | K80: rental_purpose_name | L80: =D80&"("&E80&")," -> VARCHAR(300), | N80: ="COMMENT ON COLUMN "&$K$3&"."&$K80&" IS '"&C80&"';" -> COMMENT ON COLUMN rms_contract_basic_information.rental_purpose_name IS 'レンタル用途名'; | R80: rental_purpose_name VARCHAR(300),
... B84: 76 | C84: キャンペーンコード | D84: VARCHAR | E84: 36 | F84: － | G84: キャンペーンコードを保持 | K84: campaign_code | L84: =D84&"("&E84&")," -> VARCHAR(36), | N84: ="COMMENT ON COLUMN "&$K$3&"."&$K84&" IS '"&C84&"';" -> COMMENT ON COLUMN rms_contract_basic_information.campaign_code IS 'キャンペーンコード'; | R84: campaign_code VARCHAR(36),
B85: 77 | C85: レンタル契約形態 | D85: VARCHAR | E85: 3 | F85: － | J85: 2024/05/22 追加 | K85: rental_contract_type | L85: =D85&"("&E85&")," -> VARCHAR(3), | N85: ="COMMENT ON COLUMN "&$K$3&"."&$K85&" IS '"&C85&"';" -> COMMENT ON COLUMN rms_contract_basic_information.rental_contract_type IS 'レンタル契約形態'; | R85: rental_contract_type VARCHAR(3),
B86: 78 | C86: 契約年月 | D86: VARCHAR | E86: 18 | F86: － | G86: 累積時の処理月 | J86: 2024/05/22 追加 | K86: contract_year_and_month | L86: =D86&"("&E86&")," -> VARCHAR(18), | N86: ="COMMENT ON COLUMN "&$K$3&"."&$K86&" IS '"&C86&"';" -> COMMENT ON COLUMN rms_contract_basic_information.contract_year_and_month IS '契約年月'; | R86: contract_year_and_month VARCHAR(18),
B87: 79 | C87: 端末取得原価 | D87: DECIMAL | E87: 9,0 | F87: － | G87: 契約年月の端末コスト | J87: 2024/05/22 追加 | K87: device_acquisition_cost | L87: =D87&"("&E87&")," -> DECIMAL(9,0), | N87: ="COMMENT ON COLUMN "&$K$3&"."&$K87&" IS '"&C87&"';" -> COMMENT ON COLUMN rms_contract_basic_information.device_acquisition_cost IS '端末取得原価'; | R87: device_acquisition_cost DECIMAL(9,0),
B88: 80 | C88: 端末取得原価分割計上額 | D88: DECIMAL | E88: 11,2 | F88: － | G88: 端末コスト÷契約月数（小数点以下第3位四捨五入） | J88: 2024/05/22 追加 | K88: device_acquisition_cost_amount_recorded | L88: =D88&"("&E88&")," -> DECIMAL(11,2), | N88: ="COMMENT ON COLUMN "&$K$3&"."&$K88&" IS '"&C88&"';" -> COMMENT ON COLUMN rms_contract_basic_information.device_acquisition_cost_amount_recorded IS '端末取得原価分割計上額'; | R88: device_acquisition_cost_amount_recorded DECIMAL(11,2),
K89: ="CONSTRAINT pk_"&K3&" PRIMARY KEY (id));" -> CONSTRAINT pk_rms_contract_basic_information PRIMARY KEY (id)); | R89: CONSTRAINT pk_rms_contract_basic_information PRIMARY KEY (id));
R90: COMMENT ON TABLE rms_contract_basic_information IS 'b_hjn_rms_契約基本情報';
R91: COMMENT ON COLUMN rms_contract_basic_information.id IS 'id';
R92: COMMENT ON COLUMN rms_contract_basic_information.order_number IS 'オーダ番号';
R93: COMMENT ON COLUMN rms_contract_basic_information.order_detail_line_number IS 'オーダ明細行番号';
R94: COMMENT ON COLUMN rms_contract_basic_information.g3_order_number IS 'g3オーダ番号';
R95: COMMENT ON COLUMN rms_contract_basic_information.g3_order_line_code IS 'g3オーダ回線コード';
R96: COMMENT ON COLUMN rms_contract_basic_information.ssharp IS 's#';
R97: COMMENT ON COLUMN rms_contract_basic_information.bsharp IS 'b#';
R98: COMMENT ON COLUMN rms_contract_basic_information.model_contract_ssharp IS '機種契約s#';
R99: COMMENT ON COLUMN rms_contract_basic_information.model_contract_bsharp IS '機種契約b#';
R100: COMMENT ON COLUMN rms_contract_basic_information.group_number IS '群番号';
R101: COMMENT ON COLUMN rms_contract_basic_information.catalog_item_code IS 'カタログ品目コード';
... R171: COMMENT ON COLUMN rms_contract_basic_information.device_acquisition_cost_amount_recorded IS '端末取得原価分割計上額';

Sheet (RMS)契約料金情報
F2: 種別 | G2: DWH公開名 | H2: 旧DWH公開名 | I2: 統合テーブルID | J2: スキーマ
F3: ビュー | G3: b_hjn_rms_契約料金情報 | I3: V004573 | J3: user_l2_prvl | K3: rms_contract_fee_information
F4: データ概要：
F5: オーダー番号毎に、契約料金情報等の情報を持つ
K6: ="DROP TABLE IF EXISTS "&K3&" CASCADE;" -> DROP TABLE IF EXISTS rms_contract_fee_information CASCADE; | R6: DROP TABLE IF EXISTS rms_contract_fee_information CASCADE;
K7: ="CREATE TABLE IF NOT EXISTS "&K3&" (" -> CREATE TABLE IF NOT EXISTS rms_contract_fee_information ( | N7: ="COMMENT ON TABLE "&K3&" IS '"&G3&"';" -> COMMENT ON TABLE rms_contract_fee_information IS 'b_hjn_rms_契約料金情報'; | R7: CREATE TABLE IF NOT EXISTS rms_contract_fee_information (
A8: pk | B8: SEQ | C8: 項目名 | D8: TYPE | E8: 桁 | F8: 仮名化 | G8: 項目説明およびリスト値 | H8: コードリファレンスリンク | I8: 備考 | J8: 更新日 | K8: id BIGINT GENERATED BY DEFAULT AS IDENTITY, | N8: ="COMMENT ON COLUMN "&$K$3&".id IS 'id';" -> COMMENT ON COLUMN rms_contract_fee_information.id IS 'id'; | R8: id BIGINT GENERATED BY DEFAULT AS IDENTITY,
B9: 1 | C9: オーダ番号 | D9: VARCHAR | E9: 48 | F9: － | K9: order_number | L9: =D9&"("&E9&")," -> VARCHAR(48), | N9: ="COMMENT ON COLUMN "&$K$3&"."&$K9&" IS '"&C9&"';" -> COMMENT ON COLUMN rms_contract_fee_information.order_number IS 'オーダ番号'; | R9: order_number VARCHAR(48),
B10: 2 | C10: オーダ明細行番号 | D10: VARCHAR | E10: 9 | F10: － | K10: order_detail_line_number | L10: =D10&"("&E10&")," -> VARCHAR(9), | N10: ="COMMENT ON COLUMN "&$K$3&"."&$K10&" IS '"&C10&"';" -> COMMENT ON COLUMN rms_contract_fee_information.order_detail_line_number IS 'オーダ明細行番号'; | R10: order_detail_line_number VARCHAR(9),
B11: 3 | C11: オーダ料金明細行番号 | D11: VARCHAR | E11: 9 | F11: － | K11: order_charge_detail_line_number | L11: =D11&"("&E11&")," -> VARCHAR(9), | N11: ="COMMENT ON COLUMN "&$K$3&"."&$K11&" IS '"&C11&"';" -> COMMENT ON COLUMN rms_contract_fee_information.order_charge_detail_line_number IS 'オーダ料金明細行番号'; | R11: order_charge_detail_line_number VARCHAR(9),
B12: 4 | C12: 料金項目id | D12: VARCHAR | E12: 18 | F12: － | K12: charge_item_id | L12: =D12&"("&E12&")," -> VARCHAR(18), | N12: ="COMMENT ON COLUMN "&$K$3&"."&$K12&" IS '"&C12&"';" -> COMMENT ON COLUMN rms_contract_fee_information.charge_item_id IS '料金項目id'; | R12: charge_item_id VARCHAR(18),
B13: 5 | C13: 料金項目名称 | D13: VARCHAR | E13: 600 | F13: － | G13: UTF全角。 画面表示用の料金項目名 | K13: charge_item_name | L13: =D13&"("&E13&")," -> VARCHAR(600), | N13: ="COMMENT ON COLUMN "&$K$3&"."&$K13&" IS '"&C13&"';" -> COMMENT ON COLUMN rms_contract_fee_information.charge_item_name IS '料金項目名称'; | R13: charge_item_name VARCHAR(600),
B14: 6 | C14: 料金項目分類コード | D14: VARCHAR | E14: 9 | F14: － | G14: コード変換はコードマスタ「大区分コード：406」参照 | K14: charge_item_classification_code | L14: =D14&"("&E14&")," -> VARCHAR(9), | N14: ="COMMENT ON COLUMN "&$K$3&"."&$K14&" IS '"&C14&"';" -> COMMENT ON COLUMN rms_contract_fee_information.charge_item_classification_code IS '料金項目分類コード'; | R14: charge_item_classification_code VARCHAR(9),
B15: 7 | C15: 料金項目分類コード名 | D15: VARCHAR | E15: 300 | F15: － | G15: コードマスタの[内容] 「大区分コード：406」 | K15: charge_item_classification_code_name | L15: =D15&"("&E15&")," -> VARCHAR(300), | N15: ="COMMENT ON COLUMN "&$K$3&"."&$K15&" IS '"&C15&"';" -> COMMENT ON COLUMN rms_contract_fee_information.charge_item_classification_code_name IS '料金項目分類コード名'; | R15: charge_item_classification_code_name VARCHAR(300),
B16: 8 | C16: 表示ソート制御 | D16: DECIMAL | E16: 12 | F16: － | G16: 料金マスタのソート情報を保持 | K16: display_sort_control | L16: =D16&"("&E16&")," -> DECIMAL(12), | N16: ="COMMENT ON COLUMN "&$K$3&"."&$K16&" IS '"&C16&"';" -> COMMENT ON COLUMN rms_contract_fee_information.display_sort_control IS '表示ソート制御'; | R16: display_sort_control DECIMAL(12),
B17: 9 | C17: 契約開始日 | D17: VARCHAR | E17: 24 | F17: － | G17: YYYYMMDD形式 | K17: contract_start_date | L17: =D17&"("&E17&")," -> VARCHAR(24), | N17: ="COMMENT ON COLUMN "&$K$3&"."&$K17&" IS '"&C17&"';" -> COMMENT ON COLUMN rms_contract_fee_information.contract_start_date IS '契約開始日'; | R17: contract_start_date VARCHAR(24),
B18: 10 | C18: 契約終了日 | D18: VARCHAR | E18: 24 | F18: － | G18: YYYYMMDD形式 | K18: contract_end_date | L18: =D18&"("&E18&")," -> VARCHAR(24), | N18: ="COMMENT ON COLUMN "&$K$3&"."&$K18&" IS '"&C18&"';" -> COMMENT ON COLUMN rms_contract_fee_information.contract_end_date IS '契約終了日'; | R18: contract_end_date VARCHAR(24),
B19: 11 | C19: 課金開始日 | D19: VARCHAR | E19: 24 | F19: － | G19: YYYYMMDD形式。 月額一時金区分が月額の場合のみ指定する。 レンタル契約情報としての課金開始日。 ※ＧＩＳＵＮからのＩＦにより自動でセットされる。（画面変更不可） | K19: billing_start_date | L19: =D19&"("&E19&")," -> VARCHAR(24), | N19: ="COMMENT ON COLUMN "&$K$3&"."&$K19&" IS '"&C19&"';" -> COMMENT ON COLUMN rms_contract_fee_information.billing_start_date IS '課金開始日'; | R19: billing_start_date VARCHAR(24),
B20: 12 | C20: 課金終了日 | D20: VARCHAR | E20: 24 | F20: － | G20: YYYYMMDD形式。 月額一時金区分が月額の場合のみ指定する。 レンタル契約情報としての課金終了日。 （解約時には、レンタル料金情報の課金終了日は更新せずに、 本項目のみを更新する）。 ※ＧＩＳＵＮからのＩＦにより自動でセットされる。（画面変更不可） | K20: billing_end_date | L20: =D20&"("&E20&")," -> VARCHAR(24), | N20: ="COMMENT ON COLUMN "&$K$3&"."&$K20&" IS '"&C20&"';" -> COMMENT ON COLUMN rms_contract_fee_information.billing_end_date IS '課金終了日'; | R20: billing_end_date VARCHAR(24),
B21: 13 | C21: 料金情報登録日 | D21: VARCHAR | E21: 24 | F21: － | G21: YYYYMMDD形式。 バッチ処理にて解約違約金をセットするタイミングで登録日をセット。 バッチ処理にて月初の請求処理前の違約金は翌月請求とする | K21: charge_information_registration_date | L21: =D21&"("&E21&")," -> VARCHAR(24), | N21: ="COMMENT ON COLUMN "&$K$3&"."&$K21&" IS '"&C21&"';" -> COMMENT ON COLUMN rms_contract_fee_information.charge_information_registration_date IS '料金情報登録日'; | R21: charge_information_registration_date VARCHAR(24),
B22: 14 | C22: 月額一時金区分 | D22: VARCHAR | E22: 3 | F22: － | G22: コード変換はコードマスタ「大区分コード：401」参照 | K22: monthly_lump_sum_category | L22: =D22&"("&E22&")," -> VARCHAR(3), | N22: ="COMMENT ON COLUMN "&$K$3&"."&$K22&" IS '"&C22&"';" -> COMMENT ON COLUMN rms_contract_fee_information.monthly_lump_sum_category IS '月額一時金区分'; | R22: monthly_lump_sum_category VARCHAR(3),
B23: 15 | C23: 月額一時金区分名 | D23: VARCHAR | E23: 300 | F23: － | G23: コードマスタの[内容] 「大区分コード：401」 | K23: monthly_lump_sum_category_name | L23: =D23&"("&E23&")," -> VARCHAR(300), | N23: ="COMMENT ON COLUMN "&$K$3&"."&$K23&" IS '"&C23&"';" -> COMMENT ON COLUMN rms_contract_fee_information.monthly_lump_sum_category_name IS '月額一時金区分名'; | R23: monthly_lump_sum_category_name VARCHAR(300),
B24: 16 | C24: 税区分 | D24: VARCHAR | E24: 3 | F24: － | G24: コード変換はコードマスタ「大区分コード：301」参照 | K24: tax_category | L24: =D24&"("&E24&")," -> VARCHAR(3), | N24: ="COMMENT ON COLUMN "&$K$3&"."&$K24&" IS '"&C24&"';" -> COMMENT ON COLUMN rms_contract_fee_information.tax_category IS '税区分'; | R24: tax_category VARCHAR(3),
... B41: 33 | C41: ポイント利用済みflg名 | D41: VARCHAR | E41: 3 | F41: － | G41: ↑の日本語名 | K41: point_used_flag_name | L41: =D41&"("&E41&")," -> VARCHAR(3), | N41: ="COMMENT ON COLUMN "&$K$3&"."&$K41&" IS '"&C41&"';" -> COMMENT ON COLUMN rms_contract_fee_information.point_used_flag_name IS 'ポイント利用済みflg名'; | R41: point_used_flag_name VARCHAR(3),
K42: ="CONSTRAINT pk_"&K3&" PRIMARY KEY (id));" -> CONSTRAINT pk_rms_contract_fee_information PRIMARY KEY (id)); | R42: CONSTRAINT pk_rms_contract_fee_information PRIMARY KEY (id));
R43: COMMENT ON TABLE rms_contract_fee_information IS 'b_hjn_rms_契約料金情報';
R44: COMMENT ON COLUMN rms_contract_fee_information.id IS 'id';
R45: COMMENT ON COLUMN rms_contract_fee_information.order_number IS 'オーダ番号';
R46: COMMENT ON COLUMN rms_contract_fee_information.order_detail_line_number IS 'オーダ明細行番号';
R47: COMMENT ON COLUMN rms_contract_fee_information.order_charge_detail_line_number IS 'オーダ料金明細行番号';
R48: COMMENT ON COLUMN rms_contract_fee_information.charge_item_id IS '料金項目id';
R49: COMMENT ON COLUMN rms_contract_fee_information.charge_item_name IS '料金項目名称';
R50: COMMENT ON COLUMN rms_contract_fee_information.charge_item_classification_code IS '料金項目分類コード';
R51: COMMENT ON COLUMN rms_contract_fee_information.charge_item_classification_code_name IS '料金項目分類コード名';
R52: COMMENT ON COLUMN rms_contract_fee_information.display_sort_control IS '表示ソート制御';
R53: COMMENT ON COLUMN rms_contract_fee_information.contract_start_date IS '契約開始日';
R54: COMMENT ON COLUMN rms_contract_fee_information.contract_end_date IS '契約終了日';
... R77: COMMENT ON COLUMN rms_contract_fee_information.point_used_flag_name IS 'ポイント利用済みflg名';

Sheet (COP)支払情報
F2: 種別 | G2: DWH公開名 | H2: 旧DWH公開名 | I2: 統合テーブルID | J2: スキーマ
F3: ビュー | G3: b_cop_支払情報 | H3: B_支払情報_[権限] | I3: V000604 | J3: user_l2id | K3: cop_payment_information
F4: データ概要：
F5: 支払い方法（窓口、郵便、口振、クレジットなど）を管理。
K6: ="DROP TABLE IF EXISTS "&K3&" CASCADE;" -> DROP TABLE IF EXISTS cop_payment_information CASCADE; | R6: DROP TABLE IF EXISTS cop_payment_information CASCADE;
K7: ="CREATE TABLE IF NOT EXISTS "&K3&" (" -> CREATE TABLE IF NOT EXISTS cop_payment_information ( | N7: ="COMMENT ON TABLE "&K3&" IS '"&G3&"';" -> COMMENT ON TABLE cop_payment_information IS 'b_cop_支払情報'; | R7: CREATE TABLE IF NOT EXISTS cop_payment_information (
A8: pk | B8: SEQ | C8: 項目名 | D8: TYPE | E8: 桁 | F8: 仮名化 | G8: 項目説明およびリスト値 | H8: コードリファレンスリンク | I8: 備考 | J8: 更新日 | K8: id BIGINT GENERATED BY DEFAULT AS IDENTITY, | N8: ="COMMENT ON COLUMN "&$K$3&".id IS 'id';" -> COMMENT ON COLUMN cop_payment_information.id IS 'id'; | R8: id BIGINT GENERATED BY DEFAULT AS IDENTITY,
A9: ○ | B9: 1 | C9: レコード通番 | D9: DECIMAL | E9: 38,0 | F9: － | G9: レコード通番 | I9: X3対応(桁変更) | K9: record_serial_number | L9: =D9&"("&E9&")," -> DECIMAL(38,0), | N9: ="COMMENT ON COLUMN "&$K$3&"."&$K9&" IS '"&C9&"';" -> COMMENT ON COLUMN cop_payment_information.record_serial_number IS 'レコード通番'; | R9: record_serial_number DECIMAL(38,0),
B10: 2 | C10: 請求グループid | D10: VARCHAR | E10: 40 | F10: ○ | G10: 請求グループID(B#) | I10: ・H制御Viewでは仮名加工された値が表示されます | K10: billing_group_id | L10: =D10&"("&E10&")," -> VARCHAR(40), | N10: ="COMMENT ON COLUMN "&$K$3&"."&$K10&" IS '"&C10&"';" -> COMMENT ON COLUMN cop_payment_information.billing_group_id IS '請求グループid'; | R10: billing_group_id VARCHAR(40),
B11: 3 | C11: 有効開始日 | D11: VARCHAR | E11: 16 | F11: － | G11: 有効開始日(YYYYMMDD) | J11: ★項目説明修正(2025/6/24) | K11: effective_start_date | L11: =D11&"("&E11&")," -> VARCHAR(16), | N11: ="COMMENT ON COLUMN "&$K$3&"."&$K11&" IS '"&C11&"';" -> COMMENT ON COLUMN cop_payment_information.effective_start_date IS '有効開始日'; | R11: effective_start_date VARCHAR(16),
G12: 前提：データ投入方法は、システム連携・フロント(GINIE等)経由の2種類がある | L12: =D12&"("&E12&")," -> (), | N12: ="COMMENT ON COLUMN "&$K$3&"."&$K12&" IS '"&C12&"';" -> COMMENT ON COLUMN cop_payment_information. IS ''; | R12: effective_end_date VARCHAR(16),
L13: =D13&"("&E13&")," -> (), | N13: ="COMMENT ON COLUMN "&$K$3&"."&$K13&" IS '"&C13&"';" -> COMMENT ON COLUMN cop_payment_information. IS ''; | R13: deletion_indicator VARCHAR(2),
G14: ・システム連携のデータ | L14: =D14&"("&E14&")," -> (), | N14: ="COMMENT ON COLUMN "&$K$3&"."&$K14&" IS '"&C14&"';" -> COMMENT ON COLUMN cop_payment_information. IS ''; | R14: created_date VARCHAR(16),
G15: 99991231：最新(=継続中)のデータ | L15: =D15&"("&E15&")," -> (), | N15: ="COMMENT ON COLUMN "&$K$3&"."&$K15&" IS '"&C15&"';" -> COMMENT ON COLUMN cop_payment_information. IS ''; | R15: new_code VARCHAR(4),
L16: =D16&"("&E16&")," -> (), | N16: ="COMMENT ON COLUMN "&$K$3&"."&$K16&" IS '"&C16&"';" -> COMMENT ON COLUMN cop_payment_information. IS ''; | R16: billing_payment_method_code VARCHAR(4),
G17: ・GINIE→CCOC経由の支払方法更新時のデータ | L17: =D17&"("&E17&")," -> (), | N17: ="COMMENT ON COLUMN "&$K$3&"."&$K17&" IS '"&C17&"';" -> COMMENT ON COLUMN cop_payment_information. IS ''; | R17: reseller_company_id VARCHAR(10),
G18: 10年後：新規/譲渡でB#新設時で、支払方法が口振/クレでPay easy利用なし（承認IND：N）の場合 | L18: =D18&"("&E18&")," -> (), | N18: ="COMMENT ON COLUMN "&$K$3&"."&$K18&" IS '"&C18&"';" -> COMMENT ON COLUMN cop_payment_information. IS ''; | R18: financial_institution_type_code VARCHAR(4),
G19: 29991230：情報変更（支払方法変更）で、口振/クレでPay easy利用なし（承認IND：N）の場合 | L19: =D19&"("&E19&")," -> (), | N19: ="COMMENT ON COLUMN "&$K$3&"."&$K19&" IS '"&C19&"';" -> COMMENT ON COLUMN cop_payment_information. IS ''; | R19: invoice_type_code VARCHAR(4),
G20: 29991231：B#変更なしの承継で、支払方法が口振/クレでPay easy利用なし（承認IND：N）の場合 | L20: =D20&"("&E20&")," -> (), | N20: ="COMMENT ON COLUMN "&$K$3&"."&$K20&" IS '"&C20&"';" -> COMMENT ON COLUMN cop_payment_information. IS ''; | R20: bank_id VARCHAR(8),
L21: =D21&"("&E21&")," -> (), | N21: ="COMMENT ON COLUMN "&$K$3&"."&$K21&" IS '"&C21&"';" -> COMMENT ON COLUMN cop_payment_information. IS ''; | R21: bank_branch_id VARCHAR(6),
G22: ・その他のデータ | L22: =D22&"("&E22&")," -> (), | N22: ="COMMENT ON COLUMN "&$K$3&"."&$K22&" IS '"&C22&"';" -> COMMENT ON COLUMN cop_payment_information. IS ''; | R22: post_office_id VARCHAR(8),
G23: 上記以外の直近ではない未来日付：直投されたデータ | L23: =D23&"("&E23&")," -> (), | N23: ="COMMENT ON COLUMN "&$K$3&"."&$K23&" IS '"&C23&"';" -> COMMENT ON COLUMN cop_payment_information. IS ''; | R23: credit_card_company_id VARCHAR(10),
B24: 4 | C24: 有効終了日 | D24: VARCHAR | E24: 16 | F24: － | G24: 有効終了日(YYYYMMDD) | J24: ★項目説明修正(2025/6/24) | K24: effective_end_date | L24: =D24&"("&E24&")," -> VARCHAR(16), | N24: ="COMMENT ON COLUMN "&$K$3&"."&$K24&" IS '"&C24&"';" -> COMMENT ON COLUMN cop_payment_information.effective_end_date IS '有効終了日'; | R24: application_number VARCHAR(24),
G25: 前提：データ投入方法は、システム連携・フロント(GINIE等)経由の2種類がある | L25: =D25&"("&E25&")," -> (), | N25: ="COMMENT ON COLUMN "&$K$3&"."&$K25&" IS '"&C25&"';" -> COMMENT ON COLUMN cop_payment_information. IS ''; | R25: invoice_automatic_change_indicator VARCHAR(2),
L26: =D26&"("&E26&")," -> (), | N26: ="COMMENT ON COLUMN "&$K$3&"."&$K26&" IS '"&C26&"';" -> COMMENT ON COLUMN cop_payment_information. IS ''; | R26: CONSTRAINT pk_cop_payment_information PRIMARY KEY (id));
G27: ・システム連携のデータ | L27: =D27&"("&E27&")," -> (), | N27: ="COMMENT ON COLUMN "&$K$3&"."&$K27&" IS '"&C27&"';" -> COMMENT ON COLUMN cop_payment_information. IS ''; | R27: COMMENT ON TABLE cop_payment_information IS 'b_cop_支払情報';
G28: 99991231：最新(=継続中)のデータ | L28: =D28&"("&E28&")," -> (), | N28: ="COMMENT ON COLUMN "&$K$3&"."&$K28&" IS '"&C28&"';" -> COMMENT ON COLUMN cop_payment_information. IS ''; | R28: COMMENT ON COLUMN cop_payment_information.id IS 'id';
L29: =D29&"("&E29&")," -> (), | N29: ="COMMENT ON COLUMN "&$K$3&"."&$K29&" IS '"&C29&"';" -> COMMENT ON COLUMN cop_payment_information. IS ''; | R29: COMMENT ON COLUMN cop_payment_information.record_serial_number IS 'レコード通番';
G30: ・GINIE→CCOC経由の支払方法更新時のデータ | L30: =D30&"("&E30&")," -> (), | N30: ="COMMENT ON COLUMN "&$K$3&"."&$K30&" IS '"&C30&"';" -> COMMENT ON COLUMN cop_payment_information. IS ''; | R30: COMMENT ON COLUMN cop_payment_information.billing_group_id IS '請求グループid';
G31: 10年後：新規/譲渡でB#新設時で、支払方法が口振/クレでPay easy利用なし（承認IND：N）の場合 | L31: =D31&"("&E31&")," -> (), | N31: ="COMMENT ON COLUMN "&$K$3&"."&$K31&" IS '"&C31&"';" -> COMMENT ON COLUMN cop_payment_information. IS ''; | R31: COMMENT ON COLUMN cop_payment_information.effective_start_date IS '有効開始日';
G32: 29991230：情報変更（支払方法変更）で、口振/クレでPay easy利用なし（承認IND：N）の場合 | L32: =D32&"("&E32&")," -> (), | N32: ="COMMENT ON COLUMN "&$K$3&"."&$K32&" IS '"&C32&"';" -> COMMENT ON COLUMN cop_payment_information. IS ''; | R32: COMMENT ON COLUMN cop_payment_information.effective_end_date IS '有効終了日';
G33: 29991231：B#変更なしの承継で、支払方法が口振/クレでPay easy利用なし（承認IND：N）の場合 | L33: =D33&"("&E33&")," -> (), | N33: ="COMMENT ON COLUMN "&$K$3&"."&$K33&" IS '"&C33&"';" -> COMMENT ON COLUMN cop_payment_information. IS ''; | R33: COMMENT ON COLUMN cop_payment_information.deletion_indicator IS '削除インジケータ';
L34: =D34&"("&E34&")," -> (), | N34: ="COMMENT ON COLUMN "&$K$3&"."&$K34&" IS '"&C34&"';" -> COMMENT ON COLUMN cop_payment_information. IS ''; | R34: COMMENT ON COLUMN cop_payment_information.created_date IS '作成日';
G35: ・その他のデータ | L35: =D35&"("&E35&")," -> (), | N35: ="COMMENT ON COLUMN "&$K$3&"."&$K35&" IS '"&C35&"';" -> COMMENT ON COLUMN cop_payment_information. IS ''; | R35: COMMENT ON COLUMN cop_payment_information.new_code IS '新規コード';
G36: 上記以外の直近ではない未来日付：直投されたデータ | L36: =D36&"("&E36&")," -> (), | N36: ="COMMENT ON COLUMN "&$K$3&"."&$K36&" IS '"&C36&"';" -> COMMENT ON COLUMN cop_payment_information. IS ''; | R36: COMMENT ON COLUMN cop_payment_information.billing_payment_method_code IS '請求支払方法コード';
B37: 5 | C37: 削除インジケータ | D37: VARCHAR | E37: 2 | F37: － | G37: N：有効レコード | K37: deletion_indicator | L37: =D37&"("&E37&")," -> VARCHAR(2), | N37: ="COMMENT ON COLUMN "&$K$3&"."&$K37&" IS '"&C37&"';" -> COMMENT ON COLUMN cop_payment_information.deletion_indicator IS '削除インジケータ'; | R37: COMMENT ON COLUMN cop_payment_information.reseller_company_id IS '再販会社id';
G38: Y：論理削除（DWHでは物理削除されるため、存在しない） | L38: =D38&"("&E38&")," -> (), | N38: ="COMMENT ON COLUMN "&$K$3&"."&$K38&" IS '"&C38&"';" -> COMMENT ON COLUMN cop_payment_information. IS ''; | R38: COMMENT ON COLUMN cop_payment_information.financial_institution_type_code IS '金融機関タイプコード';
B39: 6 | C39: 作成日 | D39: VARCHAR | E39: 16 | F39: － | K39: created_date | L39: =D39&"("&E39&")," -> VARCHAR(16), | N39: ="COMMENT ON COLUMN "&$K$3&"."&$K39&" IS '"&C39&"';" -> COMMENT ON COLUMN cop_payment_information.created_date IS '作成日'; | R39: COMMENT ON COLUMN cop_payment_information.invoice_type_code IS '請求書タイプコード';
B40: 7 | C40: 新規コード | D40: VARCHAR | E40: 4 | F40: － | H40: OMコードリファレンス#0138 | K40: new_code | L40: =D40&"("&E40&")," -> VARCHAR(4), | N40: ="COMMENT ON COLUMN "&$K$3&"."&$K40&" IS '"&C40&"';" -> COMMENT ON COLUMN cop_payment_information.new_code IS '新規コード'; | R40: COMMENT ON COLUMN cop_payment_information.bank_id IS '銀行id';
B41: 8 | C41: 請求支払方法コード | D41: VARCHAR | E41: 4 | F41: － | H41: OMコードリファレンス#0071 | K41: billing_payment_method_code | L41: =D41&"("&E41&")," -> VARCHAR(4), | N41: ="COMMENT ON COLUMN "&$K$3&"."&$K41&" IS '"&C41&"';" -> COMMENT ON COLUMN cop_payment_information.billing_payment_method_code IS '請求支払方法コード'; | R41: COMMENT ON COLUMN cop_payment_information.bank_branch_id IS '銀行支店id';
B42: 9 | C42: 再販会社id | D42: VARCHAR | E42: 10 | F42: － | G42: 請求支払方法コードが"90"（再販）の場合、再販会社IDが設定される | K42: reseller_company_id | L42: =D42&"("&E42&")," -> VARCHAR(10), | N42: ="COMMENT ON COLUMN "&$K$3&"."&$K42&" IS '"&C42&"';" -> COMMENT ON COLUMN cop_payment_information.reseller_company_id IS '再販会社id'; | R42: COMMENT ON COLUMN cop_payment_information.post_office_id IS '郵便局id';
B43: 10 | C43: 金融機関タイプコード | D43: VARCHAR | E43: 4 | F43: － | H43: OMコードリファレンス#0069 | K43: financial_institution_type_code | L43: =D43&"("&E43&")," -> VARCHAR(4), | N43: ="COMMENT ON COLUMN "&$K$3&"."&$K43&" IS '"&C43&"';" -> COMMENT ON COLUMN cop_payment_information.financial_institution_type_code IS '金融機関タイプコード'; | R43: COMMENT ON COLUMN cop_payment_information.credit_card_company_id IS 'credit_card_会社id';
B44: 11 | C44: 請求書タイプコード | D44: VARCHAR | E44: 4 | F44: － | H44: OMコードリファレンス#0074 | K44: invoice_type_code | L44: =D44&"("&E44&")," -> VARCHAR(4), | N44: ="COMMENT ON COLUMN "&$K$3&"."&$K44&" IS '"&C44&"';" -> COMMENT ON COLUMN cop_payment_information.invoice_type_code IS '請求書タイプコード'; | R44: COMMENT ON COLUMN cop_payment_information.application_number IS '申込書番号';
B45: 12 | C45: 銀行id | D45: VARCHAR | E45: 8 | F45: － | G45: 銀行ID | K45: bank_id | L45: =D45&"("&E45&")," -> VARCHAR(8), | N45: ="COMMENT ON COLUMN "&$K$3&"."&$K45&" IS '"&C45&"';" -> COMMENT ON COLUMN cop_payment_information.bank_id IS '銀行id'; | R45: COMMENT ON COLUMN cop_payment_information.invoice_automatic_change_indicator IS '請求書自動変更ind';
B46: 13 | C46: 銀行支店id | D46: VARCHAR | E46: 6 | F46: － | G46: 銀行店舗番号 | K46: bank_branch_id | L46: =D46&"("&E46&")," -> VARCHAR(6), | N46: ="COMMENT ON COLUMN "&$K$3&"."&$K46&" IS '"&C46&"';" -> COMMENT ON COLUMN cop_payment_information.bank_branch_id IS '銀行支店id';
B47: 14 | C47: 郵便局id | D47: VARCHAR | E47: 8 | F47: － | G47: 郵便局ID | K47: post_office_id | L47: =D47&"("&E47&")," -> VARCHAR(8), | N47: ="COMMENT ON COLUMN "&$K$3&"."&$K47&" IS '"&C47&"';" -> COMMENT ON COLUMN cop_payment_information.post_office_id IS '郵便局id';
B48: 15 | C48: credit_card_会社id | D48: VARCHAR | E48: 10 | F48: － | G48: クレジットカード会社を表す5桁番号 | I48: X3対応(項目名変更) | K48: credit_card_company_id | L48: =D48&"("&E48&")," -> VARCHAR(10), | N48: ="COMMENT ON COLUMN "&$K$3&"."&$K48&" IS '"&C48&"';" -> COMMENT ON COLUMN cop_payment_information.credit_card_company_id IS 'credit_card_会社id';
B49: 16 | C49: 申込書番号 | D49: VARCHAR | E49: 24 | F49: ○ | G49: 申込書番号 | I49: ・H制御Viewでは仮名加工された値が表示されます | K49: application_number | L49: =D49&"("&E49&")," -> VARCHAR(24), | N49: ="COMMENT ON COLUMN "&$K$3&"."&$K49&" IS '"&C49&"';" -> COMMENT ON COLUMN cop_payment_information.application_number IS '申込書番号';
B50: 17 | C50: 請求書自動変更ind | D50: VARCHAR | E50: 2 | F50: － | I50: X3対応(項目名変更) | K50: invoice_automatic_change_indicator | L50: =D50&"("&E50&")," -> VARCHAR(2), | N50: ="COMMENT ON COLUMN "&$K$3&"."&$K50&" IS '"&C50&"';" -> COMMENT ON COLUMN cop_payment_information.invoice_automatic_change_indicator IS '請求書自動変更ind';
K51: ="CONSTRAINT pk_"&K3&" PRIMARY KEY (id));" -> CONSTRAINT pk_cop_payment_information PRIMARY KEY (id));

Sheet (COP)契約者リンク履歴
G2: 種別 | H2: DWH公開名 | I2: 旧DWH公開名 | J2: 統合テーブルID | K2: スキーマ
G3: ビュー | H3: b_cop_契約者リンク履歴 | I3: B_契約者リンク履歴_[権限] | J3: V000592 | K3: user_l2id | L3: cop_contractor_link_history
G4: データ概要：
G5: 契約者に属する回線とのリンクを管理。
L6: ="DROP TABLE IF EXISTS "&L3&" CASCADE;" -> DROP TABLE IF EXISTS cop_contractor_link_history CASCADE; | S6: DROP TABLE IF EXISTS cop_contractor_link_history CASCADE;
L7: ="CREATE TABLE IF NOT EXISTS "&L3&" (" -> CREATE TABLE IF NOT EXISTS cop_contractor_link_history ( | O7: ="COMMENT ON TABLE "&L3&" IS '"&H3&"';" -> COMMENT ON TABLE cop_contractor_link_history IS 'b_cop_契約者リンク履歴'; | S7: CREATE TABLE IF NOT EXISTS cop_contractor_link_history (
A8: pk | B8: SEQ | C8: 項目名 | E8: TYPE | F8: 桁 | G8: 仮名化 | H8: 項目説明およびリスト値 | I8: コードリファレンスリンク | J8: 備考 | K8: 更新日 | L8: id BIGINT GENERATED BY DEFAULT AS IDENTITY, | O8: ="COMMENT ON COLUMN "&$L$3&".id IS 'id';" -> COMMENT ON COLUMN cop_contractor_link_history.id IS 'id'; | S8: id BIGINT GENERATED BY DEFAULT AS IDENTITY,
B9: 1 | C9: contractor_id | D9: 請負業者ID | E9: VARCHAR | F9: 40 | G9: ○ | H9: 契約者ID(C#) | J9: ・H制御Viewでは仮名加工された値が表示されます | L9: contractor_id | M9: =E9&"("&F9&")," -> VARCHAR(40), | O9: ="COMMENT ON COLUMN "&$L$3&"."&$L9&" IS '"&D9&"';" -> COMMENT ON COLUMN cop_contractor_link_history.contractor_id IS '請負業者ID'; | S9: contractor_id VARCHAR(40),
B10: 2 | C10: created_dt | D10: 作成日時 | E10: VARCHAR | F10: 16 | G10: － | H10: 作成日(YYYYMMDD) | L10: created_dt | M10: =E10&"("&F10&")," -> VARCHAR(16), | O10: ="COMMENT ON COLUMN "&$L$3&"."&$L10&" IS '"&D10&"';" -> COMMENT ON COLUMN cop_contractor_link_history.created_dt IS '作成日時'; | S10: created_dt VARCHAR(16),
B11: 3 | C11: service_id | D11: サービスID | E11: VARCHAR | F11: 40 | G11: ○ | H11: サービスID(S#) | J11: ・H制御Viewでは仮名加工された値が表示されます | L11: service_id | M11: =E11&"("&F11&")," -> VARCHAR(40), | O11: ="COMMENT ON COLUMN "&$L$3&"."&$L11&" IS '"&D11&"';" -> COMMENT ON COLUMN cop_contractor_link_history.service_id IS 'サービスID'; | S11: service_id VARCHAR(40),
B12: 4 | C12: effective_dt_from | D12: 有効日時開始日時 | E12: VARCHAR | F12: 16 | G12: － | H12: 有効開始日(YYYYMMDD) | L12: effective_dt_from | M12: =E12&"("&F12&")," -> VARCHAR(16), | O12: ="COMMENT ON COLUMN "&$L$3&"."&$L12&" IS '"&D12&"';" -> COMMENT ON COLUMN cop_contractor_link_history.effective_dt_from IS '有効日時開始日時'; | S12: effective_dt_from VARCHAR(16),
B13: 5 | C13: effective_dt_to | D13: 有効日時終了日時 | E13: VARCHAR | F13: 16 | G13: － | H13: 有効終了日(YYYYMMDD) | L13: effective_dt_to | M13: =E13&"("&F13&")," -> VARCHAR(16), | O13: ="COMMENT ON COLUMN "&$L$3&"."&$L13&" IS '"&D13&"';" -> COMMENT ON COLUMN cop_contractor_link_history.effective_dt_to IS '有効日時終了日時'; | S13: effective_dt_to VARCHAR(16),
B14: 6 | C14: delete_ind | D14: 削除インデックス | E14: VARCHAR | F14: 2 | G14: － | H14: N：有効レコード | L14: delete_ind | M14: =E14&"("&F14&")," -> VARCHAR(2), | O14: ="COMMENT ON COLUMN "&$L$3&"."&$L14&" IS '"&D14&"';" -> COMMENT ON COLUMN cop_contractor_link_history.delete_ind IS '削除インデックス'; | S14: delete_ind VARCHAR(2),
H15: Y：論理削除（DWHでは物理削除されるため、存在しない） | M15: =E15&"("&F15&")," -> (), | O15: ="COMMENT ON COLUMN "&$L$3&"."&$L15&" IS '"&D15&"';" -> COMMENT ON COLUMN cop_contractor_link_history. IS ''; | S15: record_sequence_nbr DECIMAL(38,0),
A16: ○ | B16: 7 | C16: record_sequence_nbr | D16: レコードシーケンス番号 | E16: DECIMAL | F16: 38,0 | G16: － | H16: レコード通番 | J16: X3対応(桁変更) | L16: record_sequence_nbr | M16: =E16&"("&F16&")," -> DECIMAL(38,0), | O16: ="COMMENT ON COLUMN "&$L$3&"."&$L16&" IS '"&D16&"';" -> COMMENT ON COLUMN cop_contractor_link_history.record_sequence_nbr IS 'レコードシーケンス番号'; | S16: deactivate_ind VARCHAR(2),
B17: 8 | C17: deactivate_ind | D17: 無効化インデックス | E17: VARCHAR | F17: 2 | G17: － | H17: 解約インジケータ | I17: DWHコードリファレンス#0009 | L17: deactivate_ind | M17: =E17&"("&F17&")," -> VARCHAR(2), | O17: ="COMMENT ON COLUMN "&$L$3&"."&$L17&" IS '"&D17&"';" -> COMMENT ON COLUMN cop_contractor_link_history.deactivate_ind IS '無効化インデックス'; | S17: CONSTRAINT pk_cop_contractor_link_history PRIMARY KEY (id));
L18: ="CONSTRAINT pk_"&L3&" PRIMARY KEY (id));" -> CONSTRAINT pk_cop_contractor_link_history PRIMARY KEY (id)); | S18: COMMENT ON TABLE cop_contractor_link_history IS 'b_cop_契約者リンク履歴';
S19: COMMENT ON COLUMN cop_contractor_link_history.id IS 'id';
S20: COMMENT ON COLUMN cop_contractor_link_history.contractor_id IS '請負業者ID';
S21: COMMENT ON COLUMN cop_contractor_link_history.created_dt IS '作成日時';
S22: COMMENT ON COLUMN cop_contractor_link_history.service_id IS 'サービスID';
S23: COMMENT ON COLUMN cop_contractor_link_history.effective_dt_from IS '有効日時開始日時';
S24: COMMENT ON COLUMN cop_contractor_link_history.effective_dt_to IS '有効日時終了日時';
S25: COMMENT ON COLUMN cop_contractor_link_history.delete_ind IS '削除インデックス';
S26: COMMENT ON COLUMN cop_contractor_link_history.record_sequence_nbr IS 'レコードシーケンス番号';
S27: COMMENT ON COLUMN cop_contractor_link_history.deactivate_ind IS '無効化インデックス';

Sheet (COP)svcリンク履歴
G2: 種別 | H2: DWH公開名 | I2: 旧DWH公開名 | J2: 統合テーブルID | K2: スキーマ
G3: ビュー | H3: b_cop_svcリンク履歴 | I3: B_SVCリンク履歴_[権限] | J3: V000446 | K3: user_l2id | L3: cop_svc_link_history
G4: データ概要：
G5: 請求先に属する回線とのリンクを管理。
L6: ="DROP TABLE IF EXISTS "&L3&" CASCADE;" -> DROP TABLE IF EXISTS cop_svc_link_history CASCADE; | S6: DROP TABLE IF EXISTS cop_svc_link_history CASCADE;
L7: ="CREATE TABLE IF NOT EXISTS "&L3&" (" -> CREATE TABLE IF NOT EXISTS cop_svc_link_history ( | O7: ="COMMENT ON TABLE "&L3&" IS '"&H3&"';" -> COMMENT ON TABLE cop_svc_link_history IS 'b_cop_svcリンク履歴'; | S7: CREATE TABLE IF NOT EXISTS cop_svc_link_history (
A8: pk | B8: SEQ | C8: 項目名 | E8: TYPE | F8: 桁 | G8: 仮名化 | H8: 項目説明およびリスト値 | I8: コードリファレンスリンク | J8: 備考 | K8: 更新日 | L8: id BIGINT GENERATED BY DEFAULT AS IDENTITY, | O8: ="COMMENT ON COLUMN "&$L$3&".id IS 'id';" -> COMMENT ON COLUMN cop_svc_link_history.id IS 'id'; | S8: id BIGINT GENERATED BY DEFAULT AS IDENTITY,
A9: ○ | B9: 1 | C9: record_sequence_nbr | D9: レコードシーケンス番号 | E9: DECIMAL | F9: 38,0 | G9: － | H9: レコード通番 | J9: X3対応(桁変更) | L9: =C9 -> record_sequence_nbr | M9: =E9&"("&F9&")," -> DECIMAL(38,0), | O9: ="COMMENT ON COLUMN "&$L$3&"."&$L9&" IS '"&D9&"';" -> COMMENT ON COLUMN cop_svc_link_history.record_sequence_nbr IS 'レコードシーケンス番号'; | S9: record_sequence_nbr DECIMAL(38,0),
B10: 2 | C10: ifdb_proc_type | D10: ifdb_proc_type | E10: VARCHAR | F10: 2 | G10: － | H10: 変更種別 | I10: DWHコードリファレンス#0008 | L10: =C10 -> ifdb_proc_type | M10: =E10&"("&F10&")," -> VARCHAR(2), | O10: ="COMMENT ON COLUMN "&$L$3&"."&$L10&" IS '"&D10&"';" -> COMMENT ON COLUMN cop_svc_link_history.ifdb_proc_type IS 'ifdb_proc_type'; | S10: ifdb_proc_type VARCHAR(2),
B11: 3 | C11: service_id | D11: サービスID | E11: VARCHAR | F11: 40 | G11: ○ | H11: サービスID(S#) | J11: ・H制御Viewでは仮名加工された値が表示されます | L11: =C11 -> service_id | M11: =E11&"("&F11&")," -> VARCHAR(40), | O11: ="COMMENT ON COLUMN "&$L$3&"."&$L11&" IS '"&D11&"';" -> COMMENT ON COLUMN cop_svc_link_history.service_id IS 'サービスID'; | S11: service_id VARCHAR(40),
B12: 4 | C12: bill_group_id | D12: 請求グループID | E12: VARCHAR | F12: 40 | G12: ○ | H12: 請求グループID(B#) | J12: ・H制御Viewでは仮名加工された値が表示されます | L12: =C12 -> bill_group_id | M12: =E12&"("&F12&")," -> VARCHAR(40), | O12: ="COMMENT ON COLUMN "&$L$3&"."&$L12&" IS '"&D12&"';" -> COMMENT ON COLUMN cop_svc_link_history.bill_group_id IS '請求グループID'; | S12: bill_group_id VARCHAR(40),
B13: 5 | C13: linkage_type_cde | D13: リンケージタイプCDE | E13: VARCHAR | F13: 4 | G13: － | H13: リンケージタイプコード | I13: OMコードリファレンス#0009 | L13: =C13 -> linkage_type_cde | M13: =E13&"("&F13&")," -> VARCHAR(4), | O13: ="COMMENT ON COLUMN "&$L$3&"."&$L13&" IS '"&D13&"';" -> COMMENT ON COLUMN cop_svc_link_history.linkage_type_cde IS 'リンケージタイプCDE'; | S13: linkage_type_cde VARCHAR(4),
B14: 6 | C14: effective_dt_from | D14: 有効データ転送元 | E14: VARCHAR | F14: 16 | G14: － | H14: 有効開始日(YYYYMMDD) | L14: =C14 -> effective_dt_from | M14: =E14&"("&F14&")," -> VARCHAR(16), | O14: ="COMMENT ON COLUMN "&$L$3&"."&$L14&" IS '"&D14&"';" -> COMMENT ON COLUMN cop_svc_link_history.effective_dt_from IS '有効データ転送元'; | S14: effective_dt_from VARCHAR(16),
B15: 7 | C15: effective_dt_to | D15: 有効データ転送先 | E15: VARCHAR | F15: 16 | G15: － | H15: 有効終了日(YYYYMMDD) | L15: =C15 -> effective_dt_to | M15: =E15&"("&F15&")," -> VARCHAR(16), | O15: ="COMMENT ON COLUMN "&$L$3&"."&$L15&" IS '"&D15&"';" -> COMMENT ON COLUMN cop_svc_link_history.effective_dt_to IS '有効データ転送先'; | S15: effective_dt_to VARCHAR(16),
B16: 8 | C16: transaction_nbr | D16: トランザクション番号 | E16: DECIMAL | F16: 15,0 | G16: － | H16: トランザクション番号 | J16: X3対応(桁変更) | L16: =C16 -> transaction_nbr | M16: =E16&"("&F16&")," -> DECIMAL(15,0), | O16: ="COMMENT ON COLUMN "&$L$3&"."&$L16&" IS '"&D16&"';" -> COMMENT ON COLUMN cop_svc_link_history.transaction_nbr IS 'トランザクション番号'; | S16: transaction_nbr DECIMAL(15,0),
B17: 9 | C17: created_dt | D17: 作成日時 | E17: VARCHAR | F17: 16 | G17: － | H17: 作成日(YYYYMMDD) | L17: =C17 -> created_dt | M17: =E17&"("&F17&")," -> VARCHAR(16), | O17: ="COMMENT ON COLUMN "&$L$3&"."&$L17&" IS '"&D17&"';" -> COMMENT ON COLUMN cop_svc_link_history.created_dt IS '作成日時'; | S17: created_dt VARCHAR(16),
B18: 10 | C18: created_tm | D18: 作成日時TM | E18: VARCHAR | F18: 12 | G18: － | H18: 作成時間(HHMMSS) | L18: =C18 -> created_tm | M18: =E18&"("&F18&")," -> VARCHAR(12), | O18: ="COMMENT ON COLUMN "&$L$3&"."&$L18&" IS '"&D18&"';" -> COMMENT ON COLUMN cop_svc_link_history.created_tm IS '作成日時TM'; | S18: created_tm VARCHAR(12),
B19: 11 | C19: last_updated_dt | D19: 最終更新日時TM | E19: VARCHAR | F19: 16 | G19: － | H19: 最終更新日(YYYYMMDD) | L19: =C19 -> last_updated_dt | M19: =E19&"("&F19&")," -> VARCHAR(16), | O19: ="COMMENT ON COLUMN "&$L$3&"."&$L19&" IS '"&D19&"';" -> COMMENT ON COLUMN cop_svc_link_history.last_updated_dt IS '最終更新日時TM'; | S19: last_updated_dt VARCHAR(16),
B20: 12 | C20: last_updated_tm | D20: 最終更新日時TM | E20: VARCHAR | F20: 12 | G20: － | H20: 最終更新時間(HHMMSS) | L20: =C20 -> last_updated_tm | M20: =E20&"("&F20&")," -> VARCHAR(12), | O20: ="COMMENT ON COLUMN "&$L$3&"."&$L20&" IS '"&D20&"';" -> COMMENT ON COLUMN cop_svc_link_history.last_updated_tm IS '最終更新日時TM'; | S20: last_updated_tm VARCHAR(12),
B21: 13 | C21: delete_ind | D21: インデックス削除 | E21: VARCHAR | F21: 2 | G21: － | H21: N：有効レコード | L21: =C21 -> delete_ind | M21: =E21&"("&F21&")," -> VARCHAR(2), | O21: ="COMMENT ON COLUMN "&$L$3&"."&$L21&" IS '"&D21&"';" -> COMMENT ON COLUMN cop_svc_link_history.delete_ind IS 'インデックス削除'; | S21: delete_ind VARCHAR(2),
H22: Y：論理削除（DWHでは物理削除されるため、存在しない） | L22: =C22 -> 0 | M22: =E22&"("&F22&")," -> (), | O22: ="COMMENT ON COLUMN "&$L$3&"."&$L22&" IS '"&D22&"';" -> COMMENT ON COLUMN cop_svc_link_history.0 IS ''; | S22: deactivate_ind VARCHAR(2),
B23: 14 | C23: deactivate_ind | D23: インデックス無効化 | E23: VARCHAR | F23: 2 | G23: － | H23: 解約インジケータ | I23: DWHコードリファレンス#0009 | L23: =C23 -> deactivate_ind | M23: =E23&"("&F23&")," -> VARCHAR(2), | O23: ="COMMENT ON COLUMN "&$L$3&"."&$L23&" IS '"&D23&"';" -> COMMENT ON COLUMN cop_svc_link_history.deactivate_ind IS 'インデックス無効化'; | S23: CONSTRAINT pk_cop_svc_link_history PRIMARY KEY (id));
L24: ="CONSTRAINT pk_"&L3&" PRIMARY KEY (id));" -> CONSTRAINT pk_cop_svc_link_history PRIMARY KEY (id)); | S24: COMMENT ON TABLE cop_svc_link_history IS 'b_cop_svcリンク履歴';
S25: COMMENT ON COLUMN cop_svc_link_history.id IS 'id';
S26: COMMENT ON COLUMN cop_svc_link_history.record_sequence_nbr IS 'レコードシーケンス番号';
S27: COMMENT ON COLUMN cop_svc_link_history.ifdb_proc_type IS 'ifdb_proc_type';
S28: COMMENT ON COLUMN cop_svc_link_history.service_id IS 'サービスID';
S29: COMMENT ON COLUMN cop_svc_link_history.bill_group_id IS '請求グループID';
S30: COMMENT ON COLUMN cop_svc_link_history.linkage_type_cde IS 'リンケージタイプCDE';
S31: COMMENT ON COLUMN cop_svc_link_history.effective_dt_from IS '有効データ転送元';
S32: COMMENT ON COLUMN cop_svc_link_history.effective_dt_to IS '有効データ転送先';
S33: COMMENT ON COLUMN cop_svc_link_history.transaction_nbr IS 'トランザクション番号';
S34: COMMENT ON COLUMN cop_svc_link_history.created_dt IS '作成日時';
S35: COMMENT ON COLUMN cop_svc_link_history.created_tm IS '作成日時TM';
S36: COMMENT ON COLUMN cop_svc_link_history.last_updated_dt IS '最終更新日時TM';
... S39: COMMENT ON COLUMN cop_svc_link_history.deactivate_ind IS 'インデックス無効化';

Sheet (COP)販売履歴
G2: 種別 | H2: DWH公開名 | I2: 旧DWH公開名 | J2: 統合テーブルID | K2: スキーマ
G3: ビュー | H3: b_cop_販売履歴 | I3: B_販売履歴_[権限] | J3: V000748 | K3: user_l2id | L3: cop_sales_history
G4: データ概要：
G5: 移動機や付属品、その他商品の販売履歴を管理。
L6: ="DROP TABLE IF EXISTS "&L3&" CASCADE;" -> DROP TABLE IF EXISTS cop_sales_history CASCADE; | S6: DROP TABLE IF EXISTS cop_sales_history CASCADE;
L7: ="CREATE TABLE IF NOT EXISTS "&L3&" (" -> CREATE TABLE IF NOT EXISTS cop_sales_history ( | O7: ="COMMENT ON TABLE "&L3&" IS '"&H3&"';" -> COMMENT ON TABLE cop_sales_history IS 'b_cop_販売履歴'; | S7: CREATE TABLE IF NOT EXISTS cop_sales_history (
A8: pk | B8: SEQ | C8: 項目名 | E8: TYPE | F8: 桁 | G8: 仮名化 | H8: 項目説明およびリスト値 | I8: コードリファレンスリンク | J8: 備考 | K8: 更新日 | L8: id BIGINT GENERATED BY DEFAULT AS IDENTITY, | O8: ="COMMENT ON COLUMN "&$L$3&".id IS 'id';" -> COMMENT ON COLUMN cop_sales_history.id IS 'id'; | S8: id BIGINT GENERATED BY DEFAULT AS IDENTITY,
B9: 1 | C9: service_id | D9: サービスID | E9: VARCHAR | F9: 40 | G9: ○ | H9: サービスID(S#) | J9: ・H制御Viewでは仮名加工された値が表示されます | L9: =C9 -> service_id | M9: =E9&"("&F9&")," -> VARCHAR(40), | O9: ="COMMENT ON COLUMN "&$L$3&"."&$L9&" IS '"&D9&"';" -> COMMENT ON COLUMN cop_sales_history.service_id IS 'サービスID'; | S9: service_id VARCHAR(40),
B10: 2 | C10: bill_group_id | D10: 請求書グループID | E10: VARCHAR | F10: 40 | G10: ○ | H10: 請求グループID(B#) | J10: ・H制御Viewでは仮名加工された値が表示されます | L10: =C10 -> bill_group_id | M10: =E10&"("&F10&")," -> VARCHAR(40), | O10: ="COMMENT ON COLUMN "&$L$3&"."&$L10&" IS '"&D10&"';" -> COMMENT ON COLUMN cop_sales_history.bill_group_id IS '請求書グループID'; | S10: bill_group_id VARCHAR(40),
B11: 3 | C11: contractor_id | D11: 契約者ID | E11: VARCHAR | F11: 40 | G11: ○ | H11: 契約者ID(C#) | J11: ・H制御Viewでは仮名加工された値が表示されます | L11: =C11 -> contractor_id | M11: =E11&"("&F11&")," -> VARCHAR(40), | O11: ="COMMENT ON COLUMN "&$L$3&"."&$L11&" IS '"&D11&"';" -> COMMENT ON COLUMN cop_sales_history.contractor_id IS '契約者ID'; | S11: contractor_id VARCHAR(40),
B12: 4 | C12: item_nbr | D12: 商品番号 | E12: VARCHAR | F12: 40 | G12: － | H12: アイテム番号 | L12: =C12 -> item_nbr | M12: =E12&"("&F12&")," -> VARCHAR(40), | O12: ="COMMENT ON COLUMN "&$L$3&"."&$L12&" IS '"&D12&"';" -> COMMENT ON COLUMN cop_sales_history.item_nbr IS '商品番号'; | S12: item_nbr VARCHAR(40),
B13: 5 | C13: equipment_serial_nbr | D13: 機器シリアル番号 | E13: VARCHAR | F13: 60 | G13: － | H13: 機器のシリアル番号 | L13: =C13 -> equipment_serial_nbr | M13: =E13&"("&F13&")," -> VARCHAR(60), | O13: ="COMMENT ON COLUMN "&$L$3&"."&$L13&" IS '"&D13&"';" -> COMMENT ON COLUMN cop_sales_history.equipment_serial_nbr IS '機器シリアル番号'; | S13: equipment_serial_nbr VARCHAR(60),
H14: (International Mobile Equipment Identity) IMT-2000対応移動機を特定するための内部的ID | L14: =C14 -> 0 | M14: =E14&"("&F14&")," -> (), | O14: ="COMMENT ON COLUMN "&$L$3&"."&$L14&" IS '"&D14&"';" -> COMMENT ON COLUMN cop_sales_history.0 IS ''; | S14: created_dt VARCHAR(16),
B15: 6 | C15: created_dt | D15: 作成日時 | E15: VARCHAR | F15: 16 | G15: － | H15: 作成日(YYYYMMDD) | L15: =C15 -> created_dt | M15: =E15&"("&F15&")," -> VARCHAR(16), | O15: ="COMMENT ON COLUMN "&$L$3&"."&$L15&" IS '"&D15&"';" -> COMMENT ON COLUMN cop_sales_history.created_dt IS '作成日時'; | S15: created_tm VARCHAR(12),
B16: 7 | C16: created_tm | D16: 作成日時_tm | E16: VARCHAR | F16: 12 | G16: － | H16: 作成時間(HHMMSS) | L16: =C16 -> created_tm | M16: =E16&"("&F16&")," -> VARCHAR(12), | O16: ="COMMENT ON COLUMN "&$L$3&"."&$L16&" IS '"&D16&"';" -> COMMENT ON COLUMN cop_sales_history.created_tm IS '作成日時_tm'; | S16: delete_ind VARCHAR(2),
B17: 8 | C17: delete_ind | D17: 削除_ind | E17: VARCHAR | F17: 2 | G17: － | H17: N：有効レコード | L17: =C17 -> delete_ind | M17: =E17&"("&F17&")," -> VARCHAR(2), | O17: ="COMMENT ON COLUMN "&$L$3&"."&$L17&" IS '"&D17&"';" -> COMMENT ON COLUMN cop_sales_history.delete_ind IS '削除_ind'; | S17: selling_dt VARCHAR(16),
H18: Y：論理削除（DWHでは物理削除されるため、存在しない） | L18: =C18 -> 0 | M18: =E18&"("&F18&")," -> (), | O18: ="COMMENT ON COLUMN "&$L$3&"."&$L18&" IS '"&D18&"';" -> COMMENT ON COLUMN cop_sales_history.0 IS ''; | S18: selling_cancel_dt VARCHAR(16),
B19: 9 | C19: selling_dt | D19: 販売日時_tt | E19: VARCHAR | F19: 16 | G19: － | H19: DOの場合:発送予定日(YYYYMMDD) | L19: =C19 -> selling_dt | M19: =E19&"("&F19&")," -> VARCHAR(16), | O19: ="COMMENT ON COLUMN "&$L$3&"."&$L19&" IS '"&D19&"';" -> COMMENT ON COLUMN cop_sales_history.selling_dt IS '販売日時_tt'; | S19: selling_type_cde VARCHAR(4),
H20: それ以外は画面入力の販売日(YYYYMMDD) | L20: =C20 -> 0 | M20: =E20&"("&F20&")," -> (), | O20: ="COMMENT ON COLUMN "&$L$3&"."&$L20&" IS '"&D20&"';" -> COMMENT ON COLUMN cop_sales_history.0 IS ''; | S20: selling_reason_cde VARCHAR(4),
B21: 10 | C21: selling_cancel_dt | D21: 販売キャンセル日時_tt | E21: VARCHAR | F21: 16 | G21: － | H21: 移動機販売取消日(YYYYMMDD) | L21: =C21 -> selling_cancel_dt | M21: =E21&"("&F21&")," -> VARCHAR(16), | O21: ="COMMENT ON COLUMN "&$L$3&"."&$L21&" IS '"&D21&"';" -> COMMENT ON COLUMN cop_sales_history.selling_cancel_dt IS '販売キャンセル日時_tt'; | S21: cancellation_reason_cde VARCHAR(4),
B22: 11 | C22: selling_type_cde | D22: 販売タイプ_cde | E22: VARCHAR | F22: 4 | G22: － | H22: 移動機販売種別コード | I22: OMコードリファレンス#0034 | L22: =C22 -> selling_type_cde | M22: =E22&"("&F22&")," -> VARCHAR(4), | O22: ="COMMENT ON COLUMN "&$L$3&"."&$L22&" IS '"&D22&"';" -> COMMENT ON COLUMN cop_sales_history.selling_type_cde IS '販売タイプ_cde'; | S22: selling_status_cde VARCHAR(4),
B23: 12 | C23: selling_reason_cde | D23: 販売理由_cde | E23: VARCHAR | F23: 4 | G23: － | H23: 販売理由コード | I23: OMコードリファレンス#0035 | L23: =C23 -> selling_reason_cde | M23: =E23&"("&F23&")," -> VARCHAR(4), | O23: ="COMMENT ON COLUMN "&$L$3&"."&$L23&" IS '"&D23&"';" -> COMMENT ON COLUMN cop_sales_history.selling_reason_cde IS '販売理由_cde'; | S23: svc_org_id VARCHAR(40),
B24: 13 | C24: cancellation_reason_cde | D24: キャンセル理由_cde | E24: VARCHAR | F24: 4 | G24: － | H24: キャンセル理由コード | I24: OMコードリファレンス#0037 | L24: =C24 -> cancellation_reason_cde | M24: =E24&"("&F24&")," -> VARCHAR(4), | O24: ="COMMENT ON COLUMN "&$L$3&"."&$L24&" IS '"&D24&"';" -> COMMENT ON COLUMN cop_sales_history.cancellation_reason_cde IS 'キャンセル理由_cde'; | S24: cancellation_svc_org_id VARCHAR(40),
B25: 14 | C25: selling_status_cde | D25: 販売ステータス_cde | E25: VARCHAR | F25: 4 | G25: － | H25: 販売状態 | I25: OMコードリファレンス#0036 | L25: =C25 -> selling_status_cde | M25: =E25&"("&F25&")," -> VARCHAR(4), | O25: ="COMMENT ON COLUMN "&$L$3&"."&$L25&" IS '"&D25&"';" -> COMMENT ON COLUMN cop_sales_history.selling_status_cde IS '販売ステータス_cde'; | S25: selling_method_cde VARCHAR(4),
B26: 15 | C26: svc_org_id | D26: サービス提供組織ID | E26: VARCHAR | F26: 40 | G26: － | H26: サービス組織ID | L26: =C26 -> svc_org_id | M26: =E26&"("&F26&")," -> VARCHAR(40), | O26: ="COMMENT ON COLUMN "&$L$3&"."&$L26&" IS '"&D26&"';" -> COMMENT ON COLUMN cop_sales_history.svc_org_id IS 'サービス提供組織ID'; | S26: battery_pack_stat_cde VARCHAR(4),
B27: 16 | C27: cancellation_svc_org_id | D27: キャンセルサービス提供組織ID | E27: VARCHAR | F27: 40 | G27: － | H27: サービス組織ID(取消時） | L27: =C27 -> cancellation_svc_org_id | M27: =E27&"("&F27&")," -> VARCHAR(40), | O27: ="COMMENT ON COLUMN "&$L$3&"."&$L27&" IS '"&D27&"';" -> COMMENT ON COLUMN cop_sales_history.cancellation_svc_org_id IS 'キャンセルサービス提供組織ID'; | S27: item_quantity DECIMAL(10,0),
B28: 17 | C28: selling_method_cde | D28: 販売方法_cde | E28: VARCHAR | F28: 4 | G28: － | H28: 販売方法コード | I28: OMコードリファレンス#0038 | L28: =C28 -> selling_method_cde | M28: =E28&"("&F28&")," -> VARCHAR(4), | O28: ="COMMENT ON COLUMN "&$L$3&"."&$L28&" IS '"&D28&"';" -> COMMENT ON COLUMN cop_sales_history.selling_method_cde IS '販売方法_cde'; | S28: record_sequence_nbr DECIMAL(38,0),
B29: 18 | C29: battery_pack_stat_cde | D29: バッテリーパックステータス_cde | E29: VARCHAR | F29: 4 | G29: － | H29: 電池パック提供状況コード | I29: OMコードリファレンス#0039 | L29: =C29 -> battery_pack_stat_cde | M29: =E29&"("&F29&")," -> VARCHAR(4), | O29: ="COMMENT ON COLUMN "&$L$3&"."&$L29&" IS '"&D29&"';" -> COMMENT ON COLUMN cop_sales_history.battery_pack_stat_cde IS 'バッテリーパックステータス_cde'; | S29: battery_pack_request_dt VARCHAR(16),
B30: 19 | C30: item_quantity | D30: 商品数量 | E30: DECIMAL | F30: 10,0 | G30: － | H30: アイテム数量 | J30: X3対応(桁変更) | L30: =C30 -> item_quantity | M30: =E30&"("&F30&")," -> DECIMAL(10,0), | O30: ="COMMENT ON COLUMN "&$L$3&"."&$L30&" IS '"&D30&"';" -> COMMENT ON COLUMN cop_sales_history.item_quantity IS '商品数量'; | S30: pymt_method_cde VARCHAR(4),
A31: ○ | B31: 20 | C31: record_sequence_nbr | D31: レコードシーケンス番号 | E31: DECIMAL | F31: 38,0 | G31: － | H31: レコード通番 | J31: X3対応(桁変更) | L31: =C31 -> record_sequence_nbr | M31: =E31&"("&F31&")," -> DECIMAL(38,0), | O31: ="COMMENT ON COLUMN "&$L$3&"."&$L31&" IS '"&D31&"';" -> COMMENT ON COLUMN cop_sales_history.record_sequence_nbr IS 'レコードシーケンス番号'; | S31: repair_acceptance_dt VARCHAR(16),
B32: 21 | C32: battery_pack_request_dt | D32: バッテリーパック要求日時 | E32: VARCHAR | F32: 16 | G32: － | H32: 電池パック要求日(YYYYMMDD) | L32: =C32 -> battery_pack_request_dt | M32: =E32&"("&F32&")," -> VARCHAR(16), | O32: ="COMMENT ON COLUMN "&$L$3&"."&$L32&" IS '"&D32&"';" -> COMMENT ON COLUMN cop_sales_history.battery_pack_request_dt IS 'バッテリーパック要求日時'; | S32: replace_reason_cde01 VARCHAR(4),
B33: 22 | C33: pymt_method_cde | D33: 支払い方法 cde | E33: VARCHAR | F33: 4 | G33: － | H33: 支払い方法コード | I33: DWHコードリファレンス#0018 | L33: =C33 -> pymt_method_cde | M33: =E33&"("&F33&")," -> VARCHAR(4), | O33: ="COMMENT ON COLUMN "&$L$3&"."&$L33&" IS '"&D33&"';" -> COMMENT ON COLUMN cop_sales_history.pymt_method_cde IS '支払い方法 cde'; | S33: warranty_service_ind01 VARCHAR(2),
B34: 23 | C34: repair_acceptance_dt | D34: 修理受付 dt | E34: VARCHAR | F34: 16 | G34: － | H34: 故障・修理受付日 | L34: =C34 -> repair_acceptance_dt | M34: =E34&"("&F34&")," -> VARCHAR(16), | O34: ="COMMENT ON COLUMN "&$L$3&"."&$L34&" IS '"&D34&"';" -> COMMENT ON COLUMN cop_sales_history.repair_acceptance_dt IS '修理受付 dt'; | S34: replace_reason_cde02 VARCHAR(4),
B35: 24 | C35: replace_reason_cde01 | D35: 交換理由 cde01 | E35: VARCHAR | F35: 4 | G35: － | H35: 故障交換理由コード01 | I35: OMコードリファレンス#0076 | L35: =C35 -> replace_reason_cde01 | M35: =E35&"("&F35&")," -> VARCHAR(4), | O35: ="COMMENT ON COLUMN "&$L$3&"."&$L35&" IS '"&D35&"';" -> COMMENT ON COLUMN cop_sales_history.replace_reason_cde01 IS '交換理由 cde01'; | S35: warranty_service_ind02 VARCHAR(2),
B36: 25 | C36: warranty_service_ind01 | D36: 保証サービス ind01 | E36: VARCHAR | F36: 2 | G36: － | H36: 保証サービス利用インジケータ01 | L36: =C36 -> warranty_service_ind01 | M36: =E36&"("&F36&")," -> VARCHAR(2), | O36: ="COMMENT ON COLUMN "&$L$3&"."&$L36&" IS '"&D36&"';" -> COMMENT ON COLUMN cop_sales_history.warranty_service_ind01 IS '保証サービス ind01'; | S36: replace_reason_cde03 VARCHAR(4),
H37: Y：保証サービス利用あり | L37: =C37 -> 0 | M37: =E37&"("&F37&")," -> (), | O37: ="COMMENT ON COLUMN "&$L$3&"."&$L37&" IS '"&D37&"';" -> COMMENT ON COLUMN cop_sales_history.0 IS ''; | S37: warranty_service_ind03 VARCHAR(2),
B38: 26 | C38: replace_reason_cde02 | D38: 交換理由 cde02 | E38: VARCHAR | F38: 4 | G38: － | H38: 故障交換理由コード02 | I38: OMコードリファレンス#0076 | L38: =C38 -> replace_reason_cde02 | M38: =E38&"("&F38&")," -> VARCHAR(4), | O38: ="COMMENT ON COLUMN "&$L$3&"."&$L38&" IS '"&D38&"';" -> COMMENT ON COLUMN cop_sales_history.replace_reason_cde02 IS '交換理由 cde02'; | S38: replace_reason_cde04 VARCHAR(4),
B39: 27 | C39: warranty_service_ind02 | D39: 保証サービス ind02 | E39: VARCHAR | F39: 2 | G39: － | H39: 保証サービス利用インジケータ02 | L39: =C39 -> warranty_service_ind02 | M39: =E39&"("&F39&")," -> VARCHAR(2), | O39: ="COMMENT ON COLUMN "&$L$3&"."&$L39&" IS '"&D39&"';" -> COMMENT ON COLUMN cop_sales_history.warranty_service_ind02 IS '保証サービス ind02'; | S39: warranty_service_ind04 VARCHAR(2),
H40: Y：保証サービス利用あり | L40: =C40 -> 0 | M40: =E40&"("&F40&")," -> (), | O40: ="COMMENT ON COLUMN "&$L$3&"."&$L40&" IS '"&D40&"';" -> COMMENT ON COLUMN cop_sales_history.0 IS ''; | S40: replace_reason_cde05 VARCHAR(4),
B41: 28 | C41: replace_reason_cde03 | D41: 交換理由 cde03 | E41: VARCHAR | F41: 4 | G41: － | H41: 故障交換理由コード03 | I41: OMコードリファレンス#0076 | L41: =C41 -> replace_reason_cde03 | M41: =E41&"("&F41&")," -> VARCHAR(4), | O41: ="COMMENT ON COLUMN "&$L$3&"."&$L41&" IS '"&D41&"';" -> COMMENT ON COLUMN cop_sales_history.replace_reason_cde03 IS '交換理由 cde03'; | S41: warranty_service_ind05 VARCHAR(2),
B42: 29 | C42: warranty_service_ind03 | D42: 保証サービス ind03 | E42: VARCHAR | F42: 2 | G42: － | H42: 保証サービス利用インジケータ03 | L42: =C42 -> warranty_service_ind03 | M42: =E42&"("&F42&")," -> VARCHAR(2), | O42: ="COMMENT ON COLUMN "&$L$3&"."&$L42&" IS '"&D42&"';" -> COMMENT ON COLUMN cop_sales_history.warranty_service_ind03 IS '保証サービス ind03'; | S42: before_equipment_serial_nbr VARCHAR(60),
H43: Y：保証サービス利用あり | L43: =C43 -> 0 | M43: =E43&"("&F43&")," -> (), | O43: ="COMMENT ON COLUMN "&$L$3&"."&$L43&" IS '"&D43&"';" -> COMMENT ON COLUMN cop_sales_history.0 IS ''; | S43: before_rec_seq_nbr DECIMAL(38,0),
B44: 30 | C44: replace_reason_cde04 | D44: 交換理由 cde04 | E44: VARCHAR | F44: 4 | G44: － | H44: 故障交換理由コード04 | I44: OMコードリファレンス#0076 | L44: =C44 -> replace_reason_cde04 | M44: =E44&"("&F44&")," -> VARCHAR(4), | O44: ="COMMENT ON COLUMN "&$L$3&"."&$L44&" IS '"&D44&"';" -> COMMENT ON COLUMN cop_sales_history.replace_reason_cde04 IS '交換理由 cde04'; | S44: loaner_status_cde VARCHAR(4),
B45: 31 | C45: warranty_service_ind04 | D45: 保証サービス ind04 | E45: VARCHAR | F45: 2 | G45: － | H45: 保証サービス利用インジケータ04 | L45: =C45 -> warranty_service_ind04 | M45: =E45&"("&F45&")," -> VARCHAR(2), | O45: ="COMMENT ON COLUMN "&$L$3&"."&$L45&" IS '"&D45&"';" -> COMMENT ON COLUMN cop_sales_history.warranty_service_ind04 IS '保証サービス ind04'; | S45: CONSTRAINT pk_cop_sales_history PRIMARY KEY (id));
H46: Y：保証サービス利用あり | L46: =C46 -> 0 | M46: =E46&"("&F46&")," -> (), | O46: ="COMMENT ON COLUMN "&$L$3&"."&$L46&" IS '"&D46&"';" -> COMMENT ON COLUMN cop_sales_history.0 IS ''; | S46: COMMENT ON TABLE cop_sales_history IS 'b_cop_販売履歴';
B47: 32 | C47: replace_reason_cde05 | D47: 交換理由 cde05 | E47: VARCHAR | F47: 4 | G47: － | H47: 故障交換理由コード05 | I47: OMコードリファレンス#0076 | L47: =C47 -> replace_reason_cde05 | M47: =E47&"("&F47&")," -> VARCHAR(4), | O47: ="COMMENT ON COLUMN "&$L$3&"."&$L47&" IS '"&D47&"';" -> COMMENT ON COLUMN cop_sales_history.replace_reason_cde05 IS '交換理由 cde05'; | S47: COMMENT ON COLUMN cop_sales_history.id IS 'id';
B48: 33 | C48: warranty_service_ind05 | D48: 保証サービス ind05 | E48: VARCHAR | F48: 2 | G48: － | H48: 保証サービス利用インジケータ05 | L48: =C48 -> warranty_service_ind05 | M48: =E48&"("&F48&")," -> VARCHAR(2), | O48: ="COMMENT ON COLUMN "&$L$3&"."&$L48&" IS '"&D48&"';" -> COMMENT ON COLUMN cop_sales_history.warranty_service_ind05 IS '保証サービス ind05'; | S48: COMMENT ON COLUMN cop_sales_history.service_id IS 'サービスID';
H49: Y：保証サービス利用あり | L49: =C49 -> 0 | M49: =E49&"("&F49&")," -> (), | O49: ="COMMENT ON COLUMN "&$L$3&"."&$L49&" IS '"&D49&"';" -> COMMENT ON COLUMN cop_sales_history.0 IS ''; | S49: COMMENT ON COLUMN cop_sales_history.bill_group_id IS '請求書グループID';
B50: 34 | C50: before_equipment_serial_nbr | D50: 交換前機器シリアル番号 | E50: VARCHAR | F50: 60 | G50: － | H50: 変更前シリアル番号 | L50: =C50 -> before_equipment_serial_nbr | M50: =E50&"("&F50&")," -> VARCHAR(60), | O50: ="COMMENT ON COLUMN "&$L$3&"."&$L50&" IS '"&D50&"';" -> COMMENT ON COLUMN cop_sales_history.before_equipment_serial_nbr IS '交換前機器シリアル番号'; | S50: COMMENT ON COLUMN cop_sales_history.contractor_id IS '契約者ID';
B51: 35 | C51: before_rec_seq_nbr | D51: 交換前受付シーケンス番号 | E51: DECIMAL | F51: 38,0 | G51: － | H51: 変更前レコード通番 | J51: X3対応(桁変更) | L51: =C51 -> before_rec_seq_nbr | M51: =E51&"("&F51&")," -> DECIMAL(38,0), | O51: ="COMMENT ON COLUMN "&$L$3&"."&$L51&" IS '"&D51&"';" -> COMMENT ON COLUMN cop_sales_history.before_rec_seq_nbr IS '交換前受付シーケンス番号'; | S51: COMMENT ON COLUMN cop_sales_history.item_nbr IS '商品番号';
B52: 36 | C52: loaner_status_cde | D52: 貸出状況 cde | E52: VARCHAR | F52: 4 | G52: － | H52: 代替機ステータスコード | I52: OMコードリファレンス#0075 | L52: =C52 -> loaner_status_cde | M52: =E52&"("&F52&")," -> VARCHAR(4), | O52: ="COMMENT ON COLUMN "&$L$3&"."&$L52&" IS '"&D52&"';" -> COMMENT ON COLUMN cop_sales_history.loaner_status_cde IS '貸出状況 cde'; | S52: COMMENT ON COLUMN cop_sales_history.equipment_serial_nbr IS '機器シリアル番号';
L53: ="CONSTRAINT pk_"&L3&" PRIMARY KEY (id));" -> CONSTRAINT pk_cop_sales_history PRIMARY KEY (id)); | S53: COMMENT ON COLUMN cop_sales_history.created_dt IS '作成日時';
S54: COMMENT ON COLUMN cop_sales_history.created_tm IS '作成日時_tm';
S55: COMMENT ON COLUMN cop_sales_history.delete_ind IS '削除_ind';
S56: COMMENT ON COLUMN cop_sales_history.selling_dt IS '販売日時_tt';
S57: COMMENT ON COLUMN cop_sales_history.selling_cancel_dt IS '販売キャンセル日時_tt';
S58: COMMENT ON COLUMN cop_sales_history.selling_type_cde IS '販売タイプ_cde';
S59: COMMENT ON COLUMN cop_sales_history.selling_reason_cde IS '販売理由_cde';
S60: COMMENT ON COLUMN cop_sales_history.cancellation_reason_cde IS 'キャンセル理由_cde';
S61: COMMENT ON COLUMN cop_sales_history.selling_status_cde IS '販売ステータス_cde';
S62: COMMENT ON COLUMN cop_sales_history.svc_org_id IS 'サービス提供組織ID';
S63: COMMENT ON COLUMN cop_sales_history.cancellation_svc_org_id IS 'キャンセルサービス提供組織ID';
S64: COMMENT ON COLUMN cop_sales_history.selling_method_cde IS '販売方法_cde';
S65: COMMENT ON COLUMN cop_sales_history.battery_pack_stat_cde IS 'バッテリーパックステータス_cde';
... S83: COMMENT ON COLUMN cop_sales_history.loaner_status_cde IS '貸出状況 cde';

Sheet (COP)機器割当
G2: 種別 | H2: DWH公開名 | I2: 旧DWH公開名 | J2: 統合テーブルID | K2: スキーマ
G3: ビュー | H3: b_cop_機器割当 | I3: B_機器割当_[権限] | J3: V000678 | K3: user_l2id | L3: cop_equipment_allocation
G4: データ概要：
G5: 回線が使用している機器（USIM、2G/3G移動機など）を管理。
L6: ="DROP TABLE IF EXISTS "&L3&" CASCADE;" -> DROP TABLE IF EXISTS cop_equipment_allocation CASCADE; | S6: DROP TABLE IF EXISTS cop_equipment_allocation CASCADE;
L7: ="CREATE TABLE IF NOT EXISTS "&L3&" (" -> CREATE TABLE IF NOT EXISTS cop_equipment_allocation ( | O7: ="COMMENT ON TABLE "&L3&" IS '"&H3&"';" -> COMMENT ON TABLE cop_equipment_allocation IS 'b_cop_機器割当'; | S7: CREATE TABLE IF NOT EXISTS cop_equipment_allocation (
A8: pk | B8: SEQ | C8: 項目名 | D8: TYPE | F8: 桁 | G8: 仮名化 | H8: 項目説明およびリスト値 | I8: コードリファレンスリンク | J8: 備考 | K8: 更新日 | L8: id BIGINT GENERATED BY DEFAULT AS IDENTITY, | O8: ="COMMENT ON COLUMN "&$L$3&".id IS 'id';" -> COMMENT ON COLUMN cop_equipment_allocation.id IS 'id'; | S8: id BIGINT GENERATED BY DEFAULT AS IDENTITY,
B9: 1 | C9: ifdb_proc_type | D9: VARCHAR | E9: ifdb プロセスタイプ | F9: 2 | G9: － | H9: 変更種別 | I9: DWHコードリファレンス#0008 | L9: =C9 -> ifdb_proc_type | M9: =D9&"("&F9&")," -> VARCHAR(2), | O9: ="COMMENT ON COLUMN "&$L$3&"."&$L9&" IS '"&E9&"';" -> COMMENT ON COLUMN cop_equipment_allocation.ifdb_proc_type IS 'ifdb プロセスタイプ'; | S9: ifdb_proc_type VARCHAR(2),
B10: 2 | C10: service_id | D10: VARCHAR | E10: サービスID | F10: 40 | G10: ○ | H10: サービスID(S#) | J10: ・H制御Viewでは仮名加工された値が表示されます | L10: =C10 -> service_id | M10: =D10&"("&F10&")," -> VARCHAR(40), | O10: ="COMMENT ON COLUMN "&$L$3&"."&$L10&" IS '"&E10&"';" -> COMMENT ON COLUMN cop_equipment_allocation.service_id IS 'サービスID'; | S10: service_id VARCHAR(40),
B11: 3 | C11: equipment_type_cde | D11: VARCHAR | E11: 機器タイプ CDE | F11: 4 | G11: － | H11: 機器タイプコード | I11: OMコードリファレンス#0031 | L11: =C11 -> equipment_type_cde | M11: =D11&"("&F11&")," -> VARCHAR(4), | O11: ="COMMENT ON COLUMN "&$L$3&"."&$L11&" IS '"&E11&"';" -> COMMENT ON COLUMN cop_equipment_allocation.equipment_type_cde IS '機器タイプ CDE'; | S11: equipment_type_cde VARCHAR(4),
B12: 4 | C12: equipment_serial_nbr | D12: VARCHAR | E12: 機器シリアル番号 | F12: 60 | G12: － | H12: 機器のシリアル番号 | L12: =C12 -> equipment_serial_nbr | M12: =D12&"("&F12&")," -> VARCHAR(60), | O12: ="COMMENT ON COLUMN "&$L$3&"."&$L12&" IS '"&E12&"';" -> COMMENT ON COLUMN cop_equipment_allocation.equipment_serial_nbr IS '機器シリアル番号'; | S12: equipment_serial_nbr VARCHAR(60),
H13: (Integrated Circuit Card Identity) USIMを特定するためのICカードID | L13: =C13 -> 0 | M13: =D13&"("&F13&")," -> (), | O13: ="COMMENT ON COLUMN "&$L$3&"."&$L13&" IS '"&E13&"';" -> COMMENT ON COLUMN cop_equipment_allocation.0 IS ''; | S13: effective_dt_from VARCHAR(16),
B14: 5 | C14: effective_dt_from | D14: VARCHAR | E14: 有効日付開始 | F14: 16 | G14: － | H14: 有効開始日(YYYYMMDD) | L14: =C14 -> effective_dt_from | M14: =D14&"("&F14&")," -> VARCHAR(16), | O14: ="COMMENT ON COLUMN "&$L$3&"."&$L14&" IS '"&E14&"';" -> COMMENT ON COLUMN cop_equipment_allocation.effective_dt_from IS '有効日付開始'; | S14: effective_dt_to VARCHAR(16),
B15: 6 | C15: effective_dt_to | D15: VARCHAR | E15: 有効日付終了 | F15: 16 | G15: － | H15: 有効終了日(YYYYMMDD): 有効である場合は9999/12/3 | L15: =C15 -> effective_dt_to | M15: =D15&"("&F15&")," -> VARCHAR(16), | O15: ="COMMENT ON COLUMN "&$L$3&"."&$L15&" IS '"&E15&"';" -> COMMENT ON COLUMN cop_equipment_allocation.effective_dt_to IS '有効日付終了'; | S15: record_sequence_nbr DECIMAL(38,0),
A16: ○ | B16: 7 | C16: record_sequence_nbr | D16: DECIMAL | E16: レコードシーケンス番号 | F16: 38,0 | G16: － | H16: レコード通番 | J16: X3対応(桁変更) | L16: =C16 -> record_sequence_nbr | M16: =D16&"("&F16&")," -> DECIMAL(38,0), | O16: ="COMMENT ON COLUMN "&$L$3&"."&$L16&" IS '"&E16&"';" -> COMMENT ON COLUMN cop_equipment_allocation.record_sequence_nbr IS 'レコードシーケンス番号'; | S16: transaction_nbr DECIMAL(15,0),
B17: 8 | C17: transaction_nbr | D17: DECIMAL | E17: トランザクション番号 | F17: 15,0 | G17: － | H17: トランザクション番号 | J17: X3対応(桁変更) | L17: =C17 -> transaction_nbr | M17: =D17&"("&F17&")," -> DECIMAL(15,0), | O17: ="COMMENT ON COLUMN "&$L$3&"."&$L17&" IS '"&E17&"';" -> COMMENT ON COLUMN cop_equipment_allocation.transaction_nbr IS 'トランザクション番号'; | S17: created_dt VARCHAR(16),
B18: 9 | C18: created_dt | D18: VARCHAR | E18: 作成日付 | F18: 16 | G18: － | H18: 作成日(YYYYMMDD): 移動機が販売され、回線と移動機が紐づいた日付 | L18: =C18 -> created_dt | M18: =D18&"("&F18&")," -> VARCHAR(16), | O18: ="COMMENT ON COLUMN "&$L$3&"."&$L18&" IS '"&E18&"';" -> COMMENT ON COLUMN cop_equipment_allocation.created_dt IS '作成日付'; | S18: created_tm VARCHAR(12),
B19: 10 | C19: created_tm | D19: VARCHAR | E19: 作成日時 | F19: 12 | G19: － | H19: 作成時間(HHMMSS) | L19: =C19 -> created_tm | M19: =D19&"("&F19&")," -> VARCHAR(12), | O19: ="COMMENT ON COLUMN "&$L$3&"."&$L19&" IS '"&E19&"';" -> COMMENT ON COLUMN cop_equipment_allocation.created_tm IS '作成日時'; | S19: last_updated_dt VARCHAR(16),
B20: 11 | C20: last_updated_dt | D20: VARCHAR | E20: 最終更新日付 | F20: 16 | G20: － | H20: 最終更新日(YYYYMMDD): 最後に買替や解約が行われた日付 | L20: =C20 -> last_updated_dt | M20: =D20&"("&F20&")," -> VARCHAR(16), | O20: ="COMMENT ON COLUMN "&$L$3&"."&$L20&" IS '"&E20&"';" -> COMMENT ON COLUMN cop_equipment_allocation.last_updated_dt IS '最終更新日付'; | S20: last_updated_tm VARCHAR(12),
B21: 12 | C21: last_updated_tm | D21: VARCHAR | E21: 最終更新日時 | F21: 12 | G21: － | H21: 最終更新時間(HHMMSS) | L21: =C21 -> last_updated_tm | M21: =D21&"("&F21&")," -> VARCHAR(12), | O21: ="COMMENT ON COLUMN "&$L$3&"."&$L21&" IS '"&E21&"';" -> COMMENT ON COLUMN cop_equipment_allocation.last_updated_tm IS '最終更新日時'; | S21: delete_ind VARCHAR(2),
B22: 13 | C22: delete_ind | D22: VARCHAR | E22: インデックス削除 | F22: 2 | G22: － | H22: N：有効レコード | L22: =C22 -> delete_ind | M22: =D22&"("&F22&")," -> VARCHAR(2), | O22: ="COMMENT ON COLUMN "&$L$3&"."&$L22&" IS '"&E22&"';" -> COMMENT ON COLUMN cop_equipment_allocation.delete_ind IS 'インデックス削除'; | S22: imsi_nbr VARCHAR(30),
H23: Y：論理削除（DWHでは物理削除されるため、存在しない） | L23: =C23 -> 0 | M23: =D23&"("&F23&")," -> (), | O23: ="COMMENT ON COLUMN "&$L$3&"."&$L23&" IS '"&E23&"';" -> COMMENT ON COLUMN cop_equipment_allocation.0 IS ''; | S23: item_nbr VARCHAR(40),
B24: 14 | C24: imsi_nbr | D24: VARCHAR | E24: IMSI 番号 | F24: 30 | G24: ○ | H24: IMSI番号 | J24: ・H制御Viewでは仮名加工された値が表示されます | L24: =C24 -> imsi_nbr | M24: =D24&"("&F24&")," -> VARCHAR(30), | O24: ="COMMENT ON COLUMN "&$L$3&"."&$L24&" IS '"&E24&"';" -> COMMENT ON COLUMN cop_equipment_allocation.imsi_nbr IS 'IMSI 番号'; | S24: deactivate_ind VARCHAR(2),
B25: 15 | C25: item_nbr | D25: VARCHAR | E25: アイテム番号 | F25: 40 | G25: － | H25: アイテム番号 | L25: =C25 -> item_nbr | M25: =D25&"("&F25&")," -> VARCHAR(40), | O25: ="COMMENT ON COLUMN "&$L$3&"."&$L25&" IS '"&E25&"';" -> COMMENT ON COLUMN cop_equipment_allocation.item_nbr IS 'アイテム番号'; | S25: CONSTRAINT pk_cop_equipment_allocation PRIMARY KEY (id));
B26: 16 | C26: deactivate_ind | D26: VARCHAR | E26: インデックス無効化 | F26: 2 | G26: － | H26: 解約インジケータ: 回線が解約された日付 | I26: DWHコードリファレンス#0009 | L26: =C26 -> deactivate_ind | M26: =D26&"("&F26&")," -> VARCHAR(2), | O26: ="COMMENT ON COLUMN "&$L$3&"."&$L26&" IS '"&E26&"';" -> COMMENT ON COLUMN cop_equipment_allocation.deactivate_ind IS 'インデックス無効化'; | S26: COMMENT ON TABLE cop_equipment_allocation IS 'b_cop_機器割当';
L27: ="CONSTRAINT pk_"&L3&" PRIMARY KEY (id));" -> CONSTRAINT pk_cop_equipment_allocation PRIMARY KEY (id)); | S27: COMMENT ON COLUMN cop_equipment_allocation.id IS 'id';
S28: COMMENT ON COLUMN cop_equipment_allocation.ifdb_proc_type IS 'ifdb プロセスタイプ';
S29: COMMENT ON COLUMN cop_equipment_allocation.service_id IS 'サービスID';
S30: COMMENT ON COLUMN cop_equipment_allocation.equipment_type_cde IS '機器タイプ CDE';
S31: COMMENT ON COLUMN cop_equipment_allocation.equipment_serial_nbr IS '機器シリアル番号';
S32: COMMENT ON COLUMN cop_equipment_allocation.effective_dt_from IS '有効日付開始';
S33: COMMENT ON COLUMN cop_equipment_allocation.effective_dt_to IS '有効日付終了';
S34: COMMENT ON COLUMN cop_equipment_allocation.record_sequence_nbr IS 'レコードシーケンス番号';
S35: COMMENT ON COLUMN cop_equipment_allocation.transaction_nbr IS 'トランザクション番号';
S36: COMMENT ON COLUMN cop_equipment_allocation.created_dt IS '作成日付';
S37: COMMENT ON COLUMN cop_equipment_allocation.created_tm IS '作成日時';
S38: COMMENT ON COLUMN cop_equipment_allocation.last_updated_dt IS '最終更新日付';
S39: COMMENT ON COLUMN cop_equipment_allocation.last_updated_tm IS '最終更新日時';
... S43: COMMENT ON COLUMN cop_equipment_allocation.deactivate_ind IS 'インデックス無効化';

Sheet (COP)プロダクト
G2: 種別 | H2: DWH公開名 | I2: 旧DWH公開名 | J2: 統合テーブルID | K2: スキーマ
G3: ビュー | H3: b_cop_プロダクト | I3: B_プロダクト_[権限] | J3: V000517 | K3: user_l2id | L3: cop_product
G4: データ概要：
G5: 回線に提供されるプラン、オプションサービス、割引サービスや、請求Ｇに提供される割引サービスを管理。
G6: M_プロダクトINFOの「プロダクトID」と紐づけることでカタログ名を取得可能
G7: （参考資料）プロダクトカタログ、プロダクトデータモデル（配置場所：ユーザヘルプ＞データ項目一覧＞個別説明資料）
G9: ※以下の場合にレコードが削除されます
G10: ・該当のS＃が解約されて10年後
G11: ・未来日の取り消し →受付後、適用開始前にオプション解除パターン
G12: ・受付と同じ日付でのオプション解除 →受付、即適用開始後、同日にオプション解除したパターン
L13: ="DROP TABLE IF EXISTS "&L3&" CASCADE;" -> DROP TABLE IF EXISTS cop_product CASCADE; | S13: DROP TABLE IF EXISTS cop_product CASCADE;
L14: ="CREATE TABLE IF NOT EXISTS "&L3&" (" -> CREATE TABLE IF NOT EXISTS cop_product ( | O14: ="COMMENT ON TABLE "&L3&" IS '"&H3&"';" -> COMMENT ON TABLE cop_product IS 'b_cop_プロダクト'; | S14: CREATE TABLE IF NOT EXISTS cop_product (
A15: pk | B15: SEQ | C15: 項目名 | E15: TYPE | F15: 桁 | G15: 仮名化 | H15: 項目説明およびリスト値 | I15: コードリファレンスリンク | J15: 備考 | K15: 更新日 | L15: id BIGINT GENERATED BY DEFAULT AS IDENTITY, | O15: ="COMMENT ON COLUMN "&$L$3&".id IS 'id';" -> COMMENT ON COLUMN cop_product.id IS 'id'; | S15: id BIGINT GENERATED BY DEFAULT AS IDENTITY,
A16: ○ | B16: 1 | C16: record_sequence_nbr | D16: レコードシーケンス番号 | E16: DECIMAL | F16: 38,0 | G16: － | H16: レコード通番（B_プロダクト属性とのキー） | J16: X3対応(桁変更) | L16: =C16 -> record_sequence_nbr | M16: =E16&"("&F16&")," -> DECIMAL(38,0), | O16: ="COMMENT ON COLUMN "&$L$3&"."&$L16&" IS '"&D16&"';" -> COMMENT ON COLUMN cop_product.record_sequence_nbr IS 'レコードシーケンス番号'; | S16: record_sequence_nbr DECIMAL(38,0),
B17: 2 | C17: ifdb_proc_type | D17: ifdb proc タイプ | E17: VARCHAR | F17: 2 | G17: － | H17: 変更種別 | I17: DWHコードリファレンス#0008 | L17: =C17 -> ifdb_proc_type | M17: =E17&"("&F17&")," -> VARCHAR(2), | O17: ="COMMENT ON COLUMN "&$L$3&"."&$L17&" IS '"&D17&"';" -> COMMENT ON COLUMN cop_product.ifdb_proc_type IS 'ifdb proc タイプ'; | S17: ifdb_proc_type VARCHAR(2),
B18: 3 | C18: key_type_cde | D18: キータイプ cde | E18: VARCHAR | F18: 4 | G18: － | H18: キータイプコード | I18: OMコードリファレンス#0021 | L18: =C18 -> key_type_cde | M18: =E18&"("&F18&")," -> VARCHAR(4), | O18: ="COMMENT ON COLUMN "&$L$3&"."&$L18&" IS '"&D18&"';" -> COMMENT ON COLUMN cop_product.key_type_cde IS 'キータイプ cde'; | S18: key_type_cde VARCHAR(4),
B19: 4 | C19: key_id | D19: キー ID | E19: VARCHAR | F19: 40 | G19: ○ | H19: キーID | J19: ・H制御Viewでは仮名加工された値が表示されます | L19: =C19 -> key_id | M19: =E19&"("&F19&")," -> VARCHAR(40), | O19: ="COMMENT ON COLUMN "&$L$3&"."&$L19&" IS '"&D19&"';" -> COMMENT ON COLUMN cop_product.key_id IS 'キー ID'; | S19: key_id VARCHAR(40),
H20: ※KEY_TYPE_CDEの値により、格納されている値の意味が変化 | L20: =C20 -> 0 | M20: =E20&"("&F20&")," -> (), | O20: ="COMMENT ON COLUMN "&$L$3&"."&$L20&" IS '"&D20&"';" -> COMMENT ON COLUMN cop_product.0 IS ''; | S20: product_category_cde VARCHAR(40),
B21: 5 | C21: product_category_cde | D21: 製品カテゴリ cde | E21: VARCHAR | F21: 40 | G21: － | H21: プロダクトカテゴリーコード | K21: ★項目説明修正（2019/07/05） | L21: =C21 -> product_category_cde | M21: =E21&"("&F21&")," -> VARCHAR(40), | O21: ="COMMENT ON COLUMN "&$L$3&"."&$L21&" IS '"&D21&"';" -> COMMENT ON COLUMN cop_product.product_category_cde IS '製品カテゴリ cde'; | S21: product_id VARCHAR(40),
H22: プロダクトカタログのプロダクト分類 | L22: =C22 -> 0 | M22: =E22&"("&F22&")," -> (), | O22: ="COMMENT ON COLUMN "&$L$3&"."&$L22&" IS '"&D22&"';" -> COMMENT ON COLUMN cop_product.0 IS ''; | S22: effective_dt_from VARCHAR(16),
B23: 6 | C23: product_id | D23: 製品 ID | E23: VARCHAR | F23: 40 | G23: － | H23: プロダクトID | I23: OMコードリファレンス#0043 | K23: ★項目説明修正（2019/07/05） | L23: =C23 -> product_id | M23: =E23&"("&F23&")," -> VARCHAR(40), | O23: ="COMMENT ON COLUMN "&$L$3&"."&$L23&" IS '"&D23&"';" -> COMMENT ON COLUMN cop_product.product_id IS '製品 ID'; | S23: effective_dt_to VARCHAR(16),
H24: M_プロダクトINFOにて説明を確認可能 | L24: =C24 -> 0 | M24: =E24&"("&F24&")," -> (), | O24: ="COMMENT ON COLUMN "&$L$3&"."&$L24&" IS '"&D24&"';" -> COMMENT ON COLUMN cop_product.0 IS ''; | S24: transaction_nbr DECIMAL(15,0),
B25: 7 | C25: effective_dt_from | D25: 有効データ送信元 | E25: VARCHAR | F25: 16 | G25: － | H25: 有効開始日(YYYYMMDD) | L25: =C25 -> effective_dt_from | M25: =E25&"("&F25&")," -> VARCHAR(16), | O25: ="COMMENT ON COLUMN "&$L$3&"."&$L25&" IS '"&D25&"';" -> COMMENT ON COLUMN cop_product.effective_dt_from IS '有効データ送信元'; | S25: created_by_user_id VARCHAR(200),
B26: 8 | C26: effective_dt_to | D26: 有効データ送信先 | E26: VARCHAR | F26: 16 | G26: － | H26: 有効終了日(YYYYMMDD) | L26: =C26 -> effective_dt_to | M26: =E26&"("&F26&")," -> VARCHAR(16), | O26: ="COMMENT ON COLUMN "&$L$3&"."&$L26&" IS '"&D26&"';" -> COMMENT ON COLUMN cop_product.effective_dt_to IS '有効データ送信先'; | S26: created_dt VARCHAR(16),
B27: 9 | C27: transaction_nbr | D27: トランザクション番号 | E27: DECIMAL | F27: 15,0 | G27: － | H27: トランザクション番号 | J27: X3対応(桁変更) | L27: =C27 -> transaction_nbr | M27: =E27&"("&F27&")," -> DECIMAL(15,0), | O27: ="COMMENT ON COLUMN "&$L$3&"."&$L27&" IS '"&D27&"';" -> COMMENT ON COLUMN cop_product.transaction_nbr IS 'トランザクション番号'; | S27: created_tm VARCHAR(12),
B28: 10 | C28: created_by_user_id | D28: 作成者ユーザー ID | E28: VARCHAR | F28: 200 | G28: － | H28: 作成ユーザID | K28: ★項目追加（2025/07/09） | L28: =C28 -> created_by_user_id | M28: =E28&"("&F28&")," -> VARCHAR(200), | O28: ="COMMENT ON COLUMN "&$L$3&"."&$L28&" IS '"&D28&"';" -> COMMENT ON COLUMN cop_product.created_by_user_id IS '作成者ユーザー ID'; | S28: last_updated_dt VARCHAR(16),
B29: 11 | C29: created_dt | D29: 作成データ | E29: VARCHAR | F29: 16 | G29: － | H29: 作成日(YYYYMMDD) | L29: =C29 -> created_dt | M29: =E29&"("&F29&")," -> VARCHAR(16), | O29: ="COMMENT ON COLUMN "&$L$3&"."&$L29&" IS '"&D29&"';" -> COMMENT ON COLUMN cop_product.created_dt IS '作成データ'; | S29: last_updated_tm VARCHAR(12),
B30: 12 | C30: created_tm | D30: 作成日時 tm | E30: VARCHAR | F30: 12 | G30: － | H30: 作成時間(HHMMSS) | L30: =C30 -> created_tm | M30: =E30&"("&F30&")," -> VARCHAR(12), | O30: ="COMMENT ON COLUMN "&$L$3&"."&$L30&" IS '"&D30&"';" -> COMMENT ON COLUMN cop_product.created_tm IS '作成日時 tm'; | S30: last_updated_user_id VARCHAR(200),
B31: 13 | C31: last_updated_dt | D31: 最終更新日時 tm | E31: VARCHAR | F31: 16 | G31: － | H31: 最終更新日(YYYYMMDD) | L31: =C31 -> last_updated_dt | M31: =E31&"("&F31&")," -> VARCHAR(16), | O31: ="COMMENT ON COLUMN "&$L$3&"."&$L31&" IS '"&D31&"';" -> COMMENT ON COLUMN cop_product.last_updated_dt IS '最終更新日時 tm'; | S31: delete_ind VARCHAR(2),
B32: 14 | C32: last_updated_tm | D32: 最終更新日時 tm | E32: VARCHAR | F32: 12 | G32: － | H32: 最終更新時間(HHMMSS) | L32: =C32 -> last_updated_tm | M32: =E32&"("&F32&")," -> VARCHAR(12), | O32: ="COMMENT ON COLUMN "&$L$3&"."&$L32&" IS '"&D32&"';" -> COMMENT ON COLUMN cop_product.last_updated_tm IS '最終更新日時 tm'; | S32: svc_org_id VARCHAR(40),
B33: 15 | C33: last_updated_user_id | D33: 最終更新ユーザー ID | E33: VARCHAR | F33: 200 | G33: － | H33: 最終更新ユーザID | K33: ★項目追加（2025/07/09） | L33: =C33 -> last_updated_user_id | M33: =E33&"("&F33&")," -> VARCHAR(200), | O33: ="COMMENT ON COLUMN "&$L$3&"."&$L33&" IS '"&D33&"';" -> COMMENT ON COLUMN cop_product.last_updated_user_id IS '最終更新ユーザー ID'; | S33: agent_id VARCHAR(40),
B34: 16 | C34: delete_ind | D34: 削除インデックス | E34: VARCHAR | F34: 2 | G34: － | H34: N：有効レコード | L34: =C34 -> delete_ind | M34: =E34&"("&F34&")," -> VARCHAR(2), | O34: ="COMMENT ON COLUMN "&$L$3&"."&$L34&" IS '"&D34&"';" -> COMMENT ON COLUMN cop_product.delete_ind IS '削除インデックス'; | S34: deactivate_ind VARCHAR(2),
H35: Y：論理削除（DWHでは物理削除されるため、存在しない） | L35: =C35 -> 0 | M35: =E35&"("&F35&")," -> (), | O35: ="COMMENT ON COLUMN "&$L$3&"."&$L35&" IS '"&D35&"';" -> COMMENT ON COLUMN cop_product.0 IS ''; | S35: application_dt VARCHAR(20),
B36: 17 | C36: svc_org_id | D36: サービス組織 ID | E36: VARCHAR | F36: 40 | G36: － | H36: サービス組織ID | L36: =C36 -> svc_org_id | M36: =E36&"("&F36&")," -> VARCHAR(40), | O36: ="COMMENT ON COLUMN "&$L$3&"."&$L36&" IS '"&D36&"';" -> COMMENT ON COLUMN cop_product.svc_org_id IS 'サービス組織 ID'; | S36: CONSTRAINT pk_cop_product PRIMARY KEY (id));
B37: 18 | C37: agent_id | D37: エージェント ID | E37: VARCHAR | F37: 40 | G37: － | H37: 営業担当者ID | L37: =C37 -> agent_id | M37: =E37&"("&F37&")," -> VARCHAR(40), | O37: ="COMMENT ON COLUMN "&$L$3&"."&$L37&" IS '"&D37&"';" -> COMMENT ON COLUMN cop_product.agent_id IS 'エージェント ID'; | S37: COMMENT ON TABLE cop_product IS 'b_cop_プロダクト';
B38: 19 | C38: deactivate_ind | D38: 無効化インデックス | E38: VARCHAR | F38: 2 | G38: － | H38: 解約インジケータ | I38: DWHコードリファレンス#0009 | L38: =C38 -> deactivate_ind | M38: =E38&"("&F38&")," -> VARCHAR(2), | O38: ="COMMENT ON COLUMN "&$L$3&"."&$L38&" IS '"&D38&"';" -> COMMENT ON COLUMN cop_product.deactivate_ind IS '無効化インデックス'; | S38: COMMENT ON COLUMN cop_product.id IS 'id';
B39: 20 | C39: application_dt | D39: アプリケーション ID | E39: VARCHAR | F39: 20 | G39: － | H39: 申込日(YYYYMMDD HH:MM:SS) | K39: ★項目追加（2025/07/09） | L39: =C39 -> application_dt | M39: =E39&"("&F39&")," -> VARCHAR(20), | O39: ="COMMENT ON COLUMN "&$L$3&"."&$L39&" IS '"&D39&"';" -> COMMENT ON COLUMN cop_product.application_dt IS 'アプリケーション ID'; | S39: COMMENT ON COLUMN cop_product.record_sequence_nbr IS 'レコードシーケンス番号';
L40: ="CONSTRAINT pk_"&L3&" PRIMARY KEY (id));" -> CONSTRAINT pk_cop_product PRIMARY KEY (id)); | S40: COMMENT ON COLUMN cop_product.ifdb_proc_type IS 'ifdb proc タイプ';
S41: COMMENT ON COLUMN cop_product.key_type_cde IS 'キータイプ cde';
S42: COMMENT ON COLUMN cop_product.key_id IS 'キー ID';
S43: COMMENT ON COLUMN cop_product.product_category_cde IS '製品カテゴリ cde';
S44: COMMENT ON COLUMN cop_product.product_id IS '製品 ID';
S45: COMMENT ON COLUMN cop_product.effective_dt_from IS '有効データ送信元';
S46: COMMENT ON COLUMN cop_product.effective_dt_to IS '有効データ送信先';
S47: COMMENT ON COLUMN cop_product.transaction_nbr IS 'トランザクション番号';
S48: COMMENT ON COLUMN cop_product.created_by_user_id IS '作成者ユーザー ID';
S49: COMMENT ON COLUMN cop_product.created_dt IS '作成データ';
S50: COMMENT ON COLUMN cop_product.created_tm IS '作成日時 tm';
S51: COMMENT ON COLUMN cop_product.last_updated_dt IS '最終更新日時 tm';
S52: COMMENT ON COLUMN cop_product.last_updated_tm IS '最終更新日時 tm';
... S58: COMMENT ON COLUMN cop_product.application_dt IS 'アプリケーション ID';

Sheet (Mars)取次店
F2: 種別 | G2: DWH公開名 | H2: 旧DWH公開名 | I2: 統合テーブルID | J2: スキーマ
F3: ビュー | G3: m_取次店 | I3: V001776 | J3: user_l2 | K3: mars_agency_store
F4: データ概要：
F5: データ概要： 全ての代理店（親代理店及び、子代理店）情報を保有。 店舗で扱う商材についてソフトバンクや一次代理店等への発注、ソフトバンクからの請求を行う業務から「受注先」「請求先」という説明を記載しております。 M_取次店 :M_取次店_ALLから最新フラグが「1」のデータのみ抽出（前日断面情報、有効開始日が当日を除く） 有効終了日が1年以内の情報
K6: ="DROP TABLE IF EXISTS "&K3&" CASCADE;" -> DROP TABLE IF EXISTS mars_agency_store CASCADE; | R6: DROP TABLE IF EXISTS mars_agency_store CASCADE;
K7: ="CREATE TABLE IF NOT EXISTS "&K3&" (" -> CREATE TABLE IF NOT EXISTS mars_agency_store ( | N7: ="COMMENT ON TABLE "&K3&" IS '"&G3&"';" -> COMMENT ON TABLE mars_agency_store IS 'm_取次店'; | R7: CREATE TABLE IF NOT EXISTS mars_agency_store (
A8: pk | B8: SEQ | C8: 項目名 | D8: TYPE | E8: 桁 | F8: 仮名化 | G8: 項目説明およびリスト値 | H8: コードリファレンスリンク | I8: 備考 | J8: 更新日 | K8: id BIGINT GENERATED BY DEFAULT AS IDENTITY, | N8: ="COMMENT ON COLUMN "&$K$3&".id IS 'id';" -> COMMENT ON COLUMN mars_agency_store.id IS 'id'; | R8: id BIGINT GENERATED BY DEFAULT AS IDENTITY,
B9: 1 | C9: 取次店コード | D9: VARCHAR | E9: 40 | F9: － | K9: agent_code | L9: =D9&"("&E9&")," -> VARCHAR(40), | N9: ="COMMENT ON COLUMN "&$K$3&"."&$K9&" IS '"&C9&"';" -> COMMENT ON COLUMN mars_agency_store.agent_code IS '取次店コード'; | R9: agent_code VARCHAR(40),
B10: 2 | C10: 有効開始日 | D10: VARCHAR | E10: 16 | F10: － | K10: valid_start_date | L10: =D10&"("&E10&")," -> VARCHAR(16), | N10: ="COMMENT ON COLUMN "&$K$3&"."&$K10&" IS '"&C10&"';" -> COMMENT ON COLUMN mars_agency_store.valid_start_date IS '有効開始日'; | R10: valid_start_date VARCHAR(16),
B11: 3 | C11: 有効終了日 | D11: VARCHAR | E11: 16 | F11: － | K11: valid_end_date | L11: =D11&"("&E11&")," -> VARCHAR(16), | N11: ="COMMENT ON COLUMN "&$K$3&"."&$K11&" IS '"&C11&"';" -> COMMENT ON COLUMN mars_agency_store.valid_end_date IS '有効終了日'; | R11: valid_end_date VARCHAR(16),
B12: 4 | C12: 共通店舗コード | D12: VARCHAR | E12: 20 | F12: － | K12: common_store_code | L12: =D12&"("&E12&")," -> VARCHAR(20), | N12: ="COMMENT ON COLUMN "&$K$3&"."&$K12&" IS '"&C12&"';" -> COMMENT ON COLUMN mars_agency_store.common_store_code IS '共通店舗コード'; | R12: common_store_code VARCHAR(20),
B13: 5 | C13: chkdigit共通店舗cd | D13: VARCHAR | E13: 22 | F13: － | K13: chkdigit_common_store_cd | L13: =D13&"("&E13&")," -> VARCHAR(22), | N13: ="COMMENT ON COLUMN "&$K$3&"."&$K13&" IS '"&C13&"';" -> COMMENT ON COLUMN mars_agency_store.chkdigit_common_store_cd IS 'chkdigit共通店舗cd'; | R13: chkdigit_common_store_cd VARCHAR(22),
B14: 6 | C14: 物流取次店コード | D14: VARCHAR | E14: 40 | F14: － | K14: logistics_agent_code | L14: =D14&"("&E14&")," -> VARCHAR(40), | N14: ="COMMENT ON COLUMN "&$K$3&"."&$K14&" IS '"&C14&"';" -> COMMENT ON COLUMN mars_agency_store.logistics_agent_code IS '物流取次店コード'; | R14: logistics_agent_code VARCHAR(40),
B15: 7 | C15: chkdigit取次店cd | D15: VARCHAR | E15: 40 | F15: － | K15: chkdigit_agent_cd | L15: =D15&"("&E15&")," -> VARCHAR(40), | N15: ="COMMENT ON COLUMN "&$K$3&"."&$K15&" IS '"&C15&"';" -> COMMENT ON COLUMN mars_agency_store.chkdigit_agent_cd IS 'chkdigit取次店cd'; | R15: chkdigit_agent_cd VARCHAR(40),
B16: 8 | C16: フロント用コード | D16: VARCHAR | E16: 40 | F16: － | K16: front_desk_code | L16: =D16&"("&E16&")," -> VARCHAR(40), | N16: ="COMMENT ON COLUMN "&$K$3&"."&$K16&" IS '"&C16&"';" -> COMMENT ON COLUMN mars_agency_store.front_desk_code IS 'フロント用コード'; | R16: front_desk_code VARCHAR(40),
B17: 9 | C17: 一次代理店コード | D17: VARCHAR | E17: 40 | F17: － | K17: primary_agent_code | L17: =D17&"("&E17&")," -> VARCHAR(40), | N17: ="COMMENT ON COLUMN "&$K$3&"."&$K17&" IS '"&C17&"';" -> COMMENT ON COLUMN mars_agency_store.primary_agent_code IS '一次代理店コード'; | R17: primary_agent_code VARCHAR(40),
B18: 10 | C18: chkdigit一次代理店cd | D18: VARCHAR | E18: 40 | F18: － | K18: chkdigit_primary_agent_cd | L18: =D18&"("&E18&")," -> VARCHAR(40), | N18: ="COMMENT ON COLUMN "&$K$3&"."&$K18&" IS '"&C18&"';" -> COMMENT ON COLUMN mars_agency_store.chkdigit_primary_agent_cd IS 'chkdigit一次代理店cd'; | R18: chkdigit_primary_agent_cd VARCHAR(40),
B19: 11 | C19: 集約一次代理店コード | D19: VARCHAR | E19: 40 | F19: － | K19: aggregated_primary_agent_code | L19: =D19&"("&E19&")," -> VARCHAR(40), | N19: ="COMMENT ON COLUMN "&$K$3&"."&$K19&" IS '"&C19&"';" -> COMMENT ON COLUMN mars_agency_store.aggregated_primary_agent_code IS '集約一次代理店コード'; | R19: aggregated_primary_agent_code VARCHAR(40),
B20: 12 | C20: chkdigit_集_一次代理店cd | D20: VARCHAR | E20: 40 | F20: － | K20: chkdigit_collected_primary_agent_cd | L20: =D20&"("&E20&")," -> VARCHAR(40), | N20: ="COMMENT ON COLUMN "&$K$3&"."&$K20&" IS '"&C20&"';" -> COMMENT ON COLUMN mars_agency_store.chkdigit_collected_primary_agent_cd IS 'chkdigit_集_一次代理店cd'; | R20: chkdigit_collected_primary_agent_cd VARCHAR(40),
... B22: 14 | C22: chkdigit集約取次店cd | D22: VARCHAR | E22: 40 | F22: － | K22: chkdigit_aggregated_agent_cd | L22: =D22&"("&E22&")," -> VARCHAR(40), | N22: ="COMMENT ON COLUMN "&$K$3&"."&$K22&" IS '"&C22&"';" -> COMMENT ON COLUMN mars_agency_store.chkdigit_aggregated_agent_cd IS 'chkdigit集約取次店cd'; | R22: chkdigit_aggregated_agent_cd VARCHAR(40),
B23: 15 | C23: 企業区分 | D23: DECIMAL | E23: 10,0 | F23: － | K23: company_category | L23: =D23&"("&E23&")," -> DECIMAL(10,0), | N23: ="COMMENT ON COLUMN "&$K$3&"."&$K23&" IS '"&C23&"';" -> COMMENT ON COLUMN mars_agency_store.company_category IS '企業区分'; | R23: company_category DECIMAL(10,0),
B24: 16 | C24: 企業区分正式名称 | D24: VARCHAR | E24: 1200 | F24: － | K24: company_category_official_name | L24: =D24&"("&E24&")," -> VARCHAR(1200), | N24: ="COMMENT ON COLUMN "&$K$3&"."&$K24&" IS '"&C24&"';" -> COMMENT ON COLUMN mars_agency_store.company_category_official_name IS '企業区分正式名称'; | R24: company_category_official_name VARCHAR(1200),
B25: 17 | C25: 店舗種別コード | D25: DECIMAL | E25: 10,0 | F25: － | K25: store_type_code | L25: =D25&"("&E25&")," -> DECIMAL(10,0), | N25: ="COMMENT ON COLUMN "&$K$3&"."&$K25&" IS '"&C25&"';" -> COMMENT ON COLUMN mars_agency_store.store_type_code IS '店舗種別コード'; | R25: store_type_code DECIMAL(10,0),
B26: 18 | C26: 店舗登録設定ptn_cd | D26: DECIMAL | E26: 10,0 | F26: － | K26: store_registration_settings_ptn_cd | L26: =D26&"("&E26&")," -> DECIMAL(10,0), | N26: ="COMMENT ON COLUMN "&$K$3&"."&$K26&" IS '"&C26&"';" -> COMMENT ON COLUMN mars_agency_store.store_registration_settings_ptn_cd IS '店舗登録設定ptn_cd'; | R26: store_registration_settings_ptn_cd DECIMAL(10,0),
B27: 19 | C27: 取次店正式名称 | D27: VARCHAR | E27: 1200 | F27: － | K27: aggregator_official_name | L27: =D27&"("&E27&")," -> VARCHAR(1200), | N27: ="COMMENT ON COLUMN "&$K$3&"."&$K27&" IS '"&C27&"';" -> COMMENT ON COLUMN mars_agency_store.aggregator_official_name IS '取次店正式名称'; | R27: aggregator_official_name VARCHAR(1200),
B28: 20 | C28: 取次店略称 | D28: VARCHAR | E28: 240 | F28: － | K28: aggregator_abbreviation | L28: =D28&"("&E28&")," -> VARCHAR(240), | N28: ="COMMENT ON COLUMN "&$K$3&"."&$K28&" IS '"&C28&"';" -> COMMENT ON COLUMN mars_agency_store.aggregator_abbreviation IS '取次店略称'; | R28: aggregator_abbreviation VARCHAR(240),
B29: 21 | C29: 取次店カナ名称 | D29: VARCHAR | E29: 1200 | F29: － | K29: aggregator_name_katakana | L29: =D29&"("&E29&")," -> VARCHAR(1200), | N29: ="COMMENT ON COLUMN "&$K$3&"."&$K29&" IS '"&C29&"';" -> COMMENT ON COLUMN mars_agency_store.aggregator_name_katakana IS '取次店カナ名称'; | R29: aggregator_name_katakana VARCHAR(1200),
B30: 22 | C30: 取次店英語名称 | D30: VARCHAR | E30: 1200 | F30: － | K30: aggregator_store_name_in_english | L30: =D30&"("&E30&")," -> VARCHAR(1200), | N30: ="COMMENT ON COLUMN "&$K$3&"."&$K30&" IS '"&C30&"';" -> COMMENT ON COLUMN mars_agency_store.aggregator_store_name_in_english IS '取次店英語名称'; | R30: aggregator_store_name_in_english VARCHAR(1200),
B31: 23 | C31: 登記簿登録法人名 | D31: VARCHAR | E31: 600 | F31: － | K31: registered_corporate_name | L31: =D31&"("&E31&")," -> VARCHAR(600), | N31: ="COMMENT ON COLUMN "&$K$3&"."&$K31&" IS '"&C31&"';" -> COMMENT ON COLUMN mars_agency_store.registered_corporate_name IS '登記簿登録法人名'; | R31: registered_corporate_name VARCHAR(600),
B32: 24 | C32: 地域コード | D32: VARCHAR | E32: 20 | F32: － | K32: area_code | L32: =D32&"("&E32&")," -> VARCHAR(20), | N32: ="COMMENT ON COLUMN "&$K$3&"."&$K32&" IS '"&C32&"';" -> COMMENT ON COLUMN mars_agency_store.area_code IS '地域コード'; | R32: area_code VARCHAR(20),
B33: 25 | C33: 地域正式名称 | D33: VARCHAR | E33: 1200 | F33: － | K33: area_official_name | L33: =D33&"("&E33&")," -> VARCHAR(1200), | N33: ="COMMENT ON COLUMN "&$K$3&"."&$K33&" IS '"&C33&"';" -> COMMENT ON COLUMN mars_agency_store.area_official_name IS '地域正式名称'; | R33: area_official_name VARCHAR(1200),
B34: 26 | C34: 地域英語コード | D34: VARCHAR | E34: 2 | F34: － | K34: area_english_code | L34: =D34&"("&E34&")," -> VARCHAR(2), | N34: ="COMMENT ON COLUMN "&$K$3&"."&$K34&" IS '"&C34&"';" -> COMMENT ON COLUMN mars_agency_store.area_english_code IS '地域英語コード'; | R34: area_english_code VARCHAR(2),
B35: 27 | C35: 地域半角カナ名称 | D35: VARCHAR | E35: 1200 | F35: － | K35: area_half_width_kana_name | L35: =D35&"("&E35&")," -> VARCHAR(1200), | N35: ="COMMENT ON COLUMN "&$K$3&"."&$K35&" IS '"&C35&"';" -> COMMENT ON COLUMN mars_agency_store.area_half_width_kana_name IS '地域半角カナ名称'; | R35: area_half_width_kana_name VARCHAR(1200),
B36: 28 | C36: 地域英語名称 | D36: VARCHAR | E36: 1200 | F36: － | K36: area_english_name | L36: =D36&"("&E36&")," -> VARCHAR(1200), | N36: ="COMMENT ON COLUMN "&$K$3&"."&$K36&" IS '"&C36&"';" -> COMMENT ON COLUMN mars_agency_store.area_english_name IS '地域英語名称'; | R36: area_english_name VARCHAR(1200),
B37: 29 | C37: 取次店郵便番号 | D37: VARCHAR | E37: 20 | F37: － | K37: agent_postal_code | L37: =D37&"("&E37&")," -> VARCHAR(20), | N37: ="COMMENT ON COLUMN "&$K$3&"."&$K37&" IS '"&C37&"';" -> COMMENT ON COLUMN mars_agency_store.agent_postal_code IS '取次店郵便番号'; | R37: agent_postal_code VARCHAR(20),
B38: 30 | C38: 都道府県コード | D38: VARCHAR | E38: 4 | F38: － | K38: prefecture_code | L38: =D38&"("&E38&")," -> VARCHAR(4), | N38: ="COMMENT ON COLUMN "&$K$3&"."&$K38&" IS '"&C38&"';" -> COMMENT ON COLUMN mars_agency_store.prefecture_code IS '都道府県コード'; | R38: prefecture_code VARCHAR(4),
... B40: 32 | C40: 都道府県漢字 | D40: VARCHAR | E40: 96 | F40: － | K40: prefecture_kanji | L40: =D40&"("&E40&")," -> VARCHAR(96), | N40: ="COMMENT ON COLUMN "&$K$3&"."&$K40&" IS '"&C40&"';" -> COMMENT ON COLUMN mars_agency_store.prefecture_kanji IS '都道府県漢字'; | R40: prefecture_kanji VARCHAR(96),
B41: 33 | C41: 震災フラグ | D41: DECIMAL | E41: 10,0 | F41: － | K41: earthquake_flag | L41: =D41&"("&E41&")," -> DECIMAL(10,0), | N41: ="COMMENT ON COLUMN "&$K$3&"."&$K41&" IS '"&C41&"';" -> COMMENT ON COLUMN mars_agency_store.earthquake_flag IS '震災フラグ'; | R41: earthquake_flag DECIMAL(10,0),
B42: 34 | C42: 震災フラグ正式名称 | D42: VARCHAR | E42: 720 | F42: － | K42: earthquake_flag_official_name | L42: =D42&"("&E42&")," -> VARCHAR(720), | N42: ="COMMENT ON COLUMN "&$K$3&"."&$K42&" IS '"&C42&"';" -> COMMENT ON COLUMN mars_agency_store.earthquake_flag_official_name IS '震災フラグ正式名称'; | R42: earthquake_flag_official_name VARCHAR(720),
B43: 35 | C43: 市区町村コード | D43: VARCHAR | E43: 6 | F43: － | K43: city_code | L43: =D43&"("&E43&")," -> VARCHAR(6), | N43: ="COMMENT ON COLUMN "&$K$3&"."&$K43&" IS '"&C43&"';" -> COMMENT ON COLUMN mars_agency_store.city_code IS '市区町村コード'; | R43: city_code VARCHAR(6),
B44: 36 | C44: 市区町村カナ | D44: VARCHAR | E44: 288 | F44: － | K44: city_kana | L44: =D44&"("&E44&")," -> VARCHAR(288), | N44: ="COMMENT ON COLUMN "&$K$3&"."&$K44&" IS '"&C44&"';" -> COMMENT ON COLUMN mars_agency_store.city_kana IS '市区町村カナ'; | R44: city_kana VARCHAR(288),
B45: 37 | C45: 市区町村漢字 | D45: VARCHAR | E45: 288 | F45: － | K45: city_kanji | L45: =D45&"("&E45&")," -> VARCHAR(288), | N45: ="COMMENT ON COLUMN "&$K$3&"."&$K45&" IS '"&C45&"';" -> COMMENT ON COLUMN mars_agency_store.city_kanji IS '市区町村漢字'; | R45: city_kanji VARCHAR(288),
B46: 38 | C46: 通称コード | D46: VARCHAR | E46: 6 | F46: － | K46: common_name_code | L46: =D46&"("&E46&")," -> VARCHAR(6), | N46: ="COMMENT ON COLUMN "&$K$3&"."&$K46&" IS '"&C46&"';" -> COMMENT ON COLUMN mars_agency_store.common_name_code IS '通称コード'; | R46: common_name_code VARCHAR(6),
B47: 39 | C47: 通称カナ | D47: VARCHAR | E47: 432 | F47: － | K47: common_name_kana | L47: =D47&"("&E47&")," -> VARCHAR(432), | N47: ="COMMENT ON COLUMN "&$K$3&"."&$K47&" IS '"&C47&"';" -> COMMENT ON COLUMN mars_agency_store.common_name_kana IS '通称カナ'; | R47: common_name_kana VARCHAR(432),
B48: 40 | C48: 通称漢字 | D48: VARCHAR | E48: 432 | F48: － | K48: common_name_kanji | L48: =D48&"("&E48&")," -> VARCHAR(432), | N48: ="COMMENT ON COLUMN "&$K$3&"."&$K48&" IS '"&C48&"';" -> COMMENT ON COLUMN mars_agency_store.common_name_kanji IS '通称漢字'; | R48: common_name_kanji VARCHAR(432),
B49: 41 | C49: 丁目コード | D49: VARCHAR | E49: 6 | F49: － | K49: chome_code | L49: =D49&"("&E49&")," -> VARCHAR(6), | N49: ="COMMENT ON COLUMN "&$K$3&"."&$K49&" IS '"&C49&"';" -> COMMENT ON COLUMN mars_agency_store.chome_code IS '丁目コード'; | R49: chome_code VARCHAR(6),
B50: 42 | C50: 丁目カナ | D50: VARCHAR | E50: 288 | F50: － | K50: chome_kana | L50: =D50&"("&E50&")," -> VARCHAR(288), | N50: ="COMMENT ON COLUMN "&$K$3&"."&$K50&" IS '"&C50&"';" -> COMMENT ON COLUMN mars_agency_store.chome_kana IS '丁目カナ'; | R50: chome_kana VARCHAR(288),
B51: 43 | C51: 丁目漢字 | D51: VARCHAR | E51: 288 | F51: － | K51: chome_kanji | L51: =D51&"("&E51&")," -> VARCHAR(288), | N51: ="COMMENT ON COLUMN "&$K$3&"."&$K51&" IS '"&C51&"';" -> COMMENT ON COLUMN mars_agency_store.chome_kanji IS '丁目漢字'; | R51: chome_kanji VARCHAR(288),
B52: 44 | C52: 付帯住所 | D52: VARCHAR | E52: 720 | F52: － | K52: additional_address | L52: =D52&"("&E52&")," -> VARCHAR(720), | N52: ="COMMENT ON COLUMN "&$K$3&"."&$K52&" IS '"&C52&"';" -> COMMENT ON COLUMN mars_agency_store.additional_address IS '付帯住所'; | R52: additional_address VARCHAR(720),
B53: 45 | C53: 取次店tel_no | D53: VARCHAR | E53: 30 | F53: － | K53: agent_tel_no | L53: =D53&"("&E53&")," -> VARCHAR(30), | N53: ="COMMENT ON COLUMN "&$K$3&"."&$K53&" IS '"&C53&"';" -> COMMENT ON COLUMN mars_agency_store.agent_tel_no IS '取次店tel_no'; | R53: agent_tel_no VARCHAR(30),
... B61: 53 | C61: 担当者役職 | D61: VARCHAR | E61: 360 | F61: － | K61: position_of_person_in_charge | L61: =D61&"("&E61&")," -> VARCHAR(360), | N61: ="COMMENT ON COLUMN "&$K$3&"."&$K61&" IS '"&C61&"';" -> COMMENT ON COLUMN mars_agency_store.position_of_person_in_charge IS '担当者役職'; | R61: position_of_person_in_charge VARCHAR(360),
B62: 54 | C62: 取次店小分類id | D62: DECIMAL | E62: 10,0 | F62: － | K62: agency_small_category_id | L62: =D62&"("&E62&")," -> DECIMAL(10,0), | N62: ="COMMENT ON COLUMN "&$K$3&"."&$K62&" IS '"&C62&"';" -> COMMENT ON COLUMN mars_agency_store.agency_small_category_id IS '取次店小分類id'; | R62: agency_small_category_id DECIMAL(10,0),
B63: 55 | C63: 受注先小分類コード | D63: VARCHAR | E63: 6 | F63: － | K63: order_to_order_small_category_code | L63: =D63&"("&E63&")," -> VARCHAR(6), | N63: ="COMMENT ON COLUMN "&$K$3&"."&$K63&" IS '"&C63&"';" -> COMMENT ON COLUMN mars_agency_store.order_to_order_small_category_code IS '受注先小分類コード'; | R63: order_to_order_small_category_code VARCHAR(6),
B64: 56 | C64: 受注先中分類id | D64: DECIMAL | E64: 10,0 | F64: － | K64: order_to_order_medium_category_id | L64: =D64&"("&E64&")," -> DECIMAL(10,0), | N64: ="COMMENT ON COLUMN "&$K$3&"."&$K64&" IS '"&C64&"';" -> COMMENT ON COLUMN mars_agency_store.order_to_order_medium_category_id IS '受注先中分類id'; | R64: order_to_order_medium_category_id DECIMAL(10,0),
B65: 57 | C65: 受注先小分類正式名称 | D65: VARCHAR | E65: 600 | F65: － | K65: order_to_order_small_category_full_name | L65: =D65&"("&E65&")," -> VARCHAR(600), | N65: ="COMMENT ON COLUMN "&$K$3&"."&$K65&" IS '"&C65&"';" -> COMMENT ON COLUMN mars_agency_store.order_to_order_small_category_full_name IS '受注先小分類正式名称'; | R65: order_to_order_small_category_full_name VARCHAR(600),
B66: 58 | C66: 受注先小分類半角kn | D66: VARCHAR | E66: 600 | F66: － | K66: order_to_order_small_category_half_width_kn | L66: =D66&"("&E66&")," -> VARCHAR(600), | N66: ="COMMENT ON COLUMN "&$K$3&"."&$K66&" IS '"&C66&"';" -> COMMENT ON COLUMN mars_agency_store.order_to_order_small_category_half_width_kn IS '受注先小分類半角kn'; | R66: order_to_order_small_category_half_width_kn VARCHAR(600),
B67: 59 | C67: 受注先小分類英語名称 | D67: VARCHAR | E67: 600 | F67: － | K67: order_to_order_small_category_english_name | L67: =D67&"("&E67&")," -> VARCHAR(600), | N67: ="COMMENT ON COLUMN "&$K$3&"."&$K67&" IS '"&C67&"';" -> COMMENT ON COLUMN mars_agency_store.order_to_order_small_category_english_name IS '受注先小分類英語名称'; | R67: order_to_order_small_category_english_name VARCHAR(600),
B68: 60 | C68: 受注先中分類コード | D68: VARCHAR | E68: 4 | F68: － | K68: order_to_order_medium_category_code | L68: =D68&"("&E68&")," -> VARCHAR(4), | N68: ="COMMENT ON COLUMN "&$K$3&"."&$K68&" IS '"&C68&"';" -> COMMENT ON COLUMN mars_agency_store.order_to_order_medium_category_code IS '受注先中分類コード'; | R68: order_to_order_medium_category_code VARCHAR(4),
B69: 61 | C69: 受注先大分類id | D69: DECIMAL | E69: 10,0 | F69: － | K69: order_to_order_large_category_id | L69: =D69&"("&E69&")," -> DECIMAL(10,0), | N69: ="COMMENT ON COLUMN "&$K$3&"."&$K69&" IS '"&C69&"';" -> COMMENT ON COLUMN mars_agency_store.order_to_order_large_category_id IS '受注先大分類id'; | R69: order_to_order_large_category_id DECIMAL(10,0),
B70: 62 | C70: 受注先中分類正式名称 | D70: VARCHAR | E70: 600 | F70: － | K70: order_to_order_medium_category_full_name | L70: =D70&"("&E70&")," -> VARCHAR(600), | N70: ="COMMENT ON COLUMN "&$K$3&"."&$K70&" IS '"&C70&"';" -> COMMENT ON COLUMN mars_agency_store.order_to_order_medium_category_full_name IS '受注先中分類正式名称'; | R70: order_to_order_medium_category_full_name VARCHAR(600),
B71: 63 | C71: 受注先中分類半角kn | D71: VARCHAR | E71: 600 | F71: － | K71: order_to_order_medium_category_half_width_kn | L71: =D71&"("&E71&")," -> VARCHAR(600), | N71: ="COMMENT ON COLUMN "&$K$3&"."&$K71&" IS '"&C71&"';" -> COMMENT ON COLUMN mars_agency_store.order_to_order_medium_category_half_width_kn IS '受注先中分類半角kn'; | R71: order_to_order_medium_category_half_width_kn VARCHAR(600),
B72: 64 | C72: 受注先中分類英語名称 | D72: VARCHAR | E72: 600 | F72: － | K72: order_to_order_medium_category_english_name | L72: =D72&"("&E72&")," -> VARCHAR(600), | N72: ="COMMENT ON COLUMN "&$K$3&"."&$K72&" IS '"&C72&"';" -> COMMENT ON COLUMN mars_agency_store.order_to_order_medium_category_english_name IS '受注先中分類英語名称'; | R72: order_to_order_medium_category_english_name VARCHAR(600),
B73: 65 | C73: 受注先大分類コード | D73: VARCHAR | E73: 4 | F73: － | K73: order_to_order_large_category_code | L73: =D73&"("&E73&")," -> VARCHAR(4), | N73: ="COMMENT ON COLUMN "&$K$3&"."&$K73&" IS '"&C73&"';" -> COMMENT ON COLUMN mars_agency_store.order_to_order_large_category_code IS '受注先大分類コード'; | R73: order_to_order_large_category_code VARCHAR(4),
B74: 66 | C74: 受注先大分類正式名称 | D74: VARCHAR | E74: 600 | F74: － | K74: order_to_order_large_category_full_name | L74: =D74&"("&E74&")," -> VARCHAR(600), | N74: ="COMMENT ON COLUMN "&$K$3&"."&$K74&" IS '"&C74&"';" -> COMMENT ON COLUMN mars_agency_store.order_to_order_large_category_full_name IS '受注先大分類正式名称'; | R74: order_to_order_large_category_full_name VARCHAR(600),
B75: 67 | C75: 受注先大分類半角kn | D75: VARCHAR | E75: 600 | F75: － | K75: order_to_order_large_category_half_width_kn | L75: =D75&"("&E75&")," -> VARCHAR(600), | N75: ="COMMENT ON COLUMN "&$K$3&"."&$K75&" IS '"&C75&"';" -> COMMENT ON COLUMN mars_agency_store.order_to_order_large_category_half_width_kn IS '受注先大分類半角kn'; | R75: order_to_order_large_category_half_width_kn VARCHAR(600),
B76: 68 | C76: 受注先大分類英語名称 | D76: VARCHAR | E76: 600 | F76: － | K76: order_to_order_large_category_english_name | L76: =D76&"("&E76&")," -> VARCHAR(600), | N76: ="COMMENT ON COLUMN "&$K$3&"."&$K76&" IS '"&C76&"';" -> COMMENT ON COLUMN mars_agency_store.order_to_order_large_category_english_name IS '受注先大分類英語名称'; | R76: order_to_order_large_category_english_name VARCHAR(600),
B77: 69 | C77: wms同梱伝票様式 | D77: VARCHAR | E77: 6 | F77: － | K77: wms_packing_slip_format | L77: =D77&"("&E77&")," -> VARCHAR(6), | N77: ="COMMENT ON COLUMN "&$K$3&"."&$K77&" IS '"&C77&"';" -> COMMENT ON COLUMN mars_agency_store.wms_packing_slip_format IS 'wms同梱伝票様式'; | R77: wms_packing_slip_format VARCHAR(6),
B78: 70 | C78: wms同梱伝票様式nm | D78: VARCHAR | E78: 1200 | F78: － | K78: wms_packing_slip_format_nm | L78: =D78&"("&E78&")," -> VARCHAR(1200), | N78: ="COMMENT ON COLUMN "&$K$3&"."&$K78&" IS '"&C78&"';" -> COMMENT ON COLUMN mars_agency_store.wms_packing_slip_format_nm IS 'wms同梱伝票様式nm'; | R78: wms_packing_slip_format_nm VARCHAR(1200),
B79: 71 | C79: wms本伝伝票様式 | D79: VARCHAR | E79: 6 | F79: － | K79: wms_main_slip_format | L79: =D79&"("&E79&")," -> VARCHAR(6), | N79: ="COMMENT ON COLUMN "&$K$3&"."&$K79&" IS '"&C79&"';" -> COMMENT ON COLUMN mars_agency_store.wms_main_slip_format IS 'wms本伝伝票様式'; | R79: wms_main_slip_format VARCHAR(6),
B80: 72 | C80: wms本伝伝票様式nm | D80: VARCHAR | E80: 1200 | F80: － | K80: wms_main_invoice_format_nm | L80: =D80&"("&E80&")," -> VARCHAR(1200), | N80: ="COMMENT ON COLUMN "&$K$3&"."&$K80&" IS '"&C80&"';" -> COMMENT ON COLUMN mars_agency_store.wms_main_invoice_format_nm IS 'wms本伝伝票様式nm'; | R80: wms_main_invoice_format_nm VARCHAR(1200),
B81: 73 | C81: wms本伝金額印字flg | D81: VARCHAR | E81: 2 | F81: － | K81: wms_main_invoice_amount_printing_flg | L81: =D81&"("&E81&")," -> VARCHAR(2), | N81: ="COMMENT ON COLUMN "&$K$3&"."&$K81&" IS '"&C81&"';" -> COMMENT ON COLUMN mars_agency_store.wms_main_invoice_amount_printing_flg IS 'wms本伝金額印字flg'; | R81: wms_main_invoice_amount_printing_flg VARCHAR(2),
... B86: 78 | C86: 相手先sys用自社cd | D86: VARCHAR | E86: 20 | F86: － | K86: company_cd_for_recipient_sys | L86: =D86&"("&E86&")," -> VARCHAR(20), | N86: ="COMMENT ON COLUMN "&$K$3&"."&$K86&" IS '"&C86&"';" -> COMMENT ON COLUMN mars_agency_store.company_cd_for_recipient_sys IS '相手先sys用自社cd'; | R86: company_cd_for_recipient_sys VARCHAR(20),
B87: 79 | C87: 卸チャネル | D87: DECIMAL | E87: 10,0 | F87: － | K87: wholesale_channel | L87: =D87&"("&E87&")," -> DECIMAL(10,0), | N87: ="COMMENT ON COLUMN "&$K$3&"."&$K87&" IS '"&C87&"';" -> COMMENT ON COLUMN mars_agency_store.wholesale_channel IS '卸チャネル'; | R87: wholesale_channel DECIMAL(10,0),
B88: 80 | C88: 法人チャネル | D88: DECIMAL | E88: 10,0 | F88: － | K88: corporate_channel | L88: =D88&"("&E88&")," -> DECIMAL(10,0), | N88: ="COMMENT ON COLUMN "&$K$3&"."&$K88&" IS '"&C88&"';" -> COMMENT ON COLUMN mars_agency_store.corporate_channel IS '法人チャネル'; | R88: corporate_channel DECIMAL(10,0),
B89: 81 | C89: 直営店判定flg | D89: DECIMAL | E89: 10,0 | F89: － | K89: direct_store_determination_flg | L89: =D89&"("&E89&")," -> DECIMAL(10,0), | N89: ="COMMENT ON COLUMN "&$K$3&"."&$K89&" IS '"&C89&"';" -> COMMENT ON COLUMN mars_agency_store.direct_store_determination_flg IS '直営店判定flg'; | R89: direct_store_determination_flg DECIMAL(10,0),
B90: 82 | C90: 直営店判定flg_nm | D90: VARCHAR | E90: 1200 | F90: － | K90: direct_store_determination_flg_nm | L90: =D90&"("&E90&")," -> VARCHAR(1200), | N90: ="COMMENT ON COLUMN "&$K$3&"."&$K90&" IS '"&C90&"';" -> COMMENT ON COLUMN mars_agency_store.direct_store_determination_flg_nm IS '直営店判定flg_nm'; | R90: direct_store_determination_flg_nm VARCHAR(1200),
B91: 83 | C91: 店舗ユニークコード | D91: VARCHAR | E91: 14 | F91: － | K91: store_unique_code | L91: =D91&"("&E91&")," -> VARCHAR(14), | N91: ="COMMENT ON COLUMN "&$K$3&"."&$K91&" IS '"&C91&"';" -> COMMENT ON COLUMN mars_agency_store.store_unique_code IS '店舗ユニークコード'; | R91: store_unique_code VARCHAR(14),
B92: 84 | C92: 運営店法人コード | D92: VARCHAR | E92: 14 | F92: － | K92: operating_store_corporate_code | L92: =D92&"("&E92&")," -> VARCHAR(14), | N92: ="COMMENT ON COLUMN "&$K$3&"."&$K92&" IS '"&C92&"';" -> COMMENT ON COLUMN mars_agency_store.operating_store_corporate_code IS '運営店法人コード'; | R92: operating_store_corporate_code VARCHAR(14),
B93: 85 | C93: 業務開始日 | D93: VARCHAR | E93: 16 | F93: － | K93: business_start_date | L93: =D93&"("&E93&")," -> VARCHAR(16), | N93: ="COMMENT ON COLUMN "&$K$3&"."&$K93&" IS '"&C93&"';" -> COMMENT ON COLUMN mars_agency_store.business_start_date IS '業務開始日'; | R93: business_start_date VARCHAR(16),
B94: 86 | C94: 業務終了日 | D94: VARCHAR | E94: 16 | F94: － | K94: business_end_date | L94: =D94&"("&E94&")," -> VARCHAR(16), | N94: ="COMMENT ON COLUMN "&$K$3&"."&$K94&" IS '"&C94&"';" -> COMMENT ON COLUMN mars_agency_store.business_end_date IS '業務終了日'; | R94: business_end_date VARCHAR(16),
B95: 87 | C95: 登録業務部門コード | D95: VARCHAR | E95: 14 | F95: － | K95: registered_business_department_code | L95: =D95&"("&E95&")," -> VARCHAR(14), | N95: ="COMMENT ON COLUMN "&$K$3&"."&$K95&" IS '"&C95&"';" -> COMMENT ON COLUMN mars_agency_store.registered_business_department_code IS '登録業務部門コード'; | R95: registered_business_department_code VARCHAR(14),
B96: 88 | C96: 組織id右1桁 | D96: VARCHAR | E96: 2 | F96: － | K96: organization_id__right_1_digit_ | L96: =D96&"("&E96&")," -> VARCHAR(2), | N96: ="COMMENT ON COLUMN "&$K$3&"."&$K96&" IS '"&C96&"';" -> COMMENT ON COLUMN mars_agency_store.organization_id__right_1_digit_ IS '組織id右1桁'; | R96: organization_id__right_1_digit_ VARCHAR(2),
B97: 89 | C97: 組織名称 | D97: VARCHAR | E97: 2400 | F97: － | K97: organization_name | L97: =D97&"("&E97&")," -> VARCHAR(2400), | N97: ="COMMENT ON COLUMN "&$K$3&"."&$K97&" IS '"&C97&"';" -> COMMENT ON COLUMN mars_agency_store.organization_name IS '組織名称'; | R97: organization_name VARCHAR(2400),
B98: 90 | C98: 階層 | D98: VARCHAR | E98: 4 | F98: － | K98: hierarchy | L98: =D98&"("&E98&")," -> VARCHAR(4), | N98: ="COMMENT ON COLUMN "&$K$3&"."&$K98&" IS '"&C98&"';" -> COMMENT ON COLUMN mars_agency_store.hierarchy IS '階層'; | R98: hierarchy VARCHAR(4),
B99: 91 | C99: 上位組織コード | D99: VARCHAR | E99: 14 | F99: － | K99: supervisor_organization_code | L99: =D99&"("&E99&")," -> VARCHAR(14), | N99: ="COMMENT ON COLUMN "&$K$3&"."&$K99&" IS '"&C99&"';" -> COMMENT ON COLUMN mars_agency_store.supervisor_organization_code IS '上位組織コード'; | R99: supervisor_organization_code VARCHAR(14),
B100: 92 | C100: 上位組織コード右1桁 | D100: VARCHAR | E100: 2 | F100: － | K100: supervisor_organization_code__right_1_digit_ | L100: =D100&"("&E100&")," -> VARCHAR(2), | N100: ="COMMENT ON COLUMN "&$K$3&"."&$K100&" IS '"&C100&"';" -> COMMENT ON COLUMN mars_agency_store.supervisor_organization_code__right_1_digit_ IS '上位組織コード右1桁'; | R100: supervisor_organization_code__right_1_digit_ VARCHAR(2),
B101: 93 | C101: 管理者従業員番号 | D101: VARCHAR | E101: 14 | F101: － | K101: manager_employee_number | L101: =D101&"("&E101&")," -> VARCHAR(14), | N101: ="COMMENT ON COLUMN "&$K$3&"."&$K101&" IS '"&C101&"';" -> COMMENT ON COLUMN mars_agency_store.manager_employee_number IS '管理者従業員番号'; | R101: manager_employee_number VARCHAR(14),
... B114: 106 | C114: 操作権限正式名称 | D114: VARCHAR | E114: 1200 | F114: － | K114: operation_permission_official_name | L114: =D114&"("&E114&")," -> VARCHAR(1200), | N114: ="COMMENT ON COLUMN "&$K$3&"."&$K114&" IS '"&C114&"';" -> COMMENT ON COLUMN mars_agency_store.operation_permission_official_name IS '操作権限正式名称'; | R114: operation_permission_official_name VARCHAR(1200),
B115: 107 | C115: 手数料計算区分 | D115: DECIMAL | E115: 10,0 | F115: － | K115: commission_calculation_category | L115: =D115&"("&E115&")," -> DECIMAL(10,0), | N115: ="COMMENT ON COLUMN "&$K$3&"."&$K115&" IS '"&C115&"';" -> COMMENT ON COLUMN mars_agency_store.commission_calculation_category IS '手数料計算区分'; | R115: commission_calculation_category DECIMAL(10,0),
B116: 108 | C116: 手数料計算区分nm | D116: VARCHAR | E116: 1200 | F116: － | K116: commission_calculation_category_nm | L116: =D116&"("&E116&")," -> VARCHAR(1200), | N116: ="COMMENT ON COLUMN "&$K$3&"."&$K116&" IS '"&C116&"';" -> COMMENT ON COLUMN mars_agency_store.commission_calculation_category_nm IS '手数料計算区分nm'; | R116: commission_calculation_category_nm VARCHAR(1200),
B117: 109 | C117: 手数料計算終了日 | D117: VARCHAR | E117: 16 | F117: － | K117: commission_calculation_end_date | L117: =D117&"("&E117&")," -> VARCHAR(16), | N117: ="COMMENT ON COLUMN "&$K$3&"."&$K117&" IS '"&C117&"';" -> COMMENT ON COLUMN mars_agency_store.commission_calculation_end_date IS '手数料計算終了日'; | R117: commission_calculation_end_date VARCHAR(16),
B118: 110 | C118: 法人取扱店タイプ | D118: VARCHAR | E118: 4 | F118: － | K118: corporate_dealer_type | L118: =D118&"("&E118&")," -> VARCHAR(4), | N118: ="COMMENT ON COLUMN "&$K$3&"."&$K118&" IS '"&C118&"';" -> COMMENT ON COLUMN mars_agency_store.corporate_dealer_type IS '法人取扱店タイプ'; | R118: corporate_dealer_type VARCHAR(4),
B119: 111 | C119: 法人取扱店タイプnm | D119: VARCHAR | E119: 1200 | F119: － | K119: corporate_dealer_type_nm | L119: =D119&"("&E119&")," -> VARCHAR(1200), | N119: ="COMMENT ON COLUMN "&$K$3&"."&$K119&" IS '"&C119&"';" -> COMMENT ON COLUMN mars_agency_store.corporate_dealer_type_nm IS '法人取扱店タイプnm'; | R119: corporate_dealer_type_nm VARCHAR(1200),
B120: 112 | C120: 業務手数料支払ptn | D120: VARCHAR | E120: 4 | F120: － | K120: service_fee_payment_ptn | L120: =D120&"("&E120&")," -> VARCHAR(4), | N120: ="COMMENT ON COLUMN "&$K$3&"."&$K120&" IS '"&C120&"';" -> COMMENT ON COLUMN mars_agency_store.service_fee_payment_ptn IS '業務手数料支払ptn'; | R120: service_fee_payment_ptn VARCHAR(4),
B121: 113 | C121: 業務手数料支払ptn_nm | D121: VARCHAR | E121: 1200 | F121: － | K121: service_fee_payment_ptn_nm | L121: =D121&"("&E121&")," -> VARCHAR(1200), | N121: ="COMMENT ON COLUMN "&$K$3&"."&$K121&" IS '"&C121&"';" -> COMMENT ON COLUMN mars_agency_store.service_fee_payment_ptn_nm IS '業務手数料支払ptn_nm'; | R121: service_fee_payment_ptn_nm VARCHAR(1200),
B122: 114 | C122: 保守代理店区分 | D122: DECIMAL | E122: 10,0 | F122: － | K122: maintenance_agency_category | L122: =D122&"("&E122&")," -> DECIMAL(10,0), | N122: ="COMMENT ON COLUMN "&$K$3&"."&$K122&" IS '"&C122&"';" -> COMMENT ON COLUMN mars_agency_store.maintenance_agency_category IS '保守代理店区分'; | R122: maintenance_agency_category DECIMAL(10,0),
B123: 115 | C123: 保守代理店区分nm | D123: VARCHAR | E123: 1200 | F123: － | K123: maintenance_agency_category_nm | L123: =D123&"("&E123&")," -> VARCHAR(1200), | N123: ="COMMENT ON COLUMN "&$K$3&"."&$K123&" IS '"&C123&"';" -> COMMENT ON COLUMN mars_agency_store.maintenance_agency_category_nm IS '保守代理店区分nm'; | R123: maintenance_agency_category_nm VARCHAR(1200),
B124: 116 | C124: 継続手数料対象外kbn | D124: DECIMAL | E124: 10,0 | F124: － | K124: not_eligible_for_recurring_fee_kbn | L124: =D124&"("&E124&")," -> DECIMAL(10,0), | N124: ="COMMENT ON COLUMN "&$K$3&"."&$K124&" IS '"&C124&"';" -> COMMENT ON COLUMN mars_agency_store.not_eligible_for_recurring_fee_kbn IS '継続手数料対象外kbn'; | R124: not_eligible_for_recurring_fee_kbn DECIMAL(10,0),
B125: 117 | C125: 継続手数料対象外kbn_nm | D125: VARCHAR | E125: 1200 | F125: － | K125: not_eligible_for_recurring_fee_kbn_nm | L125: =D125&"("&E125&")," -> VARCHAR(1200), | N125: ="COMMENT ON COLUMN "&$K$3&"."&$K125&" IS '"&C125&"';" -> COMMENT ON COLUMN mars_agency_store.not_eligible_for_recurring_fee_kbn_nm IS '継続手数料対象外kbn_nm'; | R125: not_eligible_for_recurring_fee_kbn_nm VARCHAR(1200),
B126: 118 | C126: ショップ業務委託dt | D126: VARCHAR | E126: 16 | F126: － | K126: shop_outsourcing_dt | L126: =D126&"("&E126&")," -> VARCHAR(16), | N126: ="COMMENT ON COLUMN "&$K$3&"."&$K126&" IS '"&C126&"';" -> COMMENT ON COLUMN mars_agency_store.shop_outsourcing_dt IS 'ショップ業務委託dt'; | R126: shop_outsourcing_dt VARCHAR(16),
...

Sheet (Mars)キャンペーン
F2: 種別 | G2: DWH公開名 | H2: 旧DWH公開名 | I2: 統合テーブルID | J2: スキーマ
F3: ビュー | G3: m_キャンペーン | H3: M_キャンペーン_[権限] | I3: V001730 | J3: user_l2 | K3: mars_campaign
F4: データ概要：
F5: キャンペーンの情報を保有。
K6: ="DROP TABLE IF EXISTS "&K3&" CASCADE;" -> DROP TABLE IF EXISTS mars_campaign CASCADE; | R6: DROP TABLE IF EXISTS mars_campaign CASCADE;
K7: ="CREATE TABLE IF NOT EXISTS "&K3&" (" -> CREATE TABLE IF NOT EXISTS mars_campaign ( | N7: ="COMMENT ON TABLE "&K3&" IS '"&G3&"';" -> COMMENT ON TABLE mars_campaign IS 'm_キャンペーン'; | R7: CREATE TABLE IF NOT EXISTS mars_campaign (
A8: pk | B8: SEQ | C8: 項目名 | D8: TYPE | E8: 桁 | F8: 仮名化 | G8: 項目説明およびリスト値 | H8: コードリファレンスリンク | I8: 備考 | J8: 更新日 | K8: id BIGINT GENERATED BY DEFAULT AS IDENTITY, | N8: ="COMMENT ON COLUMN "&$K$3&".id IS 'id';" -> COMMENT ON COLUMN mars_campaign.id IS 'id'; | R8: id BIGINT GENERATED BY DEFAULT AS IDENTITY,
A9: ○ | B9: 1 | C9: キャンペーンid | D9: VARCHAR | E9: 40 | F9: － | G9: キャンペーンを一意に特定するID | K9: campaign_id | L9: =D9&"("&E9&")," -> VARCHAR(40), | N9: ="COMMENT ON COLUMN "&$K$3&"."&$K9&" IS '"&C9&"';" -> COMMENT ON COLUMN mars_campaign.campaign_id IS 'キャンペーンid'; | R9: campaign_id VARCHAR(40),
B10: 2 | C10: キャンペーン名称 | D10: VARCHAR | E10: 2400 | F10: － | G10: 半角は許容しない | K10: campaign_name | L10: =D10&"("&E10&")," -> VARCHAR(2400), | N10: ="COMMENT ON COLUMN "&$K$3&"."&$K10&" IS '"&C10&"';" -> COMMENT ON COLUMN mars_campaign.campaign_name IS 'キャンペーン名称'; | R10: campaign_name VARCHAR(2400),
B11: 3 | C11: 説明 | D11: VARCHAR | E11: 1200 | F11: － | G11: 半角は許容しない | K11: description | L11: =D11&"("&E11&")," -> VARCHAR(1200), | N11: ="COMMENT ON COLUMN "&$K$3&"."&$K11&" IS '"&C11&"';" -> COMMENT ON COLUMN mars_campaign.description IS '説明'; | R11: description VARCHAR(1200),
B12: 4 | C12: 有効開始日 | D12: VARCHAR | E12: 16 | F12: － | G12: レコードの有効開始日（履歴管理用日時） | K12: effective_start_date | L12: =D12&"("&E12&")," -> VARCHAR(16), | N12: ="COMMENT ON COLUMN "&$K$3&"."&$K12&" IS '"&C12&"';" -> COMMENT ON COLUMN mars_campaign.effective_start_date IS '有効開始日'; | R12: effective_start_date VARCHAR(16),
B13: 5 | C13: 有効終了日 | D13: VARCHAR | E13: 16 | F13: － | G13: レコードの有効終了日（履歴管理用日時） | K13: effective_end_date | L13: =D13&"("&E13&")," -> VARCHAR(16), | N13: ="COMMENT ON COLUMN "&$K$3&"."&$K13&" IS '"&C13&"';" -> COMMENT ON COLUMN mars_campaign.effective_end_date IS '有効終了日'; | R13: effective_end_date VARCHAR(16),
B14: 6 | C14: 旧フラグ | D14: VARCHAR | E14: 2 | F14: － | G14: 新データモデル：null | K14: old_flag | L14: =D14&"("&E14&")," -> VARCHAR(2), | N14: ="COMMENT ON COLUMN "&$K$3&"."&$K14&" IS '"&C14&"';" -> COMMENT ON COLUMN mars_campaign.old_flag IS '旧フラグ'; | R14: old_flag VARCHAR(2),
G15: 旧データモデル：1 | L15: =D15&"("&E15&")," -> (), | R15: CONSTRAINT pk_mars_campaign PRIMARY KEY (id));
L16: =D16&"("&E16&")," -> (), | R16: COMMENT ON TABLE mars_campaign IS 'm_キャンペーン';
G17: 新旧データモデルの区分け方は、CAERUS PJのS-in前のデータモデルを旧、S-in後のデータモデルを新とする | L17: =D17&"("&E17&")," -> (), | R17: COMMENT ON COLUMN mars_campaign.id IS 'id';
K18: ="CONSTRAINT pk_"&K3&" PRIMARY KEY (id));" -> CONSTRAINT pk_mars_campaign PRIMARY KEY (id)); | R18: COMMENT ON COLUMN mars_campaign.campaign_id IS 'キャンペーンid';
R19: COMMENT ON COLUMN mars_campaign.campaign_name IS 'キャンペーン名称';
R20: COMMENT ON COLUMN mars_campaign.description IS '説明';
R21: COMMENT ON COLUMN mars_campaign.effective_start_date IS '有効開始日';
R22: COMMENT ON COLUMN mars_campaign.effective_end_date IS '有効終了日';
R23: COMMENT ON COLUMN mars_campaign.old_flag IS '旧フラグ';

Sheet (Mars)商品
F2: 種別 | G2: DWH公開名 | H2: 旧DWH公開名 | I2: 統合テーブルID | J2: スキーマ
F3: ビュー | G3: m_商品 | I3: V001780 | J3: user_l2 | K3: mars_product
F4: データ概要：
F5: データ概要： 商品コード単位で商品に関する情報を保有。 M_商品 ：M_商品_ALLから最新フラグが「1」のデータのみ抽出
K6: ="DROP TABLE IF EXISTS "&K3&" CASCADE;" -> DROP TABLE IF EXISTS mars_product CASCADE; | R6: DROP TABLE IF EXISTS mars_product CASCADE;
K7: ="CREATE TABLE IF NOT EXISTS "&K3&" (" -> CREATE TABLE IF NOT EXISTS mars_product ( | N7: ="COMMENT ON TABLE "&K3&" IS '"&G3&"';" -> COMMENT ON TABLE mars_product IS 'm_商品'; | R7: CREATE TABLE IF NOT EXISTS mars_product (
A8: pk | B8: SEQ | C8: 項目名 | D8: TYPE | E8: 桁 | F8: 仮名化 | G8: 項目説明およびリスト値 | H8: コードリファレンスリンク | I8: 備考 | J8: 更新日 | K8: id BIGINT GENERATED BY DEFAULT AS IDENTITY, | N8: ="COMMENT ON COLUMN "&$K$3&".id IS 'id';" -> COMMENT ON COLUMN mars_product.id IS 'id'; | R8: id BIGINT GENERATED BY DEFAULT AS IDENTITY,
B9: 1 | C9: 商品コード | D9: VARCHAR | E9: 40 | F9: － | K9: product_code | L9: =D9&"("&E9&")," -> VARCHAR(40), | N9: ="COMMENT ON COLUMN "&$K$3&"."&$K9&" IS '"&C9&"';" -> COMMENT ON COLUMN mars_product.product_code IS '商品コード'; | R9: product_code VARCHAR(40),
B10: 2 | C10: 有効開始日 | D10: VARCHAR | E10: 16 | F10: － | K10: validity_start_date | L10: =D10&"("&E10&")," -> VARCHAR(16), | N10: ="COMMENT ON COLUMN "&$K$3&"."&$K10&" IS '"&C10&"';" -> COMMENT ON COLUMN mars_product.validity_start_date IS '有効開始日'; | R10: validity_start_date VARCHAR(16),
B11: 3 | C11: 有効開始時間 | D11: VARCHAR | E11: 12 | F11: － | K11: validity_start_time | L11: =D11&"("&E11&")," -> VARCHAR(12), | N11: ="COMMENT ON COLUMN "&$K$3&"."&$K11&" IS '"&C11&"';" -> COMMENT ON COLUMN mars_product.validity_start_time IS '有効開始時間'; | R11: validity_start_time VARCHAR(12),
B12: 4 | C12: 有効終了日 | D12: VARCHAR | E12: 16 | F12: － | K12: validity_end_date | L12: =D12&"("&E12&")," -> VARCHAR(16), | N12: ="COMMENT ON COLUMN "&$K$3&"."&$K12&" IS '"&C12&"';" -> COMMENT ON COLUMN mars_product.validity_end_date IS '有効終了日'; | R12: validity_end_date VARCHAR(16),
B13: 5 | C13: 有効終了時間 | D13: VARCHAR | E13: 12 | F13: － | K13: validity_end_time | L13: =D13&"("&E13&")," -> VARCHAR(12), | N13: ="COMMENT ON COLUMN "&$K$3&"."&$K13&" IS '"&C13&"';" -> COMMENT ON COLUMN mars_product.validity_end_time IS '有効終了時間'; | R13: validity_end_time VARCHAR(12),
B14: 6 | C14: 地域コード | D14: VARCHAR | E14: 6 | F14: － | K14: area_code | L14: =D14&"("&E14&")," -> VARCHAR(6), | N14: ="COMMENT ON COLUMN "&$K$3&"."&$K14&" IS '"&C14&"';" -> COMMENT ON COLUMN mars_product.area_code IS '地域コード'; | R14: area_code VARCHAR(6),
B15: 7 | C15: 商品正式名称 | D15: VARCHAR | E15: 1200 | F15: － | K15: product_official_name | L15: =D15&"("&E15&")," -> VARCHAR(1200), | N15: ="COMMENT ON COLUMN "&$K$3&"."&$K15&" IS '"&C15&"';" -> COMMENT ON COLUMN mars_product.product_official_name IS '商品正式名称'; | R15: product_official_name VARCHAR(1200),
B16: 8 | C16: 商品カナ名称 | D16: VARCHAR | E16: 1200 | F16: － | K16: product_name_in_kana | L16: =D16&"("&E16&")," -> VARCHAR(1200), | N16: ="COMMENT ON COLUMN "&$K$3&"."&$K16&" IS '"&C16&"';" -> COMMENT ON COLUMN mars_product.product_name_in_kana IS '商品カナ名称'; | R16: product_name_in_kana VARCHAR(1200),
B17: 9 | C17: 商品英語名称 | D17: VARCHAR | E17: 1200 | F17: － | K17: product_name_in_english | L17: =D17&"("&E17&")," -> VARCHAR(1200), | N17: ="COMMENT ON COLUMN "&$K$3&"."&$K17&" IS '"&C17&"';" -> COMMENT ON COLUMN mars_product.product_name_in_english IS '商品英語名称'; | R17: product_name_in_english VARCHAR(1200),
B18: 10 | C18: 商品略称 | D18: VARCHAR | E18: 600 | F18: － | K18: product_abbreviation | L18: =D18&"("&E18&")," -> VARCHAR(600), | N18: ="COMMENT ON COLUMN "&$K$3&"."&$K18&" IS '"&C18&"';" -> COMMENT ON COLUMN mars_product.product_abbreviation IS '商品略称'; | R18: product_abbreviation VARCHAR(600),
B19: 11 | C19: 商品細分類id | D19: VARCHAR | E19: 20 | F19: － | K19: product_subcategory_id | L19: =D19&"("&E19&")," -> VARCHAR(20), | N19: ="COMMENT ON COLUMN "&$K$3&"."&$K19&" IS '"&C19&"';" -> COMMENT ON COLUMN mars_product.product_subcategory_id IS '商品細分類id'; | R19: product_subcategory_id VARCHAR(20),
B20: 12 | C20: 商品細分類正式名称 | D20: VARCHAR | E20: 1200 | F20: － | K20: product_subcategory_official_name | L20: =D20&"("&E20&")," -> VARCHAR(1200), | N20: ="COMMENT ON COLUMN "&$K$3&"."&$K20&" IS '"&C20&"';" -> COMMENT ON COLUMN mars_product.product_subcategory_official_name IS '商品細分類正式名称'; | R20: product_subcategory_official_name VARCHAR(1200),
... B48: 40 | C48: 商品色略称 | D48: VARCHAR | E48: 240 | F48: － | K48: product_color_abbreviation | L48: =D48&"("&E48&")," -> VARCHAR(240), | N48: ="COMMENT ON COLUMN "&$K$3&"."&$K48&" IS '"&C48&"';" -> COMMENT ON COLUMN mars_product.product_color_abbreviation IS '商品色略称'; | R48: product_color_abbreviation VARCHAR(240),
B49: 41 | C49: 標準色id | D49: DECIMAL | E49: 10,0 | F49: － | K49: standard_color_id | L49: =D49&"("&E49&")," -> DECIMAL(10,0), | N49: ="COMMENT ON COLUMN "&$K$3&"."&$K49&" IS '"&C49&"';" -> COMMENT ON COLUMN mars_product.standard_color_id IS '標準色id'; | R49: standard_color_id DECIMAL(10,0),
B50: 42 | C50: 標準色正式名称 | D50: VARCHAR | E50: 1200 | F50: － | K50: standard_color_official_name | L50: =D50&"("&E50&")," -> VARCHAR(1200), | N50: ="COMMENT ON COLUMN "&$K$3&"."&$K50&" IS '"&C50&"';" -> COMMENT ON COLUMN mars_product.standard_color_official_name IS '標準色正式名称'; | R50: standard_color_official_name VARCHAR(1200),
B51: 43 | C51: 標準色カナ名称 | D51: VARCHAR | E51: 1200 | F51: － | K51: standard_color_name_in_kana | L51: =D51&"("&E51&")," -> VARCHAR(1200), | N51: ="COMMENT ON COLUMN "&$K$3&"."&$K51&" IS '"&C51&"';" -> COMMENT ON COLUMN mars_product.standard_color_name_in_kana IS '標準色カナ名称'; | R51: standard_color_name_in_kana VARCHAR(1200),
B52: 44 | C52: 標準色英語名称 | D52: VARCHAR | E52: 1200 | F52: － | K52: standard_color_name_in_english | L52: =D52&"("&E52&")," -> VARCHAR(1200), | N52: ="COMMENT ON COLUMN "&$K$3&"."&$K52&" IS '"&C52&"';" -> COMMENT ON COLUMN mars_product.standard_color_name_in_english IS '標準色英語名称'; | R52: standard_color_name_in_english VARCHAR(1200),
B53: 45 | C53: 機種コード | D53: VARCHAR | E53: 40 | F53: － | K53: model_code | L53: =D53&"("&E53&")," -> VARCHAR(40), | N53: ="COMMENT ON COLUMN "&$K$3&"."&$K53&" IS '"&C53&"';" -> COMMENT ON COLUMN mars_product.model_code IS '機種コード'; | R53: model_code VARCHAR(40),
B54: 46 | C54: 機種正式名称 | D54: VARCHAR | E54: 1200 | F54: － | K54: model_official_name | L54: =D54&"("&E54&")," -> VARCHAR(1200), | N54: ="COMMENT ON COLUMN "&$K$3&"."&$K54&" IS '"&C54&"';" -> COMMENT ON COLUMN mars_product.model_official_name IS '機種正式名称'; | R54: model_official_name VARCHAR(1200),
B55: 47 | C55: 手数料支払停止日 | D55: VARCHAR | E55: 16 | F55: － | K55: fee_payment_stop_date | L55: =D55&"("&E55&")," -> VARCHAR(16), | N55: ="COMMENT ON COLUMN "&$K$3&"."&$K55&" IS '"&C55&"';" -> COMMENT ON COLUMN mars_product.fee_payment_stop_date IS '手数料支払停止日'; | R55: fee_payment_stop_date VARCHAR(16),
B56: 48 | C56: mvno識別id | D56: DECIMAL | E56: 10,0 | F56: － | K56: mvno_identification_id | L56: =D56&"("&E56&")," -> DECIMAL(10,0), | N56: ="COMMENT ON COLUMN "&$K$3&"."&$K56&" IS '"&C56&"';" -> COMMENT ON COLUMN mars_product.mvno_identification_id IS 'mvno識別id'; | R56: mvno_identification_id DECIMAL(10,0),
B57: 49 | C57: mvno識別略称2 | D57: VARCHAR | E57: 120 | F57: － | K57: mvno_identification_abbreviation_2 | L57: =D57&"("&E57&")," -> VARCHAR(120), | N57: ="COMMENT ON COLUMN "&$K$3&"."&$K57&" IS '"&C57&"';" -> COMMENT ON COLUMN mars_product.mvno_identification_abbreviation_2 IS 'mvno識別略称2'; | R57: mvno_identification_abbreviation_2 VARCHAR(120),
B58: 50 | C58: 販売開始日 | D58: VARCHAR | E58: 16 | F58: － | K58: sales_start_date | L58: =D58&"("&E58&")," -> VARCHAR(16), | N58: ="COMMENT ON COLUMN "&$K$3&"."&$K58&" IS '"&C58&"';" -> COMMENT ON COLUMN mars_product.sales_start_date IS '販売開始日'; | R58: sales_start_date VARCHAR(16),
B59: 51 | C59: 販売終了日 | D59: VARCHAR | E59: 16 | F59: － | K59: sales_end_date | L59: =D59&"("&E59&")," -> VARCHAR(16), | N59: ="COMMENT ON COLUMN "&$K$3&"."&$K59&" IS '"&C59&"';" -> COMMENT ON COLUMN mars_product.sales_end_date IS '販売終了日'; | R59: sales_end_date VARCHAR(16),
B60: 52 | C60: 買い増し有効開始日 | D60: VARCHAR | E60: 16 | F60: － | K60: additional_purchase_validity_start_date | L60: =D60&"("&E60&")," -> VARCHAR(16), | N60: ="COMMENT ON COLUMN "&$K$3&"."&$K60&" IS '"&C60&"';" -> COMMENT ON COLUMN mars_product.additional_purchase_validity_start_date IS '買い増し有効開始日'; | R60: additional_purchase_validity_start_date VARCHAR(16),
B61: 53 | C61: 買い増し有効終了日 | D61: VARCHAR | E61: 16 | F61: － | K61: additional_purchase_validity_end_date | L61: =D61&"("&E61&")," -> VARCHAR(16), | N61: ="COMMENT ON COLUMN "&$K$3&"."&$K61&" IS '"&C61&"';" -> COMMENT ON COLUMN mars_product.additional_purchase_validity_end_date IS '買い増し有効終了日'; | R61: additional_purchase_validity_end_date VARCHAR(16),
B62: 54 | C62: cic商品コード | D62: VARCHAR | E62: 6 | F62: － | K62: cic_product_code | L62: =D62&"("&E62&")," -> VARCHAR(6), | N62: ="COMMENT ON COLUMN "&$K$3&"."&$K62&" IS '"&C62&"';" -> COMMENT ON COLUMN mars_product.cic_product_code IS 'cic商品コード'; | R62: cic_product_code VARCHAR(6),
B63: 55 | C63: 生活必需品外フラグ | D63: VARCHAR | E63: 2 | F63: － | K63: non_essential_flag | L63: =D63&"("&E63&")," -> VARCHAR(2), | N63: ="COMMENT ON COLUMN "&$K$3&"."&$K63&" IS '"&C63&"';" -> COMMENT ON COLUMN mars_product.non_essential_flag IS '生活必需品外フラグ'; | R63: non_essential_flag VARCHAR(2),
B64: 56 | C64: サービス世代id | D64: VARCHAR | E64: 4 | F64: － | K64: service_generation_id | L64: =D64&"("&E64&")," -> VARCHAR(4), | N64: ="COMMENT ON COLUMN "&$K$3&"."&$K64&" IS '"&C64&"';" -> COMMENT ON COLUMN mars_product.service_generation_id IS 'サービス世代id'; | R64: service_generation_id VARCHAR(4),
B65: 57 | C65: サービス世代正式名称 | D65: VARCHAR | E65: 240 | F65: － | K65: service_generation_official_name | L65: =D65&"("&E65&")," -> VARCHAR(240), | N65: ="COMMENT ON COLUMN "&$K$3&"."&$K65&" IS '"&C65&"';" -> COMMENT ON COLUMN mars_product.service_generation_official_name IS 'サービス世代正式名称'; | R65: service_generation_official_name VARCHAR(240),
B66: 58 | C66: 容量 | D66: VARCHAR | E66: 20 | F66: － | K66: capacity | L66: =D66&"("&E66&")," -> VARCHAR(20), | N66: ="COMMENT ON COLUMN "&$K$3&"."&$K66&" IS '"&C66&"';" -> COMMENT ON COLUMN mars_product.capacity IS '容量'; | R66: capacity VARCHAR(20),
B67: 59 | C67: 割賦審査上限chk対象flg | D67: VARCHAR | E67: 2 | F67: － | K67: installment_review_limit_chk_target_flg | L67: =D67&"("&E67&")," -> VARCHAR(2), | N67: ="COMMENT ON COLUMN "&$K$3&"."&$K67&" IS '"&C67&"';" -> COMMENT ON COLUMN mars_product.installment_review_limit_chk_target_flg IS '割賦審査上限chk対象flg'; | R67: installment_review_limit_chk_target_flg VARCHAR(2),
B68: 60 | C68: opt品割賦販売適用flg | D68: VARCHAR | E68: 2 | F68: － | K68: opt_installment_sales_applicable_flg | L68: =D68&"("&E68&")," -> VARCHAR(2), | N68: ="COMMENT ON COLUMN "&$K$3&"."&$K68&" IS '"&C68&"';" -> COMMENT ON COLUMN mars_product.opt_installment_sales_applicable_flg IS 'opt品割賦販売適用flg'; | R68: opt_installment_sales_applicable_flg VARCHAR(2),
B69: 61 | C69: opt品割賦販売適用from | D69: VARCHAR | E69: 16 | F69: － | K69: opt_installment_sales_applicable_from | L69: =D69&"("&E69&")," -> VARCHAR(16), | N69: ="COMMENT ON COLUMN "&$K$3&"."&$K69&" IS '"&C69&"';" -> COMMENT ON COLUMN mars_product.opt_installment_sales_applicable_from IS 'opt品割賦販売適用from'; | R69: opt_installment_sales_applicable_from VARCHAR(16),
B70: 62 | C70: 売価 | D70: DECIMAL | E70: 10,0 | F70: － | K70: sales_price | L70: =D70&"("&E70&")," -> DECIMAL(10,0), | N70: ="COMMENT ON COLUMN "&$K$3&"."&$K70&" IS '"&C70&"';" -> COMMENT ON COLUMN mars_product.sales_price IS '売価'; | R70: sales_price DECIMAL(10,0),
B71: 63 | C71: 端末区分 | D71: VARCHAR | E71: 2 | F71: － | K71: device_category | L71: =D71&"("&E71&")," -> VARCHAR(2), | N71: ="COMMENT ON COLUMN "&$K$3&"."&$K71&" IS '"&C71&"';" -> COMMENT ON COLUMN mars_product.device_category IS '端末区分'; | R71: device_category VARCHAR(2),
B72: 64 | C72: 端末区分正式名称 | D72: VARCHAR | E72: 1200 | F72: － | K72: device_category_official_name | L72: =D72&"("&E72&")," -> VARCHAR(1200), | N72: ="COMMENT ON COLUMN "&$K$3&"."&$K72&" IS '"&C72&"';" -> COMMENT ON COLUMN mars_product.device_category_official_name IS '端末区分正式名称'; | R72: device_category_official_name VARCHAR(1200),
B73: 65 | C73: 大分類 | D73: VARCHAR | E73: 4 | F73: － | K73: major_category | L73: =D73&"("&E73&")," -> VARCHAR(4), | N73: ="COMMENT ON COLUMN "&$K$3&"."&$K73&" IS '"&C73&"';" -> COMMENT ON COLUMN mars_product.major_category IS '大分類'; | R73: major_category VARCHAR(4),
B74: 66 | C74: 大分類正式名称 | D74: VARCHAR | E74: 1200 | F74: － | K74: major_category_official_name | L74: =D74&"("&E74&")," -> VARCHAR(1200), | N74: ="COMMENT ON COLUMN "&$K$3&"."&$K74&" IS '"&C74&"';" -> COMMENT ON COLUMN mars_product.major_category_official_name IS '大分類正式名称'; | R74: major_category_official_name VARCHAR(1200),
B75: 67 | C75: 中分類 | D75: VARCHAR | E75: 4 | F75: － | K75: middle_category | L75: =D75&"("&E75&")," -> VARCHAR(4), | N75: ="COMMENT ON COLUMN "&$K$3&"."&$K75&" IS '"&C75&"';" -> COMMENT ON COLUMN mars_product.middle_category IS '中分類'; | R75: middle_category VARCHAR(4),
B76: 68 | C76: 中分類正式名称 | D76: VARCHAR | E76: 1200 | F76: － | K76: middle_category_official_name | L76: =D76&"("&E76&")," -> VARCHAR(1200), | N76: ="COMMENT ON COLUMN "&$K$3&"."&$K76&" IS '"&C76&"';" -> COMMENT ON COLUMN mars_product.middle_category_official_name IS '中分類正式名称'; | R76: middle_category_official_name VARCHAR(1200),
B77: 69 | C77: 小分類 | D77: VARCHAR | E77: 4 | F77: － | K77: minor_category | L77: =D77&"("&E77&")," -> VARCHAR(4), | N77: ="COMMENT ON COLUMN "&$K$3&"."&$K77&" IS '"&C77&"';" -> COMMENT ON COLUMN mars_product.minor_category IS '小分類'; | R77: minor_category VARCHAR(4),
B78: 70 | C78: 小分類正式名称 | D78: VARCHAR | E78: 1200 | F78: － | K78: minor_category_official_name | L78: =D78&"("&E78&")," -> VARCHAR(1200), | N78: ="COMMENT ON COLUMN "&$K$3&"."&$K78&" IS '"&C78&"';" -> COMMENT ON COLUMN mars_product.minor_category_official_name IS '小分類正式名称'; | R78: minor_category_official_name VARCHAR(1200),
B79: 71 | C79: 機能フラグ | D79: VARCHAR | E79: 100 | F79: － | K79: feature_flag | L79: =D79&"("&E79&")," -> VARCHAR(100), | N79: ="COMMENT ON COLUMN "&$K$3&"."&$K79&" IS '"&C79&"';" -> COMMENT ON COLUMN mars_product.feature_flag IS '機能フラグ'; | R79: feature_flag VARCHAR(100),
B80: 72 | C80: バンドルプラン識別id | D80: VARCHAR | E80: 20 | F80: － | K80: bundle_plan_identification_id | L80: =D80&"("&E80&")," -> VARCHAR(20), | N80: ="COMMENT ON COLUMN "&$K$3&"."&$K80&" IS '"&C80&"';" -> COMMENT ON COLUMN mars_product.bundle_plan_identification_id IS 'バンドルプラン識別id'; | R80: bundle_plan_identification_id VARCHAR(20),
B81: 73 | C81: バンドルプランnm | D81: VARCHAR | E81: 1200 | F81: － | K81: bundle_plan_nm | L81: =D81&"("&E81&")," -> VARCHAR(1200), | N81: ="COMMENT ON COLUMN "&$K$3&"."&$K81&" IS '"&C81&"';" -> COMMENT ON COLUMN mars_product.bundle_plan_nm IS 'バンドルプランnm'; | R81: bundle_plan_nm VARCHAR(1200),
B82: 74 | C82: チャージ額 | D82: DECIMAL | E82: 10,0 | F82: － | K82: charge_amount | L82: =D82&"("&E82&")," -> DECIMAL(10,0), | N82: ="COMMENT ON COLUMN "&$K$3&"."&$K82&" IS '"&C82&"';" -> COMMENT ON COLUMN mars_product.charge_amount IS 'チャージ額'; | R82: charge_amount DECIMAL(10,0),
B83: 75 | C83: ユニバーサル使用料 | D83: DECIMAL | E83: 10,0 | F83: － | K83: uni_universal_usage_fee | L83: =D83&"("&E83&")," -> DECIMAL(10,0), | N83: ="COMMENT ON COLUMN "&$K$3&"."&$K83&" IS '"&C83&"';" -> COMMENT ON COLUMN mars_product.uni_universal_usage_fee IS 'ユニバーサル使用料'; | R83: uni_universal_usage_fee DECIMAL(10,0),
B84: 76 | C84: 利用有効期間 | D84: DECIMAL | E84: 10,0 | F84: － | K84: validity_period | L84: =D84&"("&E84&")," -> DECIMAL(10,0), | N84: ="COMMENT ON COLUMN "&$K$3&"."&$K84&" IS '"&C84&"';" -> COMMENT ON COLUMN mars_product.validity_period IS '利用有効期間'; | R84: validity_period DECIMAL(10,0),
B85: 77 | C85: 物流商品コード | D85: VARCHAR | E85: 30 | F85: － | K85: logistics_product_code | L85: =D85&"("&E85&")," -> VARCHAR(30), | N85: ="COMMENT ON COLUMN "&$K$3&"."&$K85&" IS '"&C85&"';" -> COMMENT ON COLUMN mars_product.logistics_product_code IS '物流商品コード'; | R85: logistics_product_code VARCHAR(30),
B86: 78 | C86: 数量金額管理区分 | D86: DECIMAL | E86: 10,0 | F86: － | K86: quantity_amount_classification | L86: =D86&"("&E86&")," -> DECIMAL(10,0), | N86: ="COMMENT ON COLUMN "&$K$3&"."&$K86&" IS '"&C86&"';" -> COMMENT ON COLUMN mars_product.quantity_amount_classification IS '数量金額管理区分'; | R86: quantity_amount_classification DECIMAL(10,0),
B87: 79 | C87: 商品税分類コード | D87: DECIMAL | E87: 10,0 | F87: － | K87: product_tax_classification_code | L87: =D87&"("&E87&")," -> DECIMAL(10,0), | N87: ="COMMENT ON COLUMN "&$K$3&"."&$K87&" IS '"&C87&"';" -> COMMENT ON COLUMN mars_product.product_tax_classification_code IS '商品税分類コード'; | R87: product_tax_classification_code DECIMAL(10,0),
B88: 80 | C88: 物流商品税分類 | D88: VARCHAR | E88: 2 | F88: － | K88: logistics_product_tax_classification | L88: =D88&"("&E88&")," -> VARCHAR(2), | N88: ="COMMENT ON COLUMN "&$K$3&"."&$K88&" IS '"&C88&"';" -> COMMENT ON COLUMN mars_product.logistics_product_tax_classification IS '物流商品税分類'; | R88: logistics_product_tax_classification VARCHAR(2),
B89: 81 | C89: 物流基本単位数量 | D89: VARCHAR | E89: 40 | F89: － | K89: logistics_base_unit_quantity | L89: =D89&"("&E89&")," -> VARCHAR(40), | N89: ="COMMENT ON COLUMN "&$K$3&"."&$K89&" IS '"&C89&"';" -> COMMENT ON COLUMN mars_product.logistics_base_unit_quantity IS '物流基本単位数量'; | R89: logistics_base_unit_quantity VARCHAR(40),
B90: 82 | C90: 標準入数 | D90: DECIMAL | E90: 13,3 | F90: － | K90: standard_quantity | L90: =D90&"("&E90&")," -> DECIMAL(13,3), | N90: ="COMMENT ON COLUMN "&$K$3&"."&$K90&" IS '"&C90&"';" -> COMMENT ON COLUMN mars_product.standard_quantity IS '標準入数'; | R90: standard_quantity DECIMAL(13,3),
B91: 83 | C91: 出荷時入数 | D91: DECIMAL | E91: 10,0 | F91: － | K91: shipping_quantity | L91: =D91&"("&E91&")," -> DECIMAL(10,0), | N91: ="COMMENT ON COLUMN "&$K$3&"."&$K91&" IS '"&C91&"';" -> COMMENT ON COLUMN mars_product.shipping_quantity IS '出荷時入数'; | R91: shipping_quantity DECIMAL(10,0),
B92: 84 | C92: 個装箱サイズ_縦 | D92: DECIMAL | E92: 10,0 | F92: － | K92: individual_box_size_length | L92: =D92&"("&E92&")," -> DECIMAL(10,0), | N92: ="COMMENT ON COLUMN "&$K$3&"."&$K92&" IS '"&C92&"';" -> COMMENT ON COLUMN mars_product.individual_box_size_length IS '個装箱サイズ_縦'; | R92: individual_box_size_length DECIMAL(10,0),
B93: 85 | C93: 個装箱サイズ_横 | D93: DECIMAL | E93: 10,0 | F93: － | K93: individual_box_size_width | L93: =D93&"("&E93&")," -> DECIMAL(10,0), | N93: ="COMMENT ON COLUMN "&$K$3&"."&$K93&" IS '"&C93&"';" -> COMMENT ON COLUMN mars_product.individual_box_size_width IS '個装箱サイズ_横'; | R93: individual_box_size_width DECIMAL(10,0),
B94: 86 | C94: 個装箱サイズ_高さ | D94: DECIMAL | E94: 10,0 | F94: － | K94: individual_box_size_height | L94: =D94&"("&E94&")," -> DECIMAL(10,0), | N94: ="COMMENT ON COLUMN "&$K$3&"."&$K94&" IS '"&C94&"';" -> COMMENT ON COLUMN mars_product.individual_box_size_height IS '個装箱サイズ_高さ'; | R94: individual_box_size_height DECIMAL(10,0),
B95: 87 | C95: 梱包財_紙重量 | D95: DECIMAL | E95: 10,0 | F95: － | K95: paper_packaging_material_weight | L95: =D95&"("&E95&")," -> DECIMAL(10,0), | N95: ="COMMENT ON COLUMN "&$K$3&"."&$K95&" IS '"&C95&"';" -> COMMENT ON COLUMN mars_product.paper_packaging_material_weight IS '梱包財_紙重量'; | R95: paper_packaging_material_weight DECIMAL(10,0),
B96: 88 | C96: 梱包財_プラ重量 | D96: DECIMAL | E96: 10,0 | F96: － | K96: plastic_packaging_material_weight | L96: =D96&"("&E96&")," -> DECIMAL(10,0), | N96: ="COMMENT ON COLUMN "&$K$3&"."&$K96&" IS '"&C96&"';" -> COMMENT ON COLUMN mars_product.plastic_packaging_material_weight IS '梱包財_プラ重量'; | R96: plastic_packaging_material_weight DECIMAL(10,0),
B97: 89 | C97: 商品重量 | D97: DECIMAL | E97: 10,0 | F97: － | K97: product_weight | L97: =D97&"("&E97&")," -> DECIMAL(10,0), | N97: ="COMMENT ON COLUMN "&$K$3&"."&$K97&" IS '"&C97&"';" -> COMMENT ON COLUMN mars_product.product_weight IS '商品重量'; | R97: product_weight DECIMAL(10,0),
B98: 90 | C98: パレット積み付け数 | D98: DECIMAL | E98: 10,0 | F98: － | K98: number_of_pallets | L98: =D98&"("&E98&")," -> DECIMAL(10,0), | N98: ="COMMENT ON COLUMN "&$K$3&"."&$K98&" IS '"&C98&"';" -> COMMENT ON COLUMN mars_product.number_of_pallets IS 'パレット積み付け数'; | R98: number_of_pallets DECIMAL(10,0),
B99: 91 | C99: 梱包仕様等 | D99: DECIMAL | E99: 10,0 | F99: － | K99: packaging_specifications_etc | L99: =D99&"("&E99&")," -> DECIMAL(10,0), | N99: ="COMMENT ON COLUMN "&$K$3&"."&$K99&" IS '"&C99&"';" -> COMMENT ON COLUMN mars_product.packaging_specifications_etc IS '梱包仕様等'; | R99: packaging_specifications_etc DECIMAL(10,0),
B100: 92 | C100: mrp管理者コード | D100: VARCHAR | E100: 6 | F100: － | K100: mrp_administrator_code | L100: =D100&"("&E100&")," -> VARCHAR(6), | N100: ="COMMENT ON COLUMN "&$K$3&"."&$K100&" IS '"&C100&"';" -> COMMENT ON COLUMN mars_product.mrp_administrator_code IS 'mrp管理者コード'; | R100: mrp_administrator_code VARCHAR(6),
B101: 93 | C101: 変換代表フラグ | D101: VARCHAR | E101: 2 | F101: － | K101: conversion_representative_flag | L101: =D101&"("&E101&")," -> VARCHAR(2), | N101: ="COMMENT ON COLUMN "&$K$3&"."&$K101&" IS '"&C101&"';" -> COMMENT ON COLUMN mars_product.conversion_representative_flag IS '変換代表フラグ'; | R101: conversion_representative_flag VARCHAR(2),
B102: 94 | C102: 検品用商品タイプcd | D102: VARCHAR | E102: 6 | F102: － | K102: product_type_for_inspection_cd | L102: =D102&"("&E102&")," -> VARCHAR(6), | N102: ="COMMENT ON COLUMN "&$K$3&"."&$K102&" IS '"&C102&"';" -> COMMENT ON COLUMN mars_product.product_type_for_inspection_cd IS '検品用商品タイプcd'; | R102: product_type_for_inspection_cd VARCHAR(6),
B103: 95 | C103: 検品用商品タイプnm | D103: VARCHAR | E103: 1200 | F103: － | K103: product_type_for_inspection_nm | L103: =D103&"("&E103&")," -> VARCHAR(1200), | N103: ="COMMENT ON COLUMN "&$K$3&"."&$K103&" IS '"&C103&"';" -> COMMENT ON COLUMN mars_product.product_type_for_inspection_nm IS '検品用商品タイプnm'; | R103: product_type_for_inspection_nm VARCHAR(1200),
B104: 96 | C104: model_id | D104: DECIMAL | E104: 10,0 | F104: － | K104: model_id | L104: =D104&"("&E104&")," -> DECIMAL(10,0), | N104: ="COMMENT ON COLUMN "&$K$3&"."&$K104&" IS '"&C104&"';" -> COMMENT ON COLUMN mars_product.model_id IS 'model_id'; | R104: model_id DECIMAL(10,0),
B105: 97 | C105: imsiタイプ | D105: VARCHAR | E105: 4 | F105: － | K105: imsi_type | L105: =D105&"("&E105&")," -> VARCHAR(4), | N105: ="COMMENT ON COLUMN "&$K$3&"."&$K105&" IS '"&C105&"';" -> COMMENT ON COLUMN mars_product.imsi_type IS 'imsiタイプ'; | R105: imsi_type VARCHAR(4),
B106: 98 | C106: imsiタイプ正式名称 | D106: VARCHAR | E106: 1200 | F106: － | K106: imsi_type_official_name | L106: =D106&"("&E106&")," -> VARCHAR(1200), | N106: ="COMMENT ON COLUMN "&$K$3&"."&$K106&" IS '"&C106&"';" -> COMMENT ON COLUMN mars_product.imsi_type_official_name IS 'imsiタイプ正式名称'; | R106: imsi_type_official_name VARCHAR(1200),
K107: ="CONSTRAINT pk_"&K3&" PRIMARY KEY (id));" -> CONSTRAINT pk_mars_product PRIMARY KEY (id)); | R107: CONSTRAINT pk_mars_product PRIMARY KEY (id));
R108: COMMENT ON TABLE mars_product IS 'ビュー';
R109: COMMENT ON COLUMN mars_product.id IS 'id';
R110: COMMENT ON COLUMN mars_product.product_code IS '商品コード';
R111: COMMENT ON COLUMN mars_product.validity_start_date IS '有効開始日';
R112: COMMENT ON COLUMN mars_product.validity_start_time IS '有効開始時間';
R113: COMMENT ON COLUMN mars_product.validity_end_date IS '有効終了日';
R114: COMMENT ON COLUMN mars_product.validity_end_time IS '有効終了時間';
R115: COMMENT ON COLUMN mars_product.area_code IS '地域コード';
R116: COMMENT ON COLUMN mars_product.product_official_name IS '商品正式名称';
R117: COMMENT ON COLUMN mars_product.product_name_in_kana IS '商品カナ名称';
R118: COMMENT ON COLUMN mars_product.product_name_in_english IS '商品英語名称';
R119: COMMENT ON COLUMN mars_product.product_abbreviation IS '商品略称';
... R207: COMMENT ON COLUMN mars_product.imsi_type_official_name IS 'imsiタイプ正式名称';

Sheet (SUMMIT)決裁_料金決裁
G2: 種別 | H2: DWH公開名 | I2: 旧DWH公開名 | J2: 統合テーブルID | K2: スキーマ
G3: ビュー | H3: b_hjn_smt_問い合わせツール_決裁_料金決裁 | J3: V004576 | K3: user_l2_prvl | L3: summit_fee_settlement
G4: データ概要：
G5: （問合せツール）営業決裁
K6: ="DROP TABLE IF EXISTS "&L3&" CASCADE;" -> DROP TABLE IF EXISTS summit_fee_settlement CASCADE; | R6: DROP TABLE IF EXISTS summit_fee_settlement CASCADE;
K7: ="CREATE TABLE IF NOT EXISTS "&L3&" (" -> CREATE TABLE IF NOT EXISTS summit_fee_settlement ( | N7: ="COMMENT ON TABLE "&L3&" IS '"&H3&"';" -> COMMENT ON TABLE summit_fee_settlement IS 'b_hjn_smt_問い合わせツール_決裁_料金決裁'; | R7: CREATE TABLE IF NOT EXISTS summit_fee_settlement (
A8: pk | B8: SEQ | C8: 項目名 | D8: TYPE | E8: 桁 | F8: 仮名化 | G8: 項目説明およびリスト値 | H8: コードリファレンスリンク | I8: 備考 | J8: 更新日 | K8: id BIGINT GENERATED BY DEFAULT AS IDENTITY, | N8: ="COMMENT ON COLUMN "&$L$3&".id IS 'id';" -> COMMENT ON COLUMN summit_fee_settlement.id IS 'id'; | R8: id BIGINT GENERATED BY DEFAULT AS IDENTITY,
B9: 1 | C9: 決裁番号 | D9: VARCHAR | E9: 48 | F9: － | K9: approval_number | L9: =D9&"("&E9&")," -> VARCHAR(48), | N9: ="COMMENT ON COLUMN "&$L$3&"."&$K9&" IS '"&C9&"';" -> COMMENT ON COLUMN summit_fee_settlement.approval_number IS '決裁番号'; | R9: approval_number VARCHAR(48),
B10: 2 | C10: ステータス名 | D10: VARCHAR | E10: 270 | F10: － | K10: status_name | L10: =D10&"("&E10&")," -> VARCHAR(270), | N10: ="COMMENT ON COLUMN "&$L$3&"."&$K10&" IS '"&C10&"';" -> COMMENT ON COLUMN summit_fee_settlement.status_name IS 'ステータス名'; | R10: status_name VARCHAR(270),
B11: 3 | C11: ノード名 | D11: VARCHAR | E11: 270 | F11: － | K11: node_name | L11: =D11&"("&E11&")," -> VARCHAR(270), | N11: ="COMMENT ON COLUMN "&$L$3&"."&$K11&" IS '"&C11&"';" -> COMMENT ON COLUMN summit_fee_settlement.node_name IS 'ノード名'; | R11: node_name VARCHAR(270),
B12: 4 | C12: 起案日時 | D12: VARCHAR | E12: 69 | F12: － | K12: date_and_time_of_proposal | L12: =D12&"("&E12&")," -> VARCHAR(69), | N12: ="COMMENT ON COLUMN "&$L$3&"."&$K12&" IS '"&C12&"';" -> COMMENT ON COLUMN summit_fee_settlement.date_and_time_of_proposal IS '起案日時'; | R12: date_and_time_of_proposal VARCHAR(69),
B13: 5 | C13: 最終処理日時 | D13: VARCHAR | E13: 69 | F13: － | K13: date_and_time_of_final_processing | L13: =D13&"("&E13&")," -> VARCHAR(69), | N13: ="COMMENT ON COLUMN "&$L$3&"."&$K13&" IS '"&C13&"';" -> COMMENT ON COLUMN summit_fee_settlement.date_and_time_of_final_processing IS '最終処理日時'; | R13: date_and_time_of_final_processing VARCHAR(69),
B14: 6 | C14: 決裁日 | D14: VARCHAR | E14: 69 | F14: － | K14: approval_date | L14: =D14&"("&E14&")," -> VARCHAR(69), | N14: ="COMMENT ON COLUMN "&$L$3&"."&$K14&" IS '"&C14&"';" -> COMMENT ON COLUMN summit_fee_settlement.approval_date IS '決裁日'; | R14: approval_date VARCHAR(69),
B15: 7 | C15: 決裁種別 | D15: VARCHAR | E15: 2304 | F15: － | K15: approval_type | L15: =D15&"("&E15&")," -> VARCHAR(2304), | N15: ="COMMENT ON COLUMN "&$L$3&"."&$K15&" IS '"&C15&"';" -> COMMENT ON COLUMN summit_fee_settlement.approval_type IS '決裁種別'; | R15: approval_type VARCHAR(2304),
B16: 8 | C16: 事業区分 | D16: VARCHAR | E16: 2304 | F16: － | K16: business_category | L16: =D16&"("&E16&")," -> VARCHAR(2304), | N16: ="COMMENT ON COLUMN "&$L$3&"."&$K16&" IS '"&C16&"';" -> COMMENT ON COLUMN summit_fee_settlement.business_category IS '事業区分'; | R16: business_category VARCHAR(2304),
B17: 9 | C17: 決裁内容 | D17: VARCHAR | E17: 2304 | F17: － | K17: approval_details | L17: =D17&"("&E17&")," -> VARCHAR(2304), | N17: ="COMMENT ON COLUMN "&$L$3&"."&$K17&" IS '"&C17&"';" -> COMMENT ON COLUMN summit_fee_settlement.approval_details IS '決裁内容'; | R17: approval_details VARCHAR(2304),
B18: 10 | C18: 決裁件名 | D18: VARCHAR | E18: 768 | F18: － | K18: approval_subject | L18: =D18&"("&E18&")," -> VARCHAR(768), | N18: ="COMMENT ON COLUMN "&$L$3&"."&$K18&" IS '"&C18&"';" -> COMMENT ON COLUMN summit_fee_settlement.approval_subject IS '決裁件名'; | R18: approval_subject VARCHAR(768),
B19: 11 | C19: 案件概要_要旨記述1 | D19: VARCHAR | E19: 12000 | F19: － | K19: project_summary_1 | L19: =D19&"("&E19&")," -> VARCHAR(12000), | N19: ="COMMENT ON COLUMN "&$L$3&"."&$K19&" IS '"&C19&"';" -> COMMENT ON COLUMN summit_fee_settlement.project_summary_1 IS '案件概要_要旨記述1'; | R19: project_summary_1 VARCHAR(12000),
B20: 12 | C20: 案件概要_要旨記述2 | D20: VARCHAR | E20: 12000 | F20: － | K20: project_summary_2 | L20: =D20&"("&E20&")," -> VARCHAR(12000), | N20: ="COMMENT ON COLUMN "&$L$3&"."&$K20&" IS '"&C20&"';" -> COMMENT ON COLUMN summit_fee_settlement.project_summary_2 IS '案件概要_要旨記述2'; | R20: project_summary_2 VARCHAR(12000),
... B35: 27 | C35: ステータスid | D35: VARCHAR | E35: 48 | F35: － | K35: status_id | L35: =D35&"("&E35&")," -> VARCHAR(48), | N35: ="COMMENT ON COLUMN "&$L$3&"."&$K35&" IS '"&C35&"';" -> COMMENT ON COLUMN summit_fee_settlement.status_id IS 'ステータスid'; | R35: status_id VARCHAR(48),
K36: ="CONSTRAINT pk_"&L3&" PRIMARY KEY (id));" -> CONSTRAINT pk_summit_fee_settlement PRIMARY KEY (id)); | R36: CONSTRAINT pk_summit_fee_settlement PRIMARY KEY (id));
R37: COMMENT ON TABLE summit_fee_settlement IS 'b_hjn_smt_問い合わせツール_決裁_料金決裁';
R38: COMMENT ON COLUMN summit_fee_settlement.id IS 'id';
R39: COMMENT ON COLUMN summit_fee_settlement.approval_number IS '決裁番号';
R40: COMMENT ON COLUMN summit_fee_settlement.status_name IS 'ステータス名';
R41: COMMENT ON COLUMN summit_fee_settlement.node_name IS 'ノード名';
R42: COMMENT ON COLUMN summit_fee_settlement.date_and_time_of_proposal IS '起案日時';
R43: COMMENT ON COLUMN summit_fee_settlement.date_and_time_of_final_processing IS '最終処理日時';
R44: COMMENT ON COLUMN summit_fee_settlement.approval_date IS '決裁日';
R45: COMMENT ON COLUMN summit_fee_settlement.approval_type IS '決裁種別';
R46: COMMENT ON COLUMN summit_fee_settlement.business_category IS '事業区分';
R47: COMMENT ON COLUMN summit_fee_settlement.approval_details IS '決裁内容';
R48: COMMENT ON COLUMN summit_fee_settlement.approval_subject IS '決裁件名';
... R65: COMMENT ON COLUMN summit_fee_settlement.status_id IS 'ステータスid';

Sheet (SUMMIT)決裁_提案モバイル
C2: テーブルレイアウト情報の掲載なし
C3: b_hjn_smt_決裁_提案モバイル | K3: summit_approval_proposal_mobile
K7: ="DROP TABLE IF EXISTS "&K3&" CASCADE;" -> DROP TABLE IF EXISTS summit_approval_proposal_mobile CASCADE; | R7: DROP TABLE IF EXISTS summit_approval_proposal_mobile CASCADE;
K8: ="CREATE TABLE IF NOT EXISTS "&K3&" (" -> CREATE TABLE IF NOT EXISTS summit_approval_proposal_mobile ( | N8: ="COMMENT ON TABLE "&K3&" IS '"&C3&"';" -> COMMENT ON TABLE summit_approval_proposal_mobile IS 'b_hjn_smt_決裁_提案モバイル'; | R8: CREATE TABLE IF NOT EXISTS summit_approval_proposal_mobile (
A9: pk | B9: SEQ | C9: 項目名 | D9: TYPE | E9: 桁 | F9: 仮名化 | G9: 項目説明およびリスト値 | H9: コードリファレンスリンク | I9: 備考 | J9: 更新日 | K9: id BIGINT GENERATED BY DEFAULT AS IDENTITY, | N9: ="COMMENT ON COLUMN "&$K$3&".id IS 'id';" -> COMMENT ON COLUMN summit_approval_proposal_mobile.id IS 'id'; | R9: id BIGINT GENERATED BY DEFAULT AS IDENTITY,
C10: 決裁番号 | D10: VARCHAR | E10: 255 | K10: approval_number | L10: =D10&"("&E10&")," -> VARCHAR(255), | N10: ="COMMENT ON COLUMN "&$K$3&"."&$K10&" IS '"&C10&"';" -> COMMENT ON COLUMN summit_approval_proposal_mobile.approval_number IS '決裁番号'; | R10: approval_number VARCHAR(255),
C11: ステータス名 | D11: VARCHAR | E11: 255 | K11: status_name | L11: =D11&"("&E11&")," -> VARCHAR(255), | N11: ="COMMENT ON COLUMN "&$K$3&"."&$K11&" IS '"&C11&"';" -> COMMENT ON COLUMN summit_approval_proposal_mobile.status_name IS 'ステータス名'; | R11: status_name VARCHAR(255),
C12: ノード名 | D12: VARCHAR | E12: 255 | K12: node_name | L12: =D12&"("&E12&")," -> VARCHAR(255), | N12: ="COMMENT ON COLUMN "&$K$3&"."&$K12&" IS '"&C12&"';" -> COMMENT ON COLUMN summit_approval_proposal_mobile.node_name IS 'ノード名'; | R12: node_name VARCHAR(255),
C13: 起案日時 | D13: VARCHAR | E13: 255 | K13: date_and_time_of_proposal | L13: =D13&"("&E13&")," -> VARCHAR(255), | N13: ="COMMENT ON COLUMN "&$K$3&"."&$K13&" IS '"&C13&"';" -> COMMENT ON COLUMN summit_approval_proposal_mobile.date_and_time_of_proposal IS '起案日時'; | R13: date_and_time_of_proposal VARCHAR(255),
C14: 最終処理日時 | D14: VARCHAR | E14: 255 | K14: final_processing_date | L14: =D14&"("&E14&")," -> VARCHAR(255), | N14: ="COMMENT ON COLUMN "&$K$3&"."&$K14&" IS '"&C14&"';" -> COMMENT ON COLUMN summit_approval_proposal_mobile.final_processing_date IS '最終処理日時'; | R14: final_processing_date VARCHAR(255),
C15: 決裁日 | D15: VARCHAR | E15: 255 | K15: approval_date | L15: =D15&"("&E15&")," -> VARCHAR(255), | N15: ="COMMENT ON COLUMN "&$K$3&"."&$K15&" IS '"&C15&"';" -> COMMENT ON COLUMN summit_approval_proposal_mobile.approval_date IS '決裁日'; | R15: approval_date VARCHAR(255),
C16: 決裁種別 | D16: VARCHAR | E16: 255 | K16: approval_type | L16: =D16&"("&E16&")," -> VARCHAR(255), | N16: ="COMMENT ON COLUMN "&$K$3&"."&$K16&" IS '"&C16&"';" -> COMMENT ON COLUMN summit_approval_proposal_mobile.approval_type IS '決裁種別'; | R16: approval_type VARCHAR(255),
C17: 事業区分 | D17: VARCHAR | E17: 255 | K17: business_category | L17: =D17&"("&E17&")," -> VARCHAR(255), | N17: ="COMMENT ON COLUMN "&$K$3&"."&$K17&" IS '"&C17&"';" -> COMMENT ON COLUMN summit_approval_proposal_mobile.business_category IS '事業区分'; | R17: business_category VARCHAR(255),
C18: 決裁内容 | D18: VARCHAR | E18: 255 | K18: approval_content | L18: =D18&"("&E18&")," -> VARCHAR(255), | N18: ="COMMENT ON COLUMN "&$K$3&"."&$K18&" IS '"&C18&"';" -> COMMENT ON COLUMN summit_approval_proposal_mobile.approval_content IS '決裁内容'; | R18: approval_content VARCHAR(255),
C19: 決裁件名 | D19: VARCHAR | E19: 255 | K19: approval_subject | L19: =D19&"("&E19&")," -> VARCHAR(255), | N19: ="COMMENT ON COLUMN "&$K$3&"."&$K19&" IS '"&C19&"';" -> COMMENT ON COLUMN summit_approval_proposal_mobile.approval_subject IS '決裁件名'; | R19: approval_subject VARCHAR(255),
C20: 競合キャリア名 | D20: VARCHAR | E20: 255 | K20: competing_carrier_name | L20: =D20&"("&E20&")," -> VARCHAR(255), | N20: ="COMMENT ON COLUMN "&$K$3&"."&$K20&" IS '"&C20&"';" -> COMMENT ON COLUMN summit_approval_proposal_mobile.competing_carrier_name IS '競合キャリア名'; | R20: competing_carrier_name VARCHAR(255),
C21: 競合キャリア提供条件 | D21: VARCHAR | E21: 255 | K21: competing_carrier_provision_conditions | L21: =D21&"("&E21&")," -> VARCHAR(255), | N21: ="COMMENT ON COLUMN "&$K$3&"."&$K21&" IS '"&C21&"';" -> COMMENT ON COLUMN summit_approval_proposal_mobile.competing_carrier_provision_conditions IS '競合キャリア提供条件'; | R21: competing_carrier_provision_conditions VARCHAR(255),
... C220: 目的_理由_効果9 | D220: VARCHAR | E220: 255 | K220: purpose_reason_effect_9 | L220: =D220&"("&E220&")," -> VARCHAR(255), | N220: ="COMMENT ON COLUMN "&$K$3&"."&$K220&" IS '"&C220&"';" -> COMMENT ON COLUMN summit_approval_proposal_mobile.purpose_reason_effect_9 IS '目的_理由_効果9'; | R220: purpose_reason_effect_9 VARCHAR(255),
K221: ="CONSTRAINT pk_"&K3&" PRIMARY KEY (id));" -> CONSTRAINT pk_summit_approval_proposal_mobile PRIMARY KEY (id)); | R221: CONSTRAINT pk_summit_approval_proposal_mobile PRIMARY KEY (id));
R222: COMMENT ON TABLE summit_approval_proposal_mobile IS 'b_hjn_smt_決裁_提案モバイル';
R223: COMMENT ON COLUMN summit_approval_proposal_mobile.id IS 'id';
R224: COMMENT ON COLUMN summit_approval_proposal_mobile.approval_number IS '決裁番号';
R225: COMMENT ON COLUMN summit_approval_proposal_mobile.status_name IS 'ステータス名';
R226: COMMENT ON COLUMN summit_approval_proposal_mobile.node_name IS 'ノード名';
R227: COMMENT ON COLUMN summit_approval_proposal_mobile.date_and_time_of_proposal IS '起案日時';
R228: COMMENT ON COLUMN summit_approval_proposal_mobile.final_processing_date IS '最終処理日時';
R229: COMMENT ON COLUMN summit_approval_proposal_mobile.approval_date IS '決裁日';
R230: COMMENT ON COLUMN summit_approval_proposal_mobile.approval_type IS '決裁種別';
R231: COMMENT ON COLUMN summit_approval_proposal_mobile.business_category IS '事業区分';
R232: COMMENT ON COLUMN summit_approval_proposal_mobile.approval_content IS '決裁内容';
R233: COMMENT ON COLUMN summit_approval_proposal_mobile.approval_subject IS '決裁件名';
... R434: COMMENT ON COLUMN summit_approval_proposal_mobile.purpose_reason_effect_9 IS '目的_理由_効果9';

Sheet (SUMMIT)決裁_共通決裁
F2: 種別 | G2: DWH公開名 | H2: 旧DWH公開名 | I2: 統合テーブルID | J2: スキーマ
F3: ビュー | G3: b_hjn_smt_問い合わせツール_決裁_共通決裁 | I3: V004532 | J3: user_l2_prvl | K3: summit_common_approval
F4: データ概要：
F5: （問合せツール）営業決裁
K6: ="DROP TABLE IF EXISTS "&K3&" CASCADE;" -> DROP TABLE IF EXISTS summit_common_approval CASCADE; | R6: DROP TABLE IF EXISTS summit_common_approval CASCADE;
K7: ="CREATE TABLE IF NOT EXISTS "&K3&" (" -> CREATE TABLE IF NOT EXISTS summit_common_approval ( | N7: ="COMMENT ON TABLE "&K3&" IS '"&G3&"';" -> COMMENT ON TABLE summit_common_approval IS 'b_hjn_smt_問い合わせツール_決裁_共通決裁'; | R7: CREATE TABLE IF NOT EXISTS summit_common_approval (
A8: pk | B8: SEQ | C8: 項目名 | D8: TYPE | E8: 桁 | F8: 仮名化 | G8: 項目説明およびリスト値 | H8: コードリファレンスリンク | I8: 備考 | J8: 更新日 | K8: id BIGINT GENERATED BY DEFAULT AS IDENTITY, | N8: ="COMMENT ON COLUMN "&$K$3&".id IS 'id';" -> COMMENT ON COLUMN summit_common_approval.id IS 'id'; | R8: id BIGINT GENERATED BY DEFAULT AS IDENTITY,
B9: 1 | C9: 決裁番号 | D9: VARCHAR | E9: 10 | F9: － | K9: approval_number | L9: =D9&"("&E9&")," -> VARCHAR(10), | N9: ="COMMENT ON COLUMN "&$K$3&"."&$K9&" IS '"&C9&"';" -> COMMENT ON COLUMN summit_common_approval.approval_number IS '決裁番号'; | R9: approval_number VARCHAR(10),
B10: 2 | C10: ステータス名 | D10: VARCHAR | E10: 255 | F10: － | K10: status_name | L10: =D10&"("&E10&")," -> VARCHAR(255), | N10: ="COMMENT ON COLUMN "&$K$3&"."&$K10&" IS '"&C10&"';" -> COMMENT ON COLUMN summit_common_approval.status_name IS 'ステータス名'; | R10: status_name VARCHAR(255),
B11: 3 | C11: ノード名 | D11: VARCHAR | E11: 255 | F11: － | K11: node_name | L11: =D11&"("&E11&")," -> VARCHAR(255), | N11: ="COMMENT ON COLUMN "&$K$3&"."&$K11&" IS '"&C11&"';" -> COMMENT ON COLUMN summit_common_approval.node_name IS 'ノード名'; | R11: node_name VARCHAR(255),
B12: 4 | C12: 起案日時 | D12: VARCHAR | E12: 255 | F12: － | K12: date_and_time_of_proposal | L12: =D12&"("&E12&")," -> VARCHAR(255), | N12: ="COMMENT ON COLUMN "&$K$3&"."&$K12&" IS '"&C12&"';" -> COMMENT ON COLUMN summit_common_approval.date_and_time_of_proposal IS '起案日時'; | R12: date_and_time_of_proposal VARCHAR(255),
B13: 5 | C13: 最終処理日時 | D13: VARCHAR | E13: 69 | F13: － | K13: date_and_time_of_final_processing | L13: =D13&"("&E13&")," -> VARCHAR(69), | N13: ="COMMENT ON COLUMN "&$K$3&"."&$K13&" IS '"&C13&"';" -> COMMENT ON COLUMN summit_common_approval.date_and_time_of_final_processing IS '最終処理日時'; | R13: date_and_time_of_final_processing VARCHAR(69),
B14: 6 | C14: 決裁日 | D14: VARCHAR | E14: 69 | F14: － | K14: approval_date | L14: =D14&"("&E14&")," -> VARCHAR(69), | N14: ="COMMENT ON COLUMN "&$K$3&"."&$K14&" IS '"&C14&"';" -> COMMENT ON COLUMN summit_common_approval.approval_date IS '決裁日'; | R14: approval_date VARCHAR(69),
B15: 7 | C15: 決裁種別 | D15: VARCHAR | E15: 2304 | F15: － | K15: approval_type | L15: =D15&"("&E15&")," -> VARCHAR(2304), | N15: ="COMMENT ON COLUMN "&$K$3&"."&$K15&" IS '"&C15&"';" -> COMMENT ON COLUMN summit_common_approval.approval_type IS '決裁種別'; | R15: approval_type VARCHAR(2304),
B16: 8 | C16: 事業区分 | D16: VARCHAR | E16: 2304 | F16: － | K16: business_category | L16: =D16&"("&E16&")," -> VARCHAR(2304), | N16: ="COMMENT ON COLUMN "&$K$3&"."&$K16&" IS '"&C16&"';" -> COMMENT ON COLUMN summit_common_approval.business_category IS '事業区分'; | R16: business_category VARCHAR(2304),
B17: 9 | C17: 決裁内容 | D17: VARCHAR | E17: 2304 | F17: － | K17: approval_content | L17: =D17&"("&E17&")," -> VARCHAR(2304), | N17: ="COMMENT ON COLUMN "&$K$3&"."&$K17&" IS '"&C17&"';" -> COMMENT ON COLUMN summit_common_approval.approval_content IS '決裁内容'; | R17: approval_content VARCHAR(2304),
B18: 10 | C18: 決裁件名 | D18: VARCHAR | E18: 768 | F18: － | K18: approval_subject | L18: =D18&"("&E18&")," -> VARCHAR(768), | N18: ="COMMENT ON COLUMN "&$K$3&"."&$K18&" IS '"&C18&"';" -> COMMENT ON COLUMN summit_common_approval.approval_subject IS '決裁件名'; | R18: approval_subject VARCHAR(768),
B19: 11 | C19: 案件概要_要旨記述1 | D19: VARCHAR | E19: 12000 | F19: － | K19: project_summary_summary_1 | L19: =D19&"("&E19&")," -> VARCHAR(12000), | N19: ="COMMENT ON COLUMN "&$K$3&"."&$K19&" IS '"&C19&"';" -> COMMENT ON COLUMN summit_common_approval.project_summary_summary_1 IS '案件概要_要旨記述1'; | R19: project_summary_summary_1 VARCHAR(12000),
B20: 12 | C20: 案件概要_要旨記述2 | D20: VARCHAR | E20: 12000 | F20: － | K20: project_summary_summary_2 | L20: =D20&"("&E20&")," -> VARCHAR(12000), | N20: ="COMMENT ON COLUMN "&$K$3&"."&$K20&" IS '"&C20&"';" -> COMMENT ON COLUMN summit_common_approval.project_summary_summary_2 IS '案件概要_要旨記述2'; | R20: project_summary_summary_2 VARCHAR(12000),
... B26: 18 | C26: ステータスid | D26: VARCHAR | E26: 48 | F26: － | K26: status_id | L26: =D26&"("&E26&")," -> VARCHAR(48), | N26: ="COMMENT ON COLUMN "&$K$3&"."&$K26&" IS '"&C26&"';" -> COMMENT ON COLUMN summit_common_approval.status_id IS 'ステータスid'; | R26: status_id VARCHAR(48),
B27: 19 | C27: 目的_理由_効果1 | D27: VARCHAR | E27: 255 | F27: － | G27: [NULL]固定 | K27: purpose_reason_effect_1 | L27: =D27&"("&E27&")," -> VARCHAR(255), | N27: ="COMMENT ON COLUMN "&$K$3&"."&$K27&" IS '"&C27&"';" -> COMMENT ON COLUMN summit_common_approval.purpose_reason_effect_1 IS '目的_理由_効果1'; | R27: purpose_reason_effect_1 VARCHAR(255),
B28: 20 | C28: 目的_理由_効果2 | D28: VARCHAR | E28: 255 | F28: － | G28: [NULL]固定 | K28: purpose_reason_effect_2 | L28: =D28&"("&E28&")," -> VARCHAR(255), | N28: ="COMMENT ON COLUMN "&$K$3&"."&$K28&" IS '"&C28&"';" -> COMMENT ON COLUMN summit_common_approval.purpose_reason_effect_2 IS '目的_理由_効果2'; | R28: purpose_reason_effect_2 VARCHAR(255),
B29: 21 | C29: 目的_理由_効果3 | D29: VARCHAR | E29: 255 | F29: － | G29: [NULL]固定 | K29: purpose_reason_effect_3 | L29: =D29&"("&E29&")," -> VARCHAR(255), | N29: ="COMMENT ON COLUMN "&$K$3&"."&$K29&" IS '"&C29&"';" -> COMMENT ON COLUMN summit_common_approval.purpose_reason_effect_3 IS '目的_理由_効果3'; | R29: purpose_reason_effect_3 VARCHAR(255),
B30: 22 | C30: 目的_理由_効果4 | D30: VARCHAR | E30: 255 | F30: － | G30: [NULL]固定 | K30: purpose_reason_effect_4 | L30: =D30&"("&E30&")," -> VARCHAR(255), | N30: ="COMMENT ON COLUMN "&$K$3&"."&$K30&" IS '"&C30&"';" -> COMMENT ON COLUMN summit_common_approval.purpose_reason_effect_4 IS '目的_理由_効果4'; | R30: purpose_reason_effect_4 VARCHAR(255),
B31: 23 | C31: 目的_理由_効果5 | D31: VARCHAR | E31: 255 | F31: － | G31: [NULL]固定 | K31: purpose_reason_effect_5 | L31: =D31&"("&E31&")," -> VARCHAR(255), | N31: ="COMMENT ON COLUMN "&$K$3&"."&$K31&" IS '"&C31&"';" -> COMMENT ON COLUMN summit_common_approval.purpose_reason_effect_5 IS '目的_理由_効果5'; | R31: purpose_reason_effect_5 VARCHAR(255),
B32: 24 | C32: 目的_理由_効果6 | D32: VARCHAR | E32: 255 | F32: － | G32: [NULL]固定 | K32: purpose_reason_effect_6 | L32: =D32&"("&E32&")," -> VARCHAR(255), | N32: ="COMMENT ON COLUMN "&$K$3&"."&$K32&" IS '"&C32&"';" -> COMMENT ON COLUMN summit_common_approval.purpose_reason_effect_6 IS '目的_理由_効果6'; | R32: purpose_reason_effect_6 VARCHAR(255),
B33: 25 | C33: 目的_理由_効果7 | D33: VARCHAR | E33: 255 | F33: － | G33: [NULL]固定 | K33: purpose_reason_effect_7 | L33: =D33&"("&E33&")," -> VARCHAR(255), | N33: ="COMMENT ON COLUMN "&$K$3&"."&$K33&" IS '"&C33&"';" -> COMMENT ON COLUMN summit_common_approval.purpose_reason_effect_7 IS '目的_理由_効果7'; | R33: purpose_reason_effect_7 VARCHAR(255),
B34: 26 | C34: 目的_理由_効果8 | D34: VARCHAR | E34: 255 | F34: － | G34: [NULL]固定 | K34: purpose_reason_effect_8 | L34: =D34&"("&E34&")," -> VARCHAR(255), | N34: ="COMMENT ON COLUMN "&$K$3&"."&$K34&" IS '"&C34&"';" -> COMMENT ON COLUMN summit_common_approval.purpose_reason_effect_8 IS '目的_理由_効果8'; | R34: purpose_reason_effect_8 VARCHAR(255),
B35: 27 | C35: 目的_理由_効果9 | D35: VARCHAR | E35: 255 | F35: － | G35: [NULL]固定 | K35: purpose_reason_effect_9 | L35: =D35&"("&E35&")," -> VARCHAR(255), | N35: ="COMMENT ON COLUMN "&$K$3&"."&$K35&" IS '"&C35&"';" -> COMMENT ON COLUMN summit_common_approval.purpose_reason_effect_9 IS '目的_理由_効果9'; | R35: purpose_reason_effect_9 VARCHAR(255),
K36: ="CONSTRAINT pk_"&K3&" PRIMARY KEY (id));" -> CONSTRAINT pk_summit_common_approval PRIMARY KEY (id)); | R36: CONSTRAINT pk_summit_common_approval PRIMARY KEY (id));
R37: COMMENT ON TABLE summit_common_approval IS 'b_hjn_smt_問い合わせツール_決裁_共通決裁';
R38: COMMENT ON COLUMN summit_common_approval.id IS 'id';
R39: COMMENT ON COLUMN summit_common_approval.approval_number IS '決裁番号';
R40: COMMENT ON COLUMN summit_common_approval.status_name IS 'ステータス名';
R41: COMMENT ON COLUMN summit_common_approval.node_name IS 'ノード名';
R42: COMMENT ON COLUMN summit_common_approval.date_and_time_of_proposal IS '起案日時';
R43: COMMENT ON COLUMN summit_common_approval.date_and_time_of_final_processing IS '最終処理日時';
R44: COMMENT ON COLUMN summit_common_approval.approval_date IS '決裁日';
R45: COMMENT ON COLUMN summit_common_approval.approval_type IS '決裁種別';
R46: COMMENT ON COLUMN summit_common_approval.business_category IS '事業区分';
R47: COMMENT ON COLUMN summit_common_approval.approval_content IS '決裁内容';
R48: COMMENT ON COLUMN summit_common_approval.approval_subject IS '決裁件名';
... R65: COMMENT ON COLUMN summit_common_approval.purpose_reason_effect_9 IS '目的_理由_効果9';

Sheet (SUMMIT)決裁_基本_補足
G2: 種別 | H2: DWH公開名 | I2: 旧DWH公開名 | J2: 統合テーブルID | K2: スキーマ
G3: ビュー | H3: b_hjn_smt_問い合わせツール_決裁_基本_補足 | J3: V004419 | K3: user_l2_prvl | L3: summit_approval_basic
G4: データ概要：
G5: （問合せツール）営業決裁
K6: ="DROP TABLE IF EXISTS "&L3&" CASCADE;" -> DROP TABLE IF EXISTS summit_approval_basic CASCADE; | R6: DROP TABLE IF EXISTS summit_approval_basic CASCADE;
K7: ="CREATE TABLE IF NOT EXISTS "&L3&" (" -> CREATE TABLE IF NOT EXISTS summit_approval_basic ( | N7: ="COMMENT ON TABLE "&L3&" IS '"&H3&"';" -> COMMENT ON TABLE summit_approval_basic IS 'b_hjn_smt_問い合わせツール_決裁_基本_補足'; | R7: CREATE TABLE IF NOT EXISTS summit_approval_basic (
